Workbook

Sheet README
A1: 36-Month Rolling Financial Analysis
A3: A complete, fictional worked example of a 36 month rolling forecast built the way a cash
A4: system is actually run. It accompanies the article Cash! Who Owns the Forecast? at
A5: https://www.darlison.com/who-owns-the-forecast/
A7: HOW TO READ IT
A8: Columns run NEWEST FIRST. The far end of the plan, December 2028, is at the left, and time
A9: walks right into the past. Every month carries three columns: Actual, Rolling and Approved.
A10: Actual is what happened, and fills in as each month closes. Rolling is the current best
A11: estimate. Approved is the plan, and does not move until the annual reset.
A13: The weekly Scoreboard takes its targets from APPROVED, never from Rolling. Rolling moves
A14: every month, so a forecast drifting downwards would quietly lower the weekly target and hide
A15: the miss the board exists to show you.
... A129: All numbers are fictional.

Sheet Summary
B1: ="FY"&YEAR(K$1) | E1: ="FY"&YEAR(AU$1) | H1: ="FY"&YEAR(CE$1) | K1: =EOMONTH(N$1,1) | N1: =EOMONTH(Q$1,1) | Q1: =EOMONTH(T$1,1) | T1: =EOMONTH(W$1,1) | W1: =EOMONTH(Z$1,1) | Z1: =EOMONTH(AC$1,1) | AC1: =EOMONTH(AF$1,1) | AF1: =EOMONTH(AI$1,1) | AI1: =EOMONTH(AL$1,1) | AL1: =EOMONTH(AO$1,1) | AO1: =EOMONTH(AR$1,1) | AR1: =EOMONTH(AU$1,1) | AU1: =EOMONTH(AX$1,1) | AX1: =EOMONTH(BA$1,1) | BA1: =EOMONTH(BD$1,1) | BD1: =EOMONTH(BG$1,1) | BG1: =EOMONTH(BJ$1,1) | BJ1: =EOMONTH(BM$1,1) | BM1: =EOMONTH(BP$1,1) | BP1: =EOMONTH(BS$1,1) | BS1: =EOMONTH(BV$1,1) | BV1: =EOMONTH(BY$1,1) | BY1: =EOMONTH(CB$1,1) | CB1: =EOMONTH(CE$1,1) | CE1: =EOMONTH(CH$1,1) | CH1: =EOMONTH(CK$1,1) | CK1: =EOMONTH(CN$1,1) | CN1: =EOMONTH(CQ$1,1) | CQ1: =EOMONTH(CT$1,1) | CT1: =EOMONTH(CW$1,1) | CW1: =EOMONTH(CZ$1,1) | CZ1: =EOMONTH(DC$1,1) | DC1: =EOMONTH(DF$1,1) | DF1: =EOMONTH(DI$1,1) | DI1: =EOMONTH(DL$1,1) | DL1: =Finance!$B$61
B2: Actual | C2: Rolling | D2: Approved | E2: Actual | F2: Rolling | G2: Approved | H2: Actual | I2: Rolling | J2: Approved | K2: Actual | L2: Rolling | M2: Approved | N2: Actual | O2: Rolling | P2: Approved | Q2: Actual | R2: Rolling | S2: Approved | T2: Actual | U2: Rolling | V2: Approved | W2: Actual | X2: Rolling | Y2: Approved | Z2: Actual | AA2: Rolling | AB2: Approved | AC2: Actual | AD2: Rolling | AE2: Approved | AF2: Actual | AG2: Rolling | AH2: Approved | AI2: Actual | AJ2: Rolling | AK2: Approved | AL2: Actual | AM2: Rolling | AN2: Approved | AO2: Actual | AP2: Rolling | AQ2: Approved | AR2: Actual | AS2: Rolling | AT2: Approved | AU2: Actual | AV2: Rolling | AW2: Approved | AX2: Actual | AY2: Rolling | AZ2: Approved | BA2: Actual | BB2: Rolling | BC2: Approved | BD2: Actual | BE2: Rolling | BF2: Approved | BG2: Actual | BH2: Rolling | BI2: Approved | BJ2: Actual | BK2: Rolling | BL2: Approved | BM2: Actual | BN2: Rolling | BO2: Approved | BP2: Actual | BQ2: Rolling | BR2: Approved | BS2: Actual | BT2: Rolling | BU2: Approved | BV2: Actual | BW2: Rolling | BX2: Approved | BY2: Actual | BZ2: Rolling | CA2: Approved | CB2: Actual | CC2: Rolling | CD2: Approved | CE2: Actual | CF2: Rolling | CG2: Approved | CH2: Actual | CI2: Rolling | CJ2: Approved | CK2: Actual | CL2: Rolling | CM2: Approved | CN2: Actual | CO2: Rolling | CP2: Approved | CQ2: Actual | CR2: Rolling | CS2: Approved | CT2: Actual | CU2: Rolling | CV2: Approved | CW2: Actual | CX2: Rolling | CY2: Approved | CZ2: Actual | DA2: Rolling | DB2: Approved | DC2: Actual | DD2: Rolling | DE2: Approved | DF2: Actual | DG2: Rolling | DH2: Approved | DI2: Actual | DJ2: Rolling | DK2: Approved | DL2: Actual | DM2: Rolling | DN2: Approved
A3: Opening Recurring Revenue | B3: =IF(AR3<>"",AR3,IF(AO3<>"",AO3,IF(AL3<>"",AL3,IF(AI3<>"",AI3,IF(AF3<>"",AF3,IF(AC3<>"",AC3,IF(Z3<>"",Z3,IF(W3<>"",W3,IF(T3<>"",T3,IF(Q3<>"",Q3,IF(N3<>"",N3,IF(K3<>"",K3,"")))))))))))) | C3: =IF(AS3<>"",AS3,IF(AP3<>"",AP3,IF(AM3<>"",AM3,IF(AJ3<>"",AJ3,IF(AG3<>"",AG3,IF(AD3<>"",AD3,IF(AA3<>"",AA3,IF(X3<>"",X3,IF(U3<>"",U3,IF(R3<>"",R3,IF(O3<>"",O3,IF(L3<>"",L3,"")))))))))))) | D3: =IF(AT3<>"",AT3,IF(AQ3<>"",AQ3,IF(AN3<>"",AN3,IF(AK3<>"",AK3,IF(AH3<>"",AH3,IF(AE3<>"",AE3,IF(AB3<>"",AB3,IF(Y3<>"",Y3,IF(V3<>"",V3,IF(S3<>"",S3,IF(P3<>"",P3,IF(M3<>"",M3,"")))))))))))) | E3: =IF(CB3<>"",CB3,IF(BY3<>"",BY3,IF(BV3<>"",BV3,IF(BS3<>"",BS3,IF(BP3<>"",BP3,IF(BM3<>"",BM3,IF(BJ3<>"",BJ3,IF(BG3<>"",BG3,IF(BD3<>"",BD3,IF(BA3<>"",BA3,IF(AX3<>"",AX3,IF(AU3<>"",AU3,"")))))))))))) | F3: =IF(CC3<>"",CC3,IF(BZ3<>"",BZ3,IF(BW3<>"",BW3,IF(BT3<>"",BT3,IF(BQ3<>"",BQ3,IF(BN3<>"",BN3,IF(BK3<>"",BK3,IF(BH3<>"",BH3,IF(BE3<>"",BE3,IF(BB3<>"",BB3,IF(AY3<>"",AY3,IF(AV3<>"",AV3,"")))))))))))) | G3: =IF(CD3<>"",CD3,IF(CA3<>"",CA3,IF(BX3<>"",BX3,IF(BU3<>"",BU3,IF(BR3<>"",BR3,IF(BO3<>"",BO3,IF(BL3<>"",BL3,IF(BI3<>"",BI3,IF(BF3<>"",BF3,IF(BC3<>"",BC3,IF(AZ3<>"",AZ3,IF(AW3<>"",AW3,"")))))))))))) | H3: =IF(DL3<>"",DL3,IF(DI3<>"",DI3,IF(DF3<>"",DF3,IF(DC3<>"",DC3,IF(CZ3<>"",CZ3,IF(CW3<>"",CW3,IF(CT3<>"",CT3,IF(CQ3<>"",CQ3,IF(CN3<>"",CN3,IF(CK3<>"",CK3,IF(CH3<>"",CH3,IF(CE3<>"",CE3,"")))))))))))) | I3: =IF(DM3<>"",DM3,IF(DJ3<>"",DJ3,IF(DG3<>"",DG3,IF(DD3<>"",DD3,IF(DA3<>"",DA3,IF(CX3<>"",CX3,IF(CU3<>"",CU3,IF(CR3<>"",CR3,IF(CO3<>"",CO3,IF(CL3<>"",CL3,IF(CI3<>"",CI3,IF(CF3<>"",CF3,"")))))))))))) | J3: =IF(DN3<>"",DN3,IF(DK3<>"",DK3,IF(DH3<>"",DH3,IF(DE3<>"",DE3,IF(DB3<>"",DB3,IF(CY3<>"",CY3,IF(CV3<>"",CV3,IF(CS3<>"",CS3,IF(CP3<>"",CP3,IF(CM3<>"",CM3,IF(CJ3<>"",CJ3,IF(CG3<>"",CG3,"")))))))))))) | K3: =IF(COUNT('Summary'!N6)=1,'Summary'!N6,"") | L3: ='Summary'!O6 | M3: ='Summary'!P6 | N3: =IF(COUNT('Summary'!Q6)=1,'Summary'!Q6,"") | O3: ='Summary'!R6 | P3: ='Summary'!S6 | Q3: =IF(COUNT('Summary'!T6)=1,'Summary'!T6,"") | R3: ='Summary'!U6 | S3: ='Summary'!V6 | T3: =IF(COUNT('Summary'!W6)=1,'Summary'!W6,"") | U3: ='Summary'!X6 | V3: ='Summary'!Y6 | W3: =IF(COUNT('Summary'!Z6)=1,'Summary'!Z6,"") | X3: ='Summary'!AA6 | Y3: ='Summary'!AB6 | Z3: =IF(COUNT('Summary'!AC6)=1,'Summary'!AC6,"") | AA3: ='Summary'!AD6 | AB3: ='Summary'!AE6 | AC3: =IF(COUNT('Summary'!AF6)=1,'Summary'!AF6,"") | AD3: ='Summary'!AG6 | AE3: ='Summary'!AH6 | AF3: =IF(COUNT('Summary'!AI6)=1,'Summary'!AI6,"") | AG3: ='Summary'!AJ6 | AH3: ='Summary'!AK6 | AI3: =IF(COUNT('Summary'!AL6)=1,'Summary'!AL6,"") | AJ3: ='Summary'!AM6 | AK3: ='Summary'!AN6 | AL3: =IF(COUNT('Summary'!AO6)=1,'Summary'!AO6,"") | AM3: ='Summary'!AP6 | AN3: ='Summary'!AQ6 | AO3: =IF(COUNT('Summary'!AR6)=1,'Summary'!AR6,"") | AP3: ='Summary'!AS6 | AQ3: ='Summary'!AT6 | AR3: =IF(COUNT('Summary'!AU6)=1,'Summary'!AU6,"") | AS3: ='Summary'!AV6 | AT3: ='Summary'!AW6 | AU3: =IF(COUNT('Summary'!AX6)=1,'Summary'!AX6,"") | AV3: ='Summary'!AY6 | AW3: ='Summary'!AZ6 | AX3: =IF(COUNT('Summary'!BA6)=1,'Summary'!BA6,"") | AY3: ='Summary'!BB6 | AZ3: ='Summary'!BC6 | BA3: =IF(COUNT('Summary'!BD6)=1,'Summary'!BD6,"") | BB3: ='Summary'!BE6 | BC3: ='Summary'!BF6 | BD3: =IF(COUNT('Summary'!BG6)=1,'Summary'!BG6,"") | BE3: ='Summary'!BH6 | BF3: ='Summary'!BI6 | BG3: =IF(COUNT('Summary'!BJ6)=1,'Summary'!BJ6,"") | BH3: ='Summary'!BK6 | BI3: ='Summary'!BL6 | BJ3: =IF(COUNT('Summary'!BM6)=1,'Summary'!BM6,"") | BK3: ='Summary'!BN6 | BL3: ='Summary'!BO6 | BM3: =IF(COUNT('Summary'!BP6)=1,'Summary'!BP6,"") | BN3: ='Summary'!BQ6 | BO3: ='Summary'!BR6 | BP3: =IF(COUNT('Summary'!BS6)=1,'Summary'!BS6,"") | BQ3: ='Summary'!BT6 | BR3: ='Summary'!BU6 | BS3: =IF(COUNT('Summary'!BV6)=1,'Summary'!BV6,"") | BT3: ='Summary'!BW6 | BU3: ='Summary'!BX6 | BV3: =IF(COUNT('Summary'!BY6)=1,'Summary'!BY6,"") | BW3: ='Summary'!BZ6 | BX3: ='Summary'!CA6 | BY3: =IF(COUNT('Summary'!CB6)=1,'Summary'!CB6,"") | BZ3: ='Summary'!CC6 | CA3: ='Summary'!CD6 | CB3: =IF(COUNT('Summary'!CE6)=1,'Summary'!CE6,"") | CC3: ='Summary'!CF6 | CD3: ='Summary'!CG6 | CE3: =IF(COUNT('Summary'!CH6)=1,'Summary'!CH6,"") | CF3: ='Summary'!CI6 | CG3: ='Summary'!CJ6 | CH3: =IF(COUNT('Summary'!CK6)=1,'Summary'!CK6,"") | CI3: ='Summary'!CL6 | CJ3: ='Summary'!CM6 | CK3: =IF(COUNT('Summary'!CN6)=1,'Summary'!CN6,"") | CL3: ='Summary'!CO6 | CM3: ='Summary'!CP6 | CN3: =IF(COUNT('Summary'!CQ6)=1,'Summary'!CQ6,"") | CO3: ='Summary'!CR6 | CP3: ='Summary'!CS6 | CQ3: =IF(COUNT('Summary'!CT6)=1,'Summary'!CT6,"") | CR3: ='Summary'!CU6 | CS3: ='Summary'!CV6 | CT3: =IF(COUNT('Summary'!CW6)=1,'Summary'!CW6,"") | CU3: ='Summary'!CX6 | CV3: ='Summary'!CY6 | CW3: =IF(COUNT('Summary'!CZ6)=1,'Summary'!CZ6,"") | CX3: ='Summary'!DA6 | CY3: ='Summary'!DB6 | CZ3: =IF(COUNT('Summary'!DC6)=1,'Summary'!DC6,"") | DA3: ='Summary'!DD6 | DB3: ='Summary'!DE6 | DC3: =IF(COUNT('Summary'!DF6)=1,'Summary'!DF6,"") | DD3: ='Summary'!DG6 | DE3: ='Summary'!DH6 | DF3: =IF(COUNT('Summary'!DI6)=1,'Summary'!DI6,"") | DG3: ='Summary'!DJ6 | DH3: ='Summary'!DK6 | DI3: =IF(COUNT('Summary'!DL6)=1,'Summary'!DL6,"") | DJ3: ='Summary'!DM6 | DK3: ='Summary'!DN6 | DL3: =IF(COUNT(Finance!$B$63)=1,Finance!$B$63,"") | DM3: =Finance!$B$63 | DN3: =Finance!$B$63
A4: New Recurring Revenue | B4: =IF(COUNT(AR4,AO4,AL4,AI4,AF4,AC4,Z4,W4,T4,Q4,N4,K4)=0,"",SUM(AR4,AO4,AL4,AI4,AF4,AC4,Z4,W4,T4,Q4,N4,K4)) | C4: =IF(COUNT(AS4,AP4,AM4,AJ4,AG4,AD4,AA4,X4,U4,R4,O4,L4)=0,"",SUM(AS4,AP4,AM4,AJ4,AG4,AD4,AA4,X4,U4,R4,O4,L4)) | D4: =IF(COUNT(AT4,AQ4,AN4,AK4,AH4,AE4,AB4,Y4,V4,S4,P4,M4)=0,"",SUM(AT4,AQ4,AN4,AK4,AH4,AE4,AB4,Y4,V4,S4,P4,M4)) | E4: =IF(COUNT(CB4,BY4,BV4,BS4,BP4,BM4,BJ4,BG4,BD4,BA4,AX4,AU4)=0,"",SUM(CB4,BY4,BV4,BS4,BP4,BM4,BJ4,BG4,BD4,BA4,AX4,AU4)) | F4: =IF(COUNT(CC4,BZ4,BW4,BT4,BQ4,BN4,BK4,BH4,BE4,BB4,AY4,AV4)=0,"",SUM(CC4,BZ4,BW4,BT4,BQ4,BN4,BK4,BH4,BE4,BB4,AY4,AV4)) | G4: =IF(COUNT(CD4,CA4,BX4,BU4,BR4,BO4,BL4,BI4,BF4,BC4,AZ4,AW4)=0,"",SUM(CD4,CA4,BX4,BU4,BR4,BO4,BL4,BI4,BF4,BC4,AZ4,AW4)) | H4: =IF(COUNT(DL4,DI4,DF4,DC4,CZ4,CW4,CT4,CQ4,CN4,CK4,CH4,CE4)=0,"",SUM(DL4,DI4,DF4,DC4,CZ4,CW4,CT4,CQ4,CN4,CK4,CH4,CE4)) | I4: =IF(COUNT(DM4,DJ4,DG4,DD4,DA4,CX4,CU4,CR4,CO4,CL4,CI4,CF4)=0,"",SUM(DM4,DJ4,DG4,DD4,DA4,CX4,CU4,CR4,CO4,CL4,CI4,CF4)) | J4: =IF(COUNT(DN4,DK4,DH4,DE4,DB4,CY4,CV4,CS4,CP4,CM4,CJ4,CG4)=0,"",SUM(DN4,DK4,DH4,DE4,DB4,CY4,CV4,CS4,CP4,CM4,CJ4,CG4)) | K4: =IF(COUNT('Sales'!K8)=1,'Sales'!K8,"") | L4: ='Sales'!L8 | M4: ='Sales'!M8 | N4: =IF(COUNT('Sales'!N8)=1,'Sales'!N8,"") | O4: ='Sales'!O8 | P4: ='Sales'!P8 | Q4: =IF(COUNT('Sales'!Q8)=1,'Sales'!Q8,"") | R4: ='Sales'!R8 | S4: ='Sales'!S8 | T4: =IF(COUNT('Sales'!T8)=1,'Sales'!T8,"") | U4: ='Sales'!U8 | V4: ='Sales'!V8 | W4: =IF(COUNT('Sales'!W8)=1,'Sales'!W8,"") | X4: ='Sales'!X8 | Y4: ='Sales'!Y8 | Z4: =IF(COUNT('Sales'!Z8)=1,'Sales'!Z8,"") | AA4: ='Sales'!AA8 | AB4: ='Sales'!AB8 | AC4: =IF(COUNT('Sales'!AC8)=1,'Sales'!AC8,"") | AD4: ='Sales'!AD8 | AE4: ='Sales'!AE8 | AF4: =IF(COUNT('Sales'!AF8)=1,'Sales'!AF8,"") | AG4: ='Sales'!AG8 | AH4: ='Sales'!AH8 | AI4: =IF(COUNT('Sales'!AI8)=1,'Sales'!AI8,"") | AJ4: ='Sales'!AJ8 | AK4: ='Sales'!AK8 | AL4: =IF(COUNT('Sales'!AL8)=1,'Sales'!AL8,"") | AM4: ='Sales'!AM8 | AN4: ='Sales'!AN8 | AO4: =IF(COUNT('Sales'!AO8)=1,'Sales'!AO8,"") | AP4: ='Sales'!AP8 | AQ4: ='Sales'!AQ8 | AR4: =IF(COUNT('Sales'!AR8)=1,'Sales'!AR8,"") | AS4: ='Sales'!AS8 | AT4: ='Sales'!AT8 | AU4: =IF(COUNT('Sales'!AU8)=1,'Sales'!AU8,"") | AV4: ='Sales'!AV8 | AW4: ='Sales'!AW8 | AX4: =IF(COUNT('Sales'!AX8)=1,'Sales'!AX8,"") | AY4: ='Sales'!AY8 | AZ4: ='Sales'!AZ8 | BA4: =IF(COUNT('Sales'!BA8)=1,'Sales'!BA8,"") | BB4: ='Sales'!BB8 | BC4: ='Sales'!BC8 | BD4: =IF(COUNT('Sales'!BD8)=1,'Sales'!BD8,"") | BE4: ='Sales'!BE8 | BF4: ='Sales'!BF8 | BG4: =IF(COUNT('Sales'!BG8)=1,'Sales'!BG8,"") | BH4: ='Sales'!BH8 | BI4: ='Sales'!BI8 | BJ4: =IF(COUNT('Sales'!BJ8)=1,'Sales'!BJ8,"") | BK4: ='Sales'!BK8 | BL4: ='Sales'!BL8 | BM4: =IF(COUNT('Sales'!BM8)=1,'Sales'!BM8,"") | BN4: ='Sales'!BN8 | BO4: ='Sales'!BO8 | BP4: =IF(COUNT('Sales'!BP8)=1,'Sales'!BP8,"") | BQ4: ='Sales'!BQ8 | BR4: ='Sales'!BR8 | BS4: =IF(COUNT('Sales'!BS8)=1,'Sales'!BS8,"") | BT4: ='Sales'!BT8 | BU4: ='Sales'!BU8 | BV4: =IF(COUNT('Sales'!BV8)=1,'Sales'!BV8,"") | BW4: ='Sales'!BW8 | BX4: ='Sales'!BX8 | BY4: =IF(COUNT('Sales'!BY8)=1,'Sales'!BY8,"") | BZ4: ='Sales'!BZ8 | CA4: ='Sales'!CA8 | CB4: =IF(COUNT('Sales'!CB8)=1,'Sales'!CB8,"") | CC4: ='Sales'!CC8 | CD4: ='Sales'!CD8 | CE4: =IF(COUNT('Sales'!CE8)=1,'Sales'!CE8,"") | CF4: ='Sales'!CF8 | CG4: ='Sales'!CG8 | CH4: =IF(COUNT('Sales'!CH8)=1,'Sales'!CH8,"") | CI4: ='Sales'!CI8 | CJ4: ='Sales'!CJ8 | CK4: =IF(COUNT('Sales'!CK8)=1,'Sales'!CK8,"") | CL4: ='Sales'!CL8 | CM4: ='Sales'!CM8 | CN4: =IF(COUNT('Sales'!CN8)=1,'Sales'!CN8,"") | CO4: ='Sales'!CO8 | CP4: ='Sales'!CP8 | CQ4: =IF(COUNT('Sales'!CQ8)=1,'Sales'!CQ8,"") | CR4: ='Sales'!CR8 | CS4: ='Sales'!CS8 | CT4: =IF(COUNT('Sales'!CT8)=1,'Sales'!CT8,"") | CU4: ='Sales'!CU8 | CV4: ='Sales'!CV8 | CW4: =IF(COUNT('Sales'!CW8)=1,'Sales'!CW8,"") | CX4: ='Sales'!CX8 | CY4: ='Sales'!CY8 | CZ4: =IF(COUNT('Sales'!CZ8)=1,'Sales'!CZ8,"") | DA4: ='Sales'!DA8 | DB4: ='Sales'!DB8 | DC4: =IF(COUNT('Sales'!DC8)=1,'Sales'!DC8,"") | DD4: ='Sales'!DD8 | DE4: ='Sales'!DE8 | DF4: =IF(COUNT('Sales'!DF8)=1,'Sales'!DF8,"") | DG4: ='Sales'!DG8 | DH4: ='Sales'!DH8 | DI4: =IF(COUNT('Sales'!DI8)=1,'Sales'!DI8,"") | DJ4: ='Sales'!DJ8 | DK4: ='Sales'!DK8 | DL4: =IF(COUNT('Sales'!DL8)=1,'Sales'!DL8,"") | DM4: ='Sales'!DM8 | DN4: ='Sales'!DN8
A5: Net Change on Existing | B5: =IF(COUNT(AR5,AO5,AL5,AI5,AF5,AC5,Z5,W5,T5,Q5,N5,K5)=0,"",SUM(AR5,AO5,AL5,AI5,AF5,AC5,Z5,W5,T5,Q5,N5,K5)) | C5: =IF(COUNT(AS5,AP5,AM5,AJ5,AG5,AD5,AA5,X5,U5,R5,O5,L5)=0,"",SUM(AS5,AP5,AM5,AJ5,AG5,AD5,AA5,X5,U5,R5,O5,L5)) | D5: =IF(COUNT(AT5,AQ5,AN5,AK5,AH5,AE5,AB5,Y5,V5,S5,P5,M5)=0,"",SUM(AT5,AQ5,AN5,AK5,AH5,AE5,AB5,Y5,V5,S5,P5,M5)) | E5: =IF(COUNT(CB5,BY5,BV5,BS5,BP5,BM5,BJ5,BG5,BD5,BA5,AX5,AU5)=0,"",SUM(CB5,BY5,BV5,BS5,BP5,BM5,BJ5,BG5,BD5,BA5,AX5,AU5)) | F5: =IF(COUNT(CC5,BZ5,BW5,BT5,BQ5,BN5,BK5,BH5,BE5,BB5,AY5,AV5)=0,"",SUM(CC5,BZ5,BW5,BT5,BQ5,BN5,BK5,BH5,BE5,BB5,AY5,AV5)) | G5: =IF(COUNT(CD5,CA5,BX5,BU5,BR5,BO5,BL5,BI5,BF5,BC5,AZ5,AW5)=0,"",SUM(CD5,CA5,BX5,BU5,BR5,BO5,BL5,BI5,BF5,BC5,AZ5,AW5)) | H5: =IF(COUNT(DL5,DI5,DF5,DC5,CZ5,CW5,CT5,CQ5,CN5,CK5,CH5,CE5)=0,"",SUM(DL5,DI5,DF5,DC5,CZ5,CW5,CT5,CQ5,CN5,CK5,CH5,CE5)) | I5: =IF(COUNT(DM5,DJ5,DG5,DD5,DA5,CX5,CU5,CR5,CO5,CL5,CI5,CF5)=0,"",SUM(DM5,DJ5,DG5,DD5,DA5,CX5,CU5,CR5,CO5,CL5,CI5,CF5)) | J5: =IF(COUNT(DN5,DK5,DH5,DE5,DB5,CY5,CV5,CS5,CP5,CM5,CJ5,CG5)=0,"",SUM(DN5,DK5,DH5,DE5,DB5,CY5,CV5,CS5,CP5,CM5,CJ5,CG5)) | K5: =IF(COUNT('Customer Success'!K11)=1,'Customer Success'!K11,"") | L5: ='Customer Success'!L11 | M5: ='Customer Success'!M11 | N5: =IF(COUNT('Customer Success'!N11)=1,'Customer Success'!N11,"") | O5: ='Customer Success'!O11 | P5: ='Customer Success'!P11 | Q5: =IF(COUNT('Customer Success'!Q11)=1,'Customer Success'!Q11,"") | R5: ='Customer Success'!R11 | S5: ='Customer Success'!S11 | T5: =IF(COUNT('Customer Success'!T11)=1,'Customer Success'!T11,"") | U5: ='Customer Success'!U11 | V5: ='Customer Success'!V11 | W5: =IF(COUNT('Customer Success'!W11)=1,'Customer Success'!W11,"") | X5: ='Customer Success'!X11 | Y5: ='Customer Success'!Y11 | Z5: =IF(COUNT('Customer Success'!Z11)=1,'Customer Success'!Z11,"") | AA5: ='Customer Success'!AA11 | AB5: ='Customer Success'!AB11 | AC5: =IF(COUNT('Customer Success'!AC11)=1,'Customer Success'!AC11,"") | AD5: ='Customer Success'!AD11 | AE5: ='Customer Success'!AE11 | AF5: =IF(COUNT('Customer Success'!AF11)=1,'Customer Success'!AF11,"") | AG5: ='Customer Success'!AG11 | AH5: ='Customer Success'!AH11 | AI5: =IF(COUNT('Customer Success'!AI11)=1,'Customer Success'!AI11,"") | AJ5: ='Customer Success'!AJ11 | AK5: ='Customer Success'!AK11 | AL5: =IF(COUNT('Customer Success'!AL11)=1,'Customer Success'!AL11,"") | AM5: ='Customer Success'!AM11 | AN5: ='Customer Success'!AN11 | AO5: =IF(COUNT('Customer Success'!AO11)=1,'Customer Success'!AO11,"") | AP5: ='Customer Success'!AP11 | AQ5: ='Customer Success'!AQ11 | AR5: =IF(COUNT('Customer Success'!AR11)=1,'Customer Success'!AR11,"") | AS5: ='Customer Success'!AS11 | AT5: ='Customer Success'!AT11 | AU5: =IF(COUNT('Customer Success'!AU11)=1,'Customer Success'!AU11,"") | AV5: ='Customer Success'!AV11 | AW5: ='Customer Success'!AW11 | AX5: =IF(COUNT('Customer Success'!AX11)=1,'Customer Success'!AX11,"") | AY5: ='Customer Success'!AY11 | AZ5: ='Customer Success'!AZ11 | BA5: =IF(COUNT('Customer Success'!BA11)=1,'Customer Success'!BA11,"") | BB5: ='Customer Success'!BB11 | BC5: ='Customer Success'!BC11 | BD5: =IF(COUNT('Customer Success'!BD11)=1,'Customer Success'!BD11,"") | BE5: ='Customer Success'!BE11 | BF5: ='Customer Success'!BF11 | BG5: =IF(COUNT('Customer Success'!BG11)=1,'Customer Success'!BG11,"") | BH5: ='Customer Success'!BH11 | BI5: ='Customer Success'!BI11 | BJ5: =IF(COUNT('Customer Success'!BJ11)=1,'Customer Success'!BJ11,"") | BK5: ='Customer Success'!BK11 | BL5: ='Customer Success'!BL11 | BM5: =IF(COUNT('Customer Success'!BM11)=1,'Customer Success'!BM11,"") | BN5: ='Customer Success'!BN11 | BO5: ='Customer Success'!BO11 | BP5: =IF(COUNT('Customer Success'!BP11)=1,'Customer Success'!BP11,"") | BQ5: ='Customer Success'!BQ11 | BR5: ='Customer Success'!BR11 | BS5: =IF(COUNT('Customer Success'!BS11)=1,'Customer Success'!BS11,"") | BT5: ='Customer Success'!BT11 | BU5: ='Customer Success'!BU11 | BV5: =IF(COUNT('Customer Success'!BV11)=1,'Customer Success'!BV11,"") | BW5: ='Customer Success'!BW11 | BX5: ='Customer Success'!BX11 | BY5: =IF(COUNT('Customer Success'!BY11)=1,'Customer Success'!BY11,"") | BZ5: ='Customer Success'!BZ11 | CA5: ='Customer Success'!CA11 | CB5: =IF(COUNT('Customer Success'!CB11)=1,'Customer Success'!CB11,"") | CC5: ='Customer Success'!CC11 | CD5: ='Customer Success'!CD11 | CE5: =IF(COUNT('Customer Success'!CE11)=1,'Customer Success'!CE11,"") | CF5: ='Customer Success'!CF11 | CG5: ='Customer Success'!CG11 | CH5: =IF(COUNT('Customer Success'!CH11)=1,'Customer Success'!CH11,"") | CI5: ='Customer Success'!CI11 | CJ5: ='Customer Success'!CJ11 | CK5: =IF(COUNT('Customer Success'!CK11)=1,'Customer Success'!CK11,"") | CL5: ='Customer Success'!CL11 | CM5: ='Customer Success'!CM11 | CN5: =IF(COUNT('Customer Success'!CN11)=1,'Customer Success'!CN11,"") | CO5: ='Customer Success'!CO11 | CP5: ='Customer Success'!CP11 | CQ5: =IF(COUNT('Customer Success'!CQ11)=1,'Customer Success'!CQ11,"") | CR5: ='Customer Success'!CR11 | CS5: ='Customer Success'!CS11 | CT5: =IF(COUNT('Customer Success'!CT11)=1,'Customer Success'!CT11,"") | CU5: ='Customer Success'!CU11 | CV5: ='Customer Success'!CV11 | CW5: =IF(COUNT('Customer Success'!CW11)=1,'Customer Success'!CW11,"") | CX5: ='Customer Success'!CX11 | CY5: ='Customer Success'!CY11 | CZ5: =IF(COUNT('Customer Success'!CZ11)=1,'Customer Success'!CZ11,"") | DA5: ='Customer Success'!DA11 | DB5: ='Customer Success'!DB11 | DC5: =IF(COUNT('Customer Success'!DC11)=1,'Customer Success'!DC11,"") | DD5: ='Customer Success'!DD11 | DE5: ='Customer Success'!DE11 | DF5: =IF(COUNT('Customer Success'!DF11)=1,'Customer Success'!DF11,"") | DG5: ='Customer Success'!DG11 | DH5: ='Customer Success'!DH11 | DI5: =IF(COUNT('Customer Success'!DI11)=1,'Customer Success'!DI11,"") | DJ5: ='Customer Success'!DJ11 | DK5: ='Customer Success'!DK11 | DL5: =IF(COUNT('Customer Success'!DL11)=1,'Customer Success'!DL11,"") | DM5: ='Customer Success'!DM11 | DN5: ='Customer Success'!DN11
A6: Closing Recurring Revenue | B6: =IF(K6<>"",K6,IF(N6<>"",N6,IF(Q6<>"",Q6,IF(T6<>"",T6,IF(W6<>"",W6,IF(Z6<>"",Z6,IF(AC6<>"",AC6,IF(AF6<>"",AF6,IF(AI6<>"",AI6,IF(AL6<>"",AL6,IF(AO6<>"",AO6,IF(AR6<>"",AR6,"")))))))))))) | C6: =IF(L6<>"",L6,IF(O6<>"",O6,IF(R6<>"",R6,IF(U6<>"",U6,IF(X6<>"",X6,IF(AA6<>"",AA6,IF(AD6<>"",AD6,IF(AG6<>"",AG6,IF(AJ6<>"",AJ6,IF(AM6<>"",AM6,IF(AP6<>"",AP6,IF(AS6<>"",AS6,"")))))))))))) | D6: =IF(M6<>"",M6,IF(P6<>"",P6,IF(S6<>"",S6,IF(V6<>"",V6,IF(Y6<>"",Y6,IF(AB6<>"",AB6,IF(AE6<>"",AE6,IF(AH6<>"",AH6,IF(AK6<>"",AK6,IF(AN6<>"",AN6,IF(AQ6<>"",AQ6,IF(AT6<>"",AT6,"")))))))))))) | E6: =IF(AU6<>"",AU6,IF(AX6<>"",AX6,IF(BA6<>"",BA6,IF(BD6<>"",BD6,IF(BG6<>"",BG6,IF(BJ6<>"",BJ6,IF(BM6<>"",BM6,IF(BP6<>"",BP6,IF(BS6<>"",BS6,IF(BV6<>"",BV6,IF(BY6<>"",BY6,IF(CB6<>"",CB6,"")))))))))))) | F6: =IF(AV6<>"",AV6,IF(AY6<>"",AY6,IF(BB6<>"",BB6,IF(BE6<>"",BE6,IF(BH6<>"",BH6,IF(BK6<>"",BK6,IF(BN6<>"",BN6,IF(BQ6<>"",BQ6,IF(BT6<>"",BT6,IF(BW6<>"",BW6,IF(BZ6<>"",BZ6,IF(CC6<>"",CC6,"")))))))))))) | G6: =IF(AW6<>"",AW6,IF(AZ6<>"",AZ6,IF(BC6<>"",BC6,IF(BF6<>"",BF6,IF(BI6<>"",BI6,IF(BL6<>"",BL6,IF(BO6<>"",BO6,IF(BR6<>"",BR6,IF(BU6<>"",BU6,IF(BX6<>"",BX6,IF(CA6<>"",CA6,IF(CD6<>"",CD6,"")))))))))))) | H6: =IF(CE6<>"",CE6,IF(CH6<>"",CH6,IF(CK6<>"",CK6,IF(CN6<>"",CN6,IF(CQ6<>"",CQ6,IF(CT6<>"",CT6,IF(CW6<>"",CW6,IF(CZ6<>"",CZ6,IF(DC6<>"",DC6,IF(DF6<>"",DF6,IF(DI6<>"",DI6,IF(DL6<>"",DL6,"")))))))))))) | I6: =IF(CF6<>"",CF6,IF(CI6<>"",CI6,IF(CL6<>"",CL6,IF(CO6<>"",CO6,IF(CR6<>"",CR6,IF(CU6<>"",CU6,IF(CX6<>"",CX6,IF(DA6<>"",DA6,IF(DD6<>"",DD6,IF(DG6<>"",DG6,IF(DJ6<>"",DJ6,IF(DM6<>"",DM6,"")))))))))))) | J6: =IF(CG6<>"",CG6,IF(CJ6<>"",CJ6,IF(CM6<>"",CM6,IF(CP6<>"",CP6,IF(CS6<>"",CS6,IF(CV6<>"",CV6,IF(CY6<>"",CY6,IF(DB6<>"",DB6,IF(DE6<>"",DE6,IF(DH6<>"",DH6,IF(DK6<>"",DK6,IF(DN6<>"",DN6,"")))))))))))) | K6: =IF(COUNT(K3,K4,K5)=3,K3+K4+K5,"") | L6: =L3+L4+L5 | M6: =M3+M4+M5 | N6: =IF(COUNT(N3,N4,N5)=3,N3+N4+N5,"") | O6: =O3+O4+O5 | P6: =P3+P4+P5 | Q6: =IF(COUNT(Q3,Q4,Q5)=3,Q3+Q4+Q5,"") | R6: =R3+R4+R5 | S6: =S3+S4+S5 | T6: =IF(COUNT(T3,T4,T5)=3,T3+T4+T5,"") | U6: =U3+U4+U5 | V6: =V3+V4+V5 | W6: =IF(COUNT(W3,W4,W5)=3,W3+W4+W5,"") | X6: =X3+X4+X5 | Y6: =Y3+Y4+Y5 | Z6: =IF(COUNT(Z3,Z4,Z5)=3,Z3+Z4+Z5,"") | AA6: =AA3+AA4+AA5 | AB6: =AB3+AB4+AB5 | AC6: =IF(COUNT(AC3,AC4,AC5)=3,AC3+AC4+AC5,"") | AD6: =AD3+AD4+AD5 | AE6: =AE3+AE4+AE5 | AF6: =IF(COUNT(AF3,AF4,AF5)=3,AF3+AF4+AF5,"") | AG6: =AG3+AG4+AG5 | AH6: =AH3+AH4+AH5 | AI6: =IF(COUNT(AI3,AI4,AI5)=3,AI3+AI4+AI5,"") | AJ6: =AJ3+AJ4+AJ5 | AK6: =AK3+AK4+AK5 | AL6: =IF(COUNT(AL3,AL4,AL5)=3,AL3+AL4+AL5,"") | AM6: =AM3+AM4+AM5 | AN6: =AN3+AN4+AN5 | AO6: =IF(COUNT(AO3,AO4,AO5)=3,AO3+AO4+AO5,"") | AP6: =AP3+AP4+AP5 | AQ6: =AQ3+AQ4+AQ5 | AR6: =IF(COUNT(AR3,AR4,AR5)=3,AR3+AR4+AR5,"") | AS6: =AS3+AS4+AS5 | AT6: =AT3+AT4+AT5 | AU6: =IF(COUNT(AU3,AU4,AU5)=3,AU3+AU4+AU5,"") | AV6: =AV3+AV4+AV5 | AW6: =AW3+AW4+AW5 | AX6: =IF(COUNT(AX3,AX4,AX5)=3,AX3+AX4+AX5,"") | AY6: =AY3+AY4+AY5 | AZ6: =AZ3+AZ4+AZ5 | BA6: =IF(COUNT(BA3,BA4,BA5)=3,BA3+BA4+BA5,"") | BB6: =BB3+BB4+BB5 | BC6: =BC3+BC4+BC5 | BD6: =IF(COUNT(BD3,BD4,BD5)=3,BD3+BD4+BD5,"") | BE6: =BE3+BE4+BE5 | BF6: =BF3+BF4+BF5 | BG6: =IF(COUNT(BG3,BG4,BG5)=3,BG3+BG4+BG5,"") | BH6: =BH3+BH4+BH5 | BI6: =BI3+BI4+BI5 | BJ6: =IF(COUNT(BJ3,BJ4,BJ5)=3,BJ3+BJ4+BJ5,"") | BK6: =BK3+BK4+BK5 | BL6: =BL3+BL4+BL5 | BM6: =IF(COUNT(BM3,BM4,BM5)=3,BM3+BM4+BM5,"") | BN6: =BN3+BN4+BN5 | BO6: =BO3+BO4+BO5 | BP6: =IF(COUNT(BP3,BP4,BP5)=3,BP3+BP4+BP5,"") | BQ6: =BQ3+BQ4+BQ5 | BR6: =BR3+BR4+BR5 | BS6: =IF(COUNT(BS3,BS4,BS5)=3,BS3+BS4+BS5,"") | BT6: =BT3+BT4+BT5 | BU6: =BU3+BU4+BU5 | BV6: =IF(COUNT(BV3,BV4,BV5)=3,BV3+BV4+BV5,"") | BW6: =BW3+BW4+BW5 | BX6: =BX3+BX4+BX5 | BY6: =IF(COUNT(BY3,BY4,BY5)=3,BY3+BY4+BY5,"") | BZ6: =BZ3+BZ4+BZ5 | CA6: =CA3+CA4+CA5 | CB6: =IF(COUNT(CB3,CB4,CB5)=3,CB3+CB4+CB5,"") | CC6: =CC3+CC4+CC5 | CD6: =CD3+CD4+CD5 | CE6: =IF(COUNT(CE3,CE4,CE5)=3,CE3+CE4+CE5,"") | CF6: =CF3+CF4+CF5 | CG6: =CG3+CG4+CG5 | CH6: =IF(COUNT(CH3,CH4,CH5)=3,CH3+CH4+CH5,"") | CI6: =CI3+CI4+CI5 | CJ6: =CJ3+CJ4+CJ5 | CK6: =IF(COUNT(CK3,CK4,CK5)=3,CK3+CK4+CK5,"") | CL6: =CL3+CL4+CL5 | CM6: =CM3+CM4+CM5 | CN6: =IF(COUNT(CN3,CN4,CN5)=3,CN3+CN4+CN5,"") | CO6: =CO3+CO4+CO5 | CP6: =CP3+CP4+CP5 | CQ6: =IF(COUNT(CQ3,CQ4,CQ5)=3,CQ3+CQ4+CQ5,"") | CR6: =CR3+CR4+CR5 | CS6: =CS3+CS4+CS5 | CT6: =IF(COUNT(CT3,CT4,CT5)=3,CT3+CT4+CT5,"") | CU6: =CU3+CU4+CU5 | CV6: =CV3+CV4+CV5 | CW6: =IF(COUNT(CW3,CW4,CW5)=3,CW3+CW4+CW5,"") | CX6: =CX3+CX4+CX5 | CY6: =CY3+CY4+CY5 | CZ6: =IF(COUNT(CZ3,CZ4,CZ5)=3,CZ3+CZ4+CZ5,"") | DA6: =DA3+DA4+DA5 | DB6: =DB3+DB4+DB5 | DC6: =IF(COUNT(DC3,DC4,DC5)=3,DC3+DC4+DC5,"") | DD6: =DD3+DD4+DD5 | DE6: =DE3+DE4+DE5 | DF6: =IF(COUNT(DF3,DF4,DF5)=3,DF3+DF4+DF5,"") | DG6: =DG3+DG4+DG5 | DH6: =DH3+DH4+DH5 | DI6: =IF(COUNT(DI3,DI4,DI5)=3,DI3+DI4+DI5,"") | DJ6: =DJ3+DJ4+DJ5 | DK6: =DK3+DK4+DK5 | DL6: =IF(COUNT(DL3,DL4,DL5)=3,DL3+DL4+DL5,"") | DM6: =DM3+DM4+DM5 | DN6: =DN3+DN4+DN5
A7: Revenue | B7: =IF(COUNT(AR7,AO7,AL7,AI7,AF7,AC7,Z7,W7,T7,Q7,N7,K7)=0,"",SUM(AR7,AO7,AL7,AI7,AF7,AC7,Z7,W7,T7,Q7,N7,K7)) | C7: =IF(COUNT(AS7,AP7,AM7,AJ7,AG7,AD7,AA7,X7,U7,R7,O7,L7)=0,"",SUM(AS7,AP7,AM7,AJ7,AG7,AD7,AA7,X7,U7,R7,O7,L7)) | D7: =IF(COUNT(AT7,AQ7,AN7,AK7,AH7,AE7,AB7,Y7,V7,S7,P7,M7)=0,"",SUM(AT7,AQ7,AN7,AK7,AH7,AE7,AB7,Y7,V7,S7,P7,M7)) | E7: =IF(COUNT(CB7,BY7,BV7,BS7,BP7,BM7,BJ7,BG7,BD7,BA7,AX7,AU7)=0,"",SUM(CB7,BY7,BV7,BS7,BP7,BM7,BJ7,BG7,BD7,BA7,AX7,AU7)) | F7: =IF(COUNT(CC7,BZ7,BW7,BT7,BQ7,BN7,BK7,BH7,BE7,BB7,AY7,AV7)=0,"",SUM(CC7,BZ7,BW7,BT7,BQ7,BN7,BK7,BH7,BE7,BB7,AY7,AV7)) | G7: =IF(COUNT(CD7,CA7,BX7,BU7,BR7,BO7,BL7,BI7,BF7,BC7,AZ7,AW7)=0,"",SUM(CD7,CA7,BX7,BU7,BR7,BO7,BL7,BI7,BF7,BC7,AZ7,AW7)) | H7: =IF(COUNT(DL7,DI7,DF7,DC7,CZ7,CW7,CT7,CQ7,CN7,CK7,CH7,CE7)=0,"",SUM(DL7,DI7,DF7,DC7,CZ7,CW7,CT7,CQ7,CN7,CK7,CH7,CE7)) | I7: =IF(COUNT(DM7,DJ7,DG7,DD7,DA7,CX7,CU7,CR7,CO7,CL7,CI7,CF7)=0,"",SUM(DM7,DJ7,DG7,DD7,DA7,CX7,CU7,CR7,CO7,CL7,CI7,CF7)) | J7: =IF(COUNT(DN7,DK7,DH7,DE7,DB7,CY7,CV7,CS7,CP7,CM7,CJ7,CG7)=0,"",SUM(DN7,DK7,DH7,DE7,DB7,CY7,CV7,CS7,CP7,CM7,CJ7,CG7)) | K7: =IF(COUNT(K6)=1,K6,"") | L7: =L6 | M7: =M6 | N7: =IF(COUNT(N6)=1,N6,"") | O7: =O6 | P7: =P6 | Q7: =IF(COUNT(Q6)=1,Q6,"") | R7: =R6 | S7: =S6 | T7: =IF(COUNT(T6)=1,T6,"") | U7: =U6 | V7: =V6 | W7: =IF(COUNT(W6)=1,W6,"") | X7: =X6 | Y7: =Y6 | Z7: =IF(COUNT(Z6)=1,Z6,"") | AA7: =AA6 | AB7: =AB6 | AC7: =IF(COUNT(AC6)=1,AC6,"") | AD7: =AD6 | AE7: =AE6 | AF7: =IF(COUNT(AF6)=1,AF6,"") | AG7: =AG6 | AH7: =AH6 | AI7: =IF(COUNT(AI6)=1,AI6,"") | AJ7: =AJ6 | AK7: =AK6 | AL7: =IF(COUNT(AL6)=1,AL6,"") | AM7: =AM6 | AN7: =AN6 | AO7: =IF(COUNT(AO6)=1,AO6,"") | AP7: =AP6 | AQ7: =AQ6 | AR7: =IF(COUNT(AR6)=1,AR6,"") | AS7: =AS6 | AT7: =AT6 | AU7: =IF(COUNT(AU6)=1,AU6,"") | AV7: =AV6 | AW7: =AW6 | AX7: =IF(COUNT(AX6)=1,AX6,"") | AY7: =AY6 | AZ7: =AZ6 | BA7: =IF(COUNT(BA6)=1,BA6,"") | BB7: =BB6 | BC7: =BC6 | BD7: =IF(COUNT(BD6)=1,BD6,"") | BE7: =BE6 | BF7: =BF6 | BG7: =IF(COUNT(BG6)=1,BG6,"") | BH7: =BH6 | BI7: =BI6 | BJ7: =IF(COUNT(BJ6)=1,BJ6,"") | BK7: =BK6 | BL7: =BL6 | BM7: =IF(COUNT(BM6)=1,BM6,"") | BN7: =BN6 | BO7: =BO6 | BP7: =IF(COUNT(BP6)=1,BP6,"") | BQ7: =BQ6 | BR7: =BR6 | BS7: =IF(COUNT(BS6)=1,BS6,"") | BT7: =BT6 | BU7: =BU6 | BV7: =IF(COUNT(BV6)=1,BV6,"") | BW7: =BW6 | BX7: =BX6 | BY7: =IF(COUNT(BY6)=1,BY6,"") | BZ7: =BZ6 | CA7: =CA6 | CB7: =IF(COUNT(CB6)=1,CB6,"") | CC7: =CC6 | CD7: =CD6 | CE7: =IF(COUNT(CE6)=1,CE6,"") | CF7: =CF6 | CG7: =CG6 | CH7: =IF(COUNT(CH6)=1,CH6,"") | CI7: =CI6 | CJ7: =CJ6 | CK7: =IF(COUNT(CK6)=1,CK6,"") | CL7: =CL6 | CM7: =CM6 | CN7: =IF(COUNT(CN6)=1,CN6,"") | CO7: =CO6 | CP7: =CP6 | CQ7: =IF(COUNT(CQ6)=1,CQ6,"") | CR7: =CR6 | CS7: =CS6 | CT7: =IF(COUNT(CT6)=1,CT6,"") | CU7: =CU6 | CV7: =CV6 | CW7: =IF(COUNT(CW6)=1,CW6,"") | CX7: =CX6 | CY7: =CY6 | CZ7: =IF(COUNT(CZ6)=1,CZ6,"") | DA7: =DA6 | DB7: =DB6 | DC7: =IF(COUNT(DC6)=1,DC6,"") | DD7: =DD6 | DE7: =DE6 | DF7: =IF(COUNT(DF6)=1,DF6,"") | DG7: =DG6 | DH7: =DH6 | DI7: =IF(COUNT(DI6)=1,DI6,"") | DJ7: =DJ6 | DK7: =DK6 | DL7: =IF(COUNT(DL6)=1,DL6,"") | DM7: =DM6 | DN7: =DN6
A8: Gross Profit | B8: =IF(COUNT(AR8,AO8,AL8,AI8,AF8,AC8,Z8,W8,T8,Q8,N8,K8)=0,"",SUM(AR8,AO8,AL8,AI8,AF8,AC8,Z8,W8,T8,Q8,N8,K8)) | C8: =IF(COUNT(AS8,AP8,AM8,AJ8,AG8,AD8,AA8,X8,U8,R8,O8,L8)=0,"",SUM(AS8,AP8,AM8,AJ8,AG8,AD8,AA8,X8,U8,R8,O8,L8)) | D8: =IF(COUNT(AT8,AQ8,AN8,AK8,AH8,AE8,AB8,Y8,V8,S8,P8,M8)=0,"",SUM(AT8,AQ8,AN8,AK8,AH8,AE8,AB8,Y8,V8,S8,P8,M8)) | E8: =IF(COUNT(CB8,BY8,BV8,BS8,BP8,BM8,BJ8,BG8,BD8,BA8,AX8,AU8)=0,"",SUM(CB8,BY8,BV8,BS8,BP8,BM8,BJ8,BG8,BD8,BA8,AX8,AU8)) | F8: =IF(COUNT(CC8,BZ8,BW8,BT8,BQ8,BN8,BK8,BH8,BE8,BB8,AY8,AV8)=0,"",SUM(CC8,BZ8,BW8,BT8,BQ8,BN8,BK8,BH8,BE8,BB8,AY8,AV8)) | G8: =IF(COUNT(CD8,CA8,BX8,BU8,BR8,BO8,BL8,BI8,BF8,BC8,AZ8,AW8)=0,"",SUM(CD8,CA8,BX8,BU8,BR8,BO8,BL8,BI8,BF8,BC8,AZ8,AW8)) | H8: =IF(COUNT(DL8,DI8,DF8,DC8,CZ8,CW8,CT8,CQ8,CN8,CK8,CH8,CE8)=0,"",SUM(DL8,DI8,DF8,DC8,CZ8,CW8,CT8,CQ8,CN8,CK8,CH8,CE8)) | I8: =IF(COUNT(DM8,DJ8,DG8,DD8,DA8,CX8,CU8,CR8,CO8,CL8,CI8,CF8)=0,"",SUM(DM8,DJ8,DG8,DD8,DA8,CX8,CU8,CR8,CO8,CL8,CI8,CF8)) | J8: =IF(COUNT(DN8,DK8,DH8,DE8,DB8,CY8,CV8,CS8,CP8,CM8,CJ8,CG8)=0,"",SUM(DN8,DK8,DH8,DE8,DB8,CY8,CV8,CS8,CP8,CM8,CJ8,CG8)) | K8: =IF(COUNT(K7,'Engineering'!K11,'Support'!K25)=3,K7-('Engineering'!K11+'Support'!K25),"") | L8: =L7-('Engineering'!L11+'Support'!L25) | M8: =M7-('Engineering'!M11+'Support'!M25) | N8: =IF(COUNT(N7,'Engineering'!N11,'Support'!N25)=3,N7-('Engineering'!N11+'Support'!N25),"") | O8: =O7-('Engineering'!O11+'Support'!O25) | P8: =P7-('Engineering'!P11+'Support'!P25) | Q8: =IF(COUNT(Q7,'Engineering'!Q11,'Support'!Q25)=3,Q7-('Engineering'!Q11+'Support'!Q25),"") | R8: =R7-('Engineering'!R11+'Support'!R25) | S8: =S7-('Engineering'!S11+'Support'!S25) | T8: =IF(COUNT(T7,'Engineering'!T11,'Support'!T25)=3,T7-('Engineering'!T11+'Support'!T25),"") | U8: =U7-('Engineering'!U11+'Support'!U25) | V8: =V7-('Engineering'!V11+'Support'!V25) | W8: =IF(COUNT(W7,'Engineering'!W11,'Support'!W25)=3,W7-('Engineering'!W11+'Support'!W25),"") | X8: =X7-('Engineering'!X11+'Support'!X25) | Y8: =Y7-('Engineering'!Y11+'Support'!Y25) | Z8: =IF(COUNT(Z7,'Engineering'!Z11,'Support'!Z25)=3,Z7-('Engineering'!Z11+'Support'!Z25),"") | AA8: =AA7-('Engineering'!AA11+'Support'!AA25) | AB8: =AB7-('Engineering'!AB11+'Support'!AB25) | AC8: =IF(COUNT(AC7,'Engineering'!AC11,'Support'!AC25)=3,AC7-('Engineering'!AC11+'Support'!AC25),"") | AD8: =AD7-('Engineering'!AD11+'Support'!AD25) | AE8: =AE7-('Engineering'!AE11+'Support'!AE25) | AF8: =IF(COUNT(AF7,'Engineering'!AF11,'Support'!AF25)=3,AF7-('Engineering'!AF11+'Support'!AF25),"") | AG8: =AG7-('Engineering'!AG11+'Support'!AG25) | AH8: =AH7-('Engineering'!AH11+'Support'!AH25) | AI8: =IF(COUNT(AI7,'Engineering'!AI11,'Support'!AI25)=3,AI7-('Engineering'!AI11+'Support'!AI25),"") | AJ8: =AJ7-('Engineering'!AJ11+'Support'!AJ25) | AK8: =AK7-('Engineering'!AK11+'Support'!AK25) | AL8: =IF(COUNT(AL7,'Engineering'!AL11,'Support'!AL25)=3,AL7-('Engineering'!AL11+'Support'!AL25),"") | AM8: =AM7-('Engineering'!AM11+'Support'!AM25) | AN8: =AN7-('Engineering'!AN11+'Support'!AN25) | AO8: =IF(COUNT(AO7,'Engineering'!AO11,'Support'!AO25)=3,AO7-('Engineering'!AO11+'Support'!AO25),"") | AP8: =AP7-('Engineering'!AP11+'Support'!AP25) | AQ8: =AQ7-('Engineering'!AQ11+'Support'!AQ25) | AR8: =IF(COUNT(AR7,'Engineering'!AR11,'Support'!AR25)=3,AR7-('Engineering'!AR11+'Support'!AR25),"") | AS8: =AS7-('Engineering'!AS11+'Support'!AS25) | AT8: =AT7-('Engineering'!AT11+'Support'!AT25) | AU8: =IF(COUNT(AU7,'Engineering'!AU11,'Support'!AU25)=3,AU7-('Engineering'!AU11+'Support'!AU25),"") | AV8: =AV7-('Engineering'!AV11+'Support'!AV25) | AW8: =AW7-('Engineering'!AW11+'Support'!AW25) | AX8: =IF(COUNT(AX7,'Engineering'!AX11,'Support'!AX25)=3,AX7-('Engineering'!AX11+'Support'!AX25),"") | AY8: =AY7-('Engineering'!AY11+'Support'!AY25) | AZ8: =AZ7-('Engineering'!AZ11+'Support'!AZ25) | BA8: =IF(COUNT(BA7,'Engineering'!BA11,'Support'!BA25)=3,BA7-('Engineering'!BA11+'Support'!BA25),"") | BB8: =BB7-('Engineering'!BB11+'Support'!BB25) | BC8: =BC7-('Engineering'!BC11+'Support'!BC25) | BD8: =IF(COUNT(BD7,'Engineering'!BD11,'Support'!BD25)=3,BD7-('Engineering'!BD11+'Support'!BD25),"") | BE8: =BE7-('Engineering'!BE11+'Support'!BE25) | BF8: =BF7-('Engineering'!BF11+'Support'!BF25) | BG8: =IF(COUNT(BG7,'Engineering'!BG11,'Support'!BG25)=3,BG7-('Engineering'!BG11+'Support'!BG25),"") | BH8: =BH7-('Engineering'!BH11+'Support'!BH25) | BI8: =BI7-('Engineering'!BI11+'Support'!BI25) | BJ8: =IF(COUNT(BJ7,'Engineering'!BJ11,'Support'!BJ25)=3,BJ7-('Engineering'!BJ11+'Support'!BJ25),"") | BK8: =BK7-('Engineering'!BK11+'Support'!BK25) | BL8: =BL7-('Engineering'!BL11+'Support'!BL25) | BM8: =IF(COUNT(BM7,'Engineering'!BM11,'Support'!BM25)=3,BM7-('Engineering'!BM11+'Support'!BM25),"") | BN8: =BN7-('Engineering'!BN11+'Support'!BN25) | BO8: =BO7-('Engineering'!BO11+'Support'!BO25) | BP8: =IF(COUNT(BP7,'Engineering'!BP11,'Support'!BP25)=3,BP7-('Engineering'!BP11+'Support'!BP25),"") | BQ8: =BQ7-('Engineering'!BQ11+'Support'!BQ25) | BR8: =BR7-('Engineering'!BR11+'Support'!BR25) | BS8: =IF(COUNT(BS7,'Engineering'!BS11,'Support'!BS25)=3,BS7-('Engineering'!BS11+'Support'!BS25),"") | BT8: =BT7-('Engineering'!BT11+'Support'!BT25) | BU8: =BU7-('Engineering'!BU11+'Support'!BU25) | BV8: =IF(COUNT(BV7,'Engineering'!BV11,'Support'!BV25)=3,BV7-('Engineering'!BV11+'Support'!BV25),"") | BW8: =BW7-('Engineering'!BW11+'Support'!BW25) | BX8: =BX7-('Engineering'!BX11+'Support'!BX25) | BY8: =IF(COUNT(BY7,'Engineering'!BY11,'Support'!BY25)=3,BY7-('Engineering'!BY11+'Support'!BY25),"") | BZ8: =BZ7-('Engineering'!BZ11+'Support'!BZ25) | CA8: =CA7-('Engineering'!CA11+'Support'!CA25) | CB8: =IF(COUNT(CB7,'Engineering'!CB11,'Support'!CB25)=3,CB7-('Engineering'!CB11+'Support'!CB25),"") | CC8: =CC7-('Engineering'!CC11+'Support'!CC25) | CD8: =CD7-('Engineering'!CD11+'Support'!CD25) | CE8: =IF(COUNT(CE7,'Engineering'!CE11,'Support'!CE25)=3,CE7-('Engineering'!CE11+'Support'!CE25),"") | CF8: =CF7-('Engineering'!CF11+'Support'!CF25) | CG8: =CG7-('Engineering'!CG11+'Support'!CG25) | CH8: =IF(COUNT(CH7,'Engineering'!CH11,'Support'!CH25)=3,CH7-('Engineering'!CH11+'Support'!CH25),"") | CI8: =CI7-('Engineering'!CI11+'Support'!CI25) | CJ8: =CJ7-('Engineering'!CJ11+'Support'!CJ25) | CK8: =IF(COUNT(CK7,'Engineering'!CK11,'Support'!CK25)=3,CK7-('Engineering'!CK11+'Support'!CK25),"") | CL8: =CL7-('Engineering'!CL11+'Support'!CL25) | CM8: =CM7-('Engineering'!CM11+'Support'!CM25) | CN8: =IF(COUNT(CN7,'Engineering'!CN11,'Support'!CN25)=3,CN7-('Engineering'!CN11+'Support'!CN25),"") | CO8: =CO7-('Engineering'!CO11+'Support'!CO25) | CP8: =CP7-('Engineering'!CP11+'Support'!CP25) | CQ8: =IF(COUNT(CQ7,'Engineering'!CQ11,'Support'!CQ25)=3,CQ7-('Engineering'!CQ11+'Support'!CQ25),"") | CR8: =CR7-('Engineering'!CR11+'Support'!CR25) | CS8: =CS7-('Engineering'!CS11+'Support'!CS25) | CT8: =IF(COUNT(CT7,'Engineering'!CT11,'Support'!CT25)=3,CT7-('Engineering'!CT11+'Support'!CT25),"") | CU8: =CU7-('Engineering'!CU11+'Support'!CU25) | CV8: =CV7-('Engineering'!CV11+'Support'!CV25) | CW8: =IF(COUNT(CW7,'Engineering'!CW11,'Support'!CW25)=3,CW7-('Engineering'!CW11+'Support'!CW25),"") | CX8: =CX7-('Engineering'!CX11+'Support'!CX25) | CY8: =CY7-('Engineering'!CY11+'Support'!CY25) | CZ8: =IF(COUNT(CZ7,'Engineering'!CZ11,'Support'!CZ25)=3,CZ7-('Engineering'!CZ11+'Support'!CZ25),"") | DA8: =DA7-('Engineering'!DA11+'Support'!DA25) | DB8: =DB7-('Engineering'!DB11+'Support'!DB25) | DC8: =IF(COUNT(DC7,'Engineering'!DC11,'Support'!DC25)=3,DC7-('Engineering'!DC11+'Support'!DC25),"") | DD8: =DD7-('Engineering'!DD11+'Support'!DD25) | DE8: =DE7-('Engineering'!DE11+'Support'!DE25) | DF8: =IF(COUNT(DF7,'Engineering'!DF11,'Support'!DF25)=3,DF7-('Engineering'!DF11+'Support'!DF25),"") | DG8: =DG7-('Engineering'!DG11+'Support'!DG25) | DH8: =DH7-('Engineering'!DH11+'Support'!DH25) | DI8: =IF(COUNT(DI7,'Engineering'!DI11,'Support'!DI25)=3,DI7-('Engineering'!DI11+'Support'!DI25),"") | DJ8: =DJ7-('Engineering'!DJ11+'Support'!DJ25) | DK8: =DK7-('Engineering'!DK11+'Support'!DK25) | DL8: =IF(COUNT(DL7,'Engineering'!DL11,'Support'!DL25)=3,DL7-('Engineering'!DL11+'Support'!DL25),"") | DM8: =DM7-('Engineering'!DM11+'Support'!DM25) | DN8: =DN7-('Engineering'!DN11+'Support'!DN25)
A9: Gross Margin | B9: =IF(N(B7)=0,"",B8/B7) | C9: =IF(N(C7)=0,"",C8/C7) | D9: =IF(N(D7)=0,"",D8/D7) | E9: =IF(N(E7)=0,"",E8/E7) | F9: =IF(N(F7)=0,"",F8/F7) | G9: =IF(N(G7)=0,"",G8/G7) | H9: =IF(N(H7)=0,"",H8/H7) | I9: =IF(N(I7)=0,"",I8/I7) | J9: =IF(N(J7)=0,"",J8/J7) | K9: =IF(COUNT(K7,K8)=2,IF(K7=0,"",K8/K7),"") | L9: =IF(L7=0,"",L8/L7) | M9: =IF(M7=0,"",M8/M7) | N9: =IF(COUNT(N7,N8)=2,IF(N7=0,"",N8/N7),"") | O9: =IF(O7=0,"",O8/O7) | P9: =IF(P7=0,"",P8/P7) | Q9: =IF(COUNT(Q7,Q8)=2,IF(Q7=0,"",Q8/Q7),"") | R9: =IF(R7=0,"",R8/R7) | S9: =IF(S7=0,"",S8/S7) | T9: =IF(COUNT(T7,T8)=2,IF(T7=0,"",T8/T7),"") | U9: =IF(U7=0,"",U8/U7) | V9: =IF(V7=0,"",V8/V7) | W9: =IF(COUNT(W7,W8)=2,IF(W7=0,"",W8/W7),"") | X9: =IF(X7=0,"",X8/X7) | Y9: =IF(Y7=0,"",Y8/Y7) | Z9: =IF(COUNT(Z7,Z8)=2,IF(Z7=0,"",Z8/Z7),"") | AA9: =IF(AA7=0,"",AA8/AA7) | AB9: =IF(AB7=0,"",AB8/AB7) | AC9: =IF(COUNT(AC7,AC8)=2,IF(AC7=0,"",AC8/AC7),"") | AD9: =IF(AD7=0,"",AD8/AD7) | AE9: =IF(AE7=0,"",AE8/AE7) | AF9: =IF(COUNT(AF7,AF8)=2,IF(AF7=0,"",AF8/AF7),"") | AG9: =IF(AG7=0,"",AG8/AG7) | AH9: =IF(AH7=0,"",AH8/AH7) | AI9: =IF(COUNT(AI7,AI8)=2,IF(AI7=0,"",AI8/AI7),"") | AJ9: =IF(AJ7=0,"",AJ8/AJ7) | AK9: =IF(AK7=0,"",AK8/AK7) | AL9: =IF(COUNT(AL7,AL8)=2,IF(AL7=0,"",AL8/AL7),"") | AM9: =IF(AM7=0,"",AM8/AM7) | AN9: =IF(AN7=0,"",AN8/AN7) | AO9: =IF(COUNT(AO7,AO8)=2,IF(AO7=0,"",AO8/AO7),"") | AP9: =IF(AP7=0,"",AP8/AP7) | AQ9: =IF(AQ7=0,"",AQ8/AQ7) | AR9: =IF(COUNT(AR7,AR8)=2,IF(AR7=0,"",AR8/AR7),"") | AS9: =IF(AS7=0,"",AS8/AS7) | AT9: =IF(AT7=0,"",AT8/AT7) | AU9: =IF(COUNT(AU7,AU8)=2,IF(AU7=0,"",AU8/AU7),"") | AV9: =IF(AV7=0,"",AV8/AV7) | AW9: =IF(AW7=0,"",AW8/AW7) | AX9: =IF(COUNT(AX7,AX8)=2,IF(AX7=0,"",AX8/AX7),"") | AY9: =IF(AY7=0,"",AY8/AY7) | AZ9: =IF(AZ7=0,"",AZ8/AZ7) | BA9: =IF(COUNT(BA7,BA8)=2,IF(BA7=0,"",BA8/BA7),"") | BB9: =IF(BB7=0,"",BB8/BB7) | BC9: =IF(BC7=0,"",BC8/BC7) | BD9: =IF(COUNT(BD7,BD8)=2,IF(BD7=0,"",BD8/BD7),"") | BE9: =IF(BE7=0,"",BE8/BE7) | BF9: =IF(BF7=0,"",BF8/BF7) | BG9: =IF(COUNT(BG7,BG8)=2,IF(BG7=0,"",BG8/BG7),"") | BH9: =IF(BH7=0,"",BH8/BH7) | BI9: =IF(BI7=0,"",BI8/BI7) | BJ9: =IF(COUNT(BJ7,BJ8)=2,IF(BJ7=0,"",BJ8/BJ7),"") | BK9: =IF(BK7=0,"",BK8/BK7) | BL9: =IF(BL7=0,"",BL8/BL7) | BM9: =IF(COUNT(BM7,BM8)=2,IF(BM7=0,"",BM8/BM7),"") | BN9: =IF(BN7=0,"",BN8/BN7) | BO9: =IF(BO7=0,"",BO8/BO7) | BP9: =IF(COUNT(BP7,BP8)=2,IF(BP7=0,"",BP8/BP7),"") | BQ9: =IF(BQ7=0,"",BQ8/BQ7) | BR9: =IF(BR7=0,"",BR8/BR7) | BS9: =IF(COUNT(BS7,BS8)=2,IF(BS7=0,"",BS8/BS7),"") | BT9: =IF(BT7=0,"",BT8/BT7) | BU9: =IF(BU7=0,"",BU8/BU7) | BV9: =IF(COUNT(BV7,BV8)=2,IF(BV7=0,"",BV8/BV7),"") | BW9: =IF(BW7=0,"",BW8/BW7) | BX9: =IF(BX7=0,"",BX8/BX7) | BY9: =IF(COUNT(BY7,BY8)=2,IF(BY7=0,"",BY8/BY7),"") | BZ9: =IF(BZ7=0,"",BZ8/BZ7) | CA9: =IF(CA7=0,"",CA8/CA7) | CB9: =IF(COUNT(CB7,CB8)=2,IF(CB7=0,"",CB8/CB7),"") | CC9: =IF(CC7=0,"",CC8/CC7) | CD9: =IF(CD7=0,"",CD8/CD7) | CE9: =IF(COUNT(CE7,CE8)=2,IF(CE7=0,"",CE8/CE7),"") | CF9: =IF(CF7=0,"",CF8/CF7) | CG9: =IF(CG7=0,"",CG8/CG7) | CH9: =IF(COUNT(CH7,CH8)=2,IF(CH7=0,"",CH8/CH7),"") | CI9: =IF(CI7=0,"",CI8/CI7) | CJ9: =IF(CJ7=0,"",CJ8/CJ7) | CK9: =IF(COUNT(CK7,CK8)=2,IF(CK7=0,"",CK8/CK7),"") | CL9: =IF(CL7=0,"",CL8/CL7) | CM9: =IF(CM7=0,"",CM8/CM7) | CN9: =IF(COUNT(CN7,CN8)=2,IF(CN7=0,"",CN8/CN7),"") | CO9: =IF(CO7=0,"",CO8/CO7) | CP9: =IF(CP7=0,"",CP8/CP7) | CQ9: =IF(COUNT(CQ7,CQ8)=2,IF(CQ7=0,"",CQ8/CQ7),"") | CR9: =IF(CR7=0,"",CR8/CR7) | CS9: =IF(CS7=0,"",CS8/CS7) | CT9: =IF(COUNT(CT7,CT8)=2,IF(CT7=0,"",CT8/CT7),"") | CU9: =IF(CU7=0,"",CU8/CU7) | CV9: =IF(CV7=0,"",CV8/CV7) | CW9: =IF(COUNT(CW7,CW8)=2,IF(CW7=0,"",CW8/CW7),"") | CX9: =IF(CX7=0,"",CX8/CX7) | CY9: =IF(CY7=0,"",CY8/CY7) | CZ9: =IF(COUNT(CZ7,CZ8)=2,IF(CZ7=0,"",CZ8/CZ7),"") | DA9: =IF(DA7=0,"",DA8/DA7) | DB9: =IF(DB7=0,"",DB8/DB7) | DC9: =IF(COUNT(DC7,DC8)=2,IF(DC7=0,"",DC8/DC7),"") | DD9: =IF(DD7=0,"",DD8/DD7) | DE9: =IF(DE7=0,"",DE8/DE7) | DF9: =IF(COUNT(DF7,DF8)=2,IF(DF7=0,"",DF8/DF7),"") | DG9: =IF(DG7=0,"",DG8/DG7) | DH9: =IF(DH7=0,"",DH8/DH7) | DI9: =IF(COUNT(DI7,DI8)=2,IF(DI7=0,"",DI8/DI7),"") | DJ9: =IF(DJ7=0,"",DJ8/DJ7) | DK9: =IF(DK7=0,"",DK8/DK7) | DL9: =IF(COUNT(DL7,DL8)=2,IF(DL7=0,"",DL8/DL7),"") | DM9: =IF(DM7=0,"",DM8/DM7) | DN9: =IF(DN7=0,"",DN8/DN7)
A10: Operating Expenses | B10: =IF(COUNT(AR10,AO10,AL10,AI10,AF10,AC10,Z10,W10,T10,Q10,N10,K10)=0,"",SUM(AR10,AO10,AL10,AI10,AF10,AC10,Z10,W10,T10,Q10,N10,K10)) | C10: =IF(COUNT(AS10,AP10,AM10,AJ10,AG10,AD10,AA10,X10,U10,R10,O10,L10)=0,"",SUM(AS10,AP10,AM10,AJ10,AG10,AD10,AA10,X10,U10,R10,O10,L10)) | D10: =IF(COUNT(AT10,AQ10,AN10,AK10,AH10,AE10,AB10,Y10,V10,S10,P10,M10)=0,"",SUM(AT10,AQ10,AN10,AK10,AH10,AE10,AB10,Y10,V10,S10,P10,M10)) | E10: =IF(COUNT(CB10,BY10,BV10,BS10,BP10,BM10,BJ10,BG10,BD10,BA10,AX10,AU10)=0,"",SUM(CB10,BY10,BV10,BS10,BP10,BM10,BJ10,BG10,BD10,BA10,AX10,AU10)) | F10: =IF(COUNT(CC10,BZ10,BW10,BT10,BQ10,BN10,BK10,BH10,BE10,BB10,AY10,AV10)=0,"",SUM(CC10,BZ10,BW10,BT10,BQ10,BN10,BK10,BH10,BE10,BB10,AY10,AV10)) | G10: =IF(COUNT(CD10,CA10,BX10,BU10,BR10,BO10,BL10,BI10,BF10,BC10,AZ10,AW10)=0,"",SUM(CD10,CA10,BX10,BU10,BR10,BO10,BL10,BI10,BF10,BC10,AZ10,AW10)) | H10: =IF(COUNT(DL10,DI10,DF10,DC10,CZ10,CW10,CT10,CQ10,CN10,CK10,CH10,CE10)=0,"",SUM(DL10,DI10,DF10,DC10,CZ10,CW10,CT10,CQ10,CN10,CK10,CH10,CE10)) | I10: =IF(COUNT(DM10,DJ10,DG10,DD10,DA10,CX10,CU10,CR10,CO10,CL10,CI10,CF10)=0,"",SUM(DM10,DJ10,DG10,DD10,DA10,CX10,CU10,CR10,CO10,CL10,CI10,CF10)) | J10: =IF(COUNT(DN10,DK10,DH10,DE10,DB10,CY10,CV10,CS10,CP10,CM10,CJ10,CG10)=0,"",SUM(DN10,DK10,DH10,DE10,DB10,CY10,CV10,CS10,CP10,CM10,CJ10,CG10)) | K10: =IF(COUNT('Marketing'!K28,'Sales'!K24,'Customer Success'!K33,'Engineering'!K27,'Finance'!K38,'Engineering'!K11)=6,'Marketing'!K28+'Sales'!K24+'Customer Success'!K33+'Engineering'!K27-'Engineering'!K11+'Finance'!K38,"") | L10: ='Marketing'!L28+'Sales'!L24+'Customer Success'!L33+'Engineering'!L27-'Engineering'!L11+'Finance'!L38 | M10: ='Marketing'!M28+'Sales'!M24+'Customer Success'!M33+'Engineering'!M27-'Engineering'!M11+'Finance'!M38 | N10: =IF(COUNT('Marketing'!N28,'Sales'!N24,'Customer Success'!N33,'Engineering'!N27,'Finance'!N38,'Engineering'!N11)=6,'Marketing'!N28+'Sales'!N24+'Customer Success'!N33+'Engineering'!N27-'Engineering'!N11+'Finance'!N38,"") | O10: ='Marketing'!O28+'Sales'!O24+'Customer Success'!O33+'Engineering'!O27-'Engineering'!O11+'Finance'!O38 | P10: ='Marketing'!P28+'Sales'!P24+'Customer Success'!P33+'Engineering'!P27-'Engineering'!P11+'Finance'!P38 | Q10: =IF(COUNT('Marketing'!Q28,'Sales'!Q24,'Customer Success'!Q33,'Engineering'!Q27,'Finance'!Q38,'Engineering'!Q11)=6,'Marketing'!Q28+'Sales'!Q24+'Customer Success'!Q33+'Engineering'!Q27-'Engineering'!Q11+'Finance'!Q38,"") | R10: ='Marketing'!R28+'Sales'!R24+'Customer Success'!R33+'Engineering'!R27-'Engineering'!R11+'Finance'!R38 | S10: ='Marketing'!S28+'Sales'!S24+'Customer Success'!S33+'Engineering'!S27-'Engineering'!S11+'Finance'!S38 | T10: =IF(COUNT('Marketing'!T28,'Sales'!T24,'Customer Success'!T33,'Engineering'!T27,'Finance'!T38,'Engineering'!T11)=6,'Marketing'!T28+'Sales'!T24+'Customer Success'!T33+'Engineering'!T27-'Engineering'!T11+'Finance'!T38,"") | U10: ='Marketing'!U28+'Sales'!U24+'Customer Success'!U33+'Engineering'!U27-'Engineering'!U11+'Finance'!U38 | V10: ='Marketing'!V28+'Sales'!V24+'Customer Success'!V33+'Engineering'!V27-'Engineering'!V11+'Finance'!V38 | W10: =IF(COUNT('Marketing'!W28,'Sales'!W24,'Customer Success'!W33,'Engineering'!W27,'Finance'!W38,'Engineering'!W11)=6,'Marketing'!W28+'Sales'!W24+'Customer Success'!W33+'Engineering'!W27-'Engineering'!W11+'Finance'!W38,"") | X10: ='Marketing'!X28+'Sales'!X24+'Customer Success'!X33+'Engineering'!X27-'Engineering'!X11+'Finance'!X38 | Y10: ='Marketing'!Y28+'Sales'!Y24+'Customer Success'!Y33+'Engineering'!Y27-'Engineering'!Y11+'Finance'!Y38 | Z10: =IF(COUNT('Marketing'!Z28,'Sales'!Z24,'Customer Success'!Z33,'Engineering'!Z27,'Finance'!Z38,'Engineering'!Z11)=6,'Marketing'!Z28+'Sales'!Z24+'Customer Success'!Z33+'Engineering'!Z27-'Engineering'!Z11+'Finance'!Z38,"") | AA10: ='Marketing'!AA28+'Sales'!AA24+'Customer Success'!AA33+'Engineering'!AA27-'Engineering'!AA11+'Finance'!AA38 | AB10: ='Marketing'!AB28+'Sales'!AB24+'Customer Success'!AB33+'Engineering'!AB27-'Engineering'!AB11+'Finance'!AB38 | AC10: =IF(COUNT('Marketing'!AC28,'Sales'!AC24,'Customer Success'!AC33,'Engineering'!AC27,'Finance'!AC38,'Engineering'!AC11)=6,'Marketing'!AC28+'Sales'!AC24+'Customer Success'!AC33+'Engineering'!AC27-'Engineering'!AC11+'Finance'!AC38,"") | AD10: ='Marketing'!AD28+'Sales'!AD24+'Customer Success'!AD33+'Engineering'!AD27-'Engineering'!AD11+'Finance'!AD38 | AE10: ='Marketing'!AE28+'Sales'!AE24+'Customer Success'!AE33+'Engineering'!AE27-'Engineering'!AE11+'Finance'!AE38 | AF10: =IF(COUNT('Marketing'!AF28,'Sales'!AF24,'Customer Success'!AF33,'Engineering'!AF27,'Finance'!AF38,'Engineering'!AF11)=6,'Marketing'!AF28+'Sales'!AF24+'Customer Success'!AF33+'Engineering'!AF27-'Engineering'!AF11+'Finance'!AF38,"") | AG10: ='Marketing'!AG28+'Sales'!AG24+'Customer Success'!AG33+'Engineering'!AG27-'Engineering'!AG11+'Finance'!AG38 | AH10: ='Marketing'!AH28+'Sales'!AH24+'Customer Success'!AH33+'Engineering'!AH27-'Engineering'!AH11+'Finance'!AH38 | AI10: =IF(COUNT('Marketing'!AI28,'Sales'!AI24,'Customer Success'!AI33,'Engineering'!AI27,'Finance'!AI38,'Engineering'!AI11)=6,'Marketing'!AI28+'Sales'!AI24+'Customer Success'!AI33+'Engineering'!AI27-'Engineering'!AI11+'Finance'!AI38,"") | AJ10: ='Marketing'!AJ28+'Sales'!AJ24+'Customer Success'!AJ33+'Engineering'!AJ27-'Engineering'!AJ11+'Finance'!AJ38 | AK10: ='Marketing'!AK28+'Sales'!AK24+'Customer Success'!AK33+'Engineering'!AK27-'Engineering'!AK11+'Finance'!AK38 | AL10: =IF(COUNT('Marketing'!AL28,'Sales'!AL24,'Customer Success'!AL33,'Engineering'!AL27,'Finance'!AL38,'Engineering'!AL11)=6,'Marketing'!AL28+'Sales'!AL24+'Customer Success'!AL33+'Engineering'!AL27-'Engineering'!AL11+'Finance'!AL38,"") | AM10: ='Marketing'!AM28+'Sales'!AM24+'Customer Success'!AM33+'Engineering'!AM27-'Engineering'!AM11+'Finance'!AM38 | AN10: ='Marketing'!AN28+'Sales'!AN24+'Customer Success'!AN33+'Engineering'!AN27-'Engineering'!AN11+'Finance'!AN38 | AO10: =IF(COUNT('Marketing'!AO28,'Sales'!AO24,'Customer Success'!AO33,'Engineering'!AO27,'Finance'!AO38,'Engineering'!AO11)=6,'Marketing'!AO28+'Sales'!AO24+'Customer Success'!AO33+'Engineering'!AO27-'Engineering'!AO11+'Finance'!AO38,"") | AP10: ='Marketing'!AP28+'Sales'!AP24+'Customer Success'!AP33+'Engineering'!AP27-'Engineering'!AP11+'Finance'!AP38 | AQ10: ='Marketing'!AQ28+'Sales'!AQ24+'Customer Success'!AQ33+'Engineering'!AQ27-'Engineering'!AQ11+'Finance'!AQ38 | AR10: =IF(COUNT('Marketing'!AR28,'Sales'!AR24,'Customer Success'!AR33,'Engineering'!AR27,'Finance'!AR38,'Engineering'!AR11)=6,'Marketing'!AR28+'Sales'!AR24+'Customer Success'!AR33+'Engineering'!AR27-'Engineering'!AR11+'Finance'!AR38,"") | AS10: ='Marketing'!AS28+'Sales'!AS24+'Customer Success'!AS33+'Engineering'!AS27-'Engineering'!AS11+'Finance'!AS38 | AT10: ='Marketing'!AT28+'Sales'!AT24+'Customer Success'!AT33+'Engineering'!AT27-'Engineering'!AT11+'Finance'!AT38 | AU10: =IF(COUNT('Marketing'!AU28,'Sales'!AU24,'Customer Success'!AU33,'Engineering'!AU27,'Finance'!AU38,'Engineering'!AU11)=6,'Marketing'!AU28+'Sales'!AU24+'Customer Success'!AU33+'Engineering'!AU27-'Engineering'!AU11+'Finance'!AU38,"") | AV10: ='Marketing'!AV28+'Sales'!AV24+'Customer Success'!AV33+'Engineering'!AV27-'Engineering'!AV11+'Finance'!AV38 | AW10: ='Marketing'!AW28+'Sales'!AW24+'Customer Success'!AW33+'Engineering'!AW27-'Engineering'!AW11+'Finance'!AW38 | AX10: =IF(COUNT('Marketing'!AX28,'Sales'!AX24,'Customer Success'!AX33,'Engineering'!AX27,'Finance'!AX38,'Engineering'!AX11)=6,'Marketing'!AX28+'Sales'!AX24+'Customer Success'!AX33+'Engineering'!AX27-'Engineering'!AX11+'Finance'!AX38,"") | AY10: ='Marketing'!AY28+'Sales'!AY24+'Customer Success'!AY33+'Engineering'!AY27-'Engineering'!AY11+'Finance'!AY38 | AZ10: ='Marketing'!AZ28+'Sales'!AZ24+'Customer Success'!AZ33+'Engineering'!AZ27-'Engineering'!AZ11+'Finance'!AZ38 | BA10: =IF(COUNT('Marketing'!BA28,'Sales'!BA24,'Customer Success'!BA33,'Engineering'!BA27,'Finance'!BA38,'Engineering'!BA11)=6,'Marketing'!BA28+'Sales'!BA24+'Customer Success'!BA33+'Engineering'!BA27-'Engineering'!BA11+'Finance'!BA38,"") | BB10: ='Marketing'!BB28+'Sales'!BB24+'Customer Success'!BB33+'Engineering'!BB27-'Engineering'!BB11+'Finance'!BB38 | BC10: ='Marketing'!BC28+'Sales'!BC24+'Customer Success'!BC33+'Engineering'!BC27-'Engineering'!BC11+'Finance'!BC38 | BD10: =IF(COUNT('Marketing'!BD28,'Sales'!BD24,'Customer Success'!BD33,'Engineering'!BD27,'Finance'!BD38,'Engineering'!BD11)=6,'Marketing'!BD28+'Sales'!BD24+'Customer Success'!BD33+'Engineering'!BD27-'Engineering'!BD11+'Finance'!BD38,"") | BE10: ='Marketing'!BE28+'Sales'!BE24+'Customer Success'!BE33+'Engineering'!BE27-'Engineering'!BE11+'Finance'!BE38 | BF10: ='Marketing'!BF28+'Sales'!BF24+'Customer Success'!BF33+'Engineering'!BF27-'Engineering'!BF11+'Finance'!BF38 | BG10: =IF(COUNT('Marketing'!BG28,'Sales'!BG24,'Customer Success'!BG33,'Engineering'!BG27,'Finance'!BG38,'Engineering'!BG11)=6,'Marketing'!BG28+'Sales'!BG24+'Customer Success'!BG33+'Engineering'!BG27-'Engineering'!BG11+'Finance'!BG38,"") | BH10: ='Marketing'!BH28+'Sales'!BH24+'Customer Success'!BH33+'Engineering'!BH27-'Engineering'!BH11+'Finance'!BH38 | BI10: ='Marketing'!BI28+'Sales'!BI24+'Customer Success'!BI33+'Engineering'!BI27-'Engineering'!BI11+'Finance'!BI38 | BJ10: =IF(COUNT('Marketing'!BJ28,'Sales'!BJ24,'Customer Success'!BJ33,'Engineering'!BJ27,'Finance'!BJ38,'Engineering'!BJ11)=6,'Marketing'!BJ28+'Sales'!BJ24+'Customer Success'!BJ33+'Engineering'!BJ27-'Engineering'!BJ11+'Finance'!BJ38,"") | BK10: ='Marketing'!BK28+'Sales'!BK24+'Customer Success'!BK33+'Engineering'!BK27-'Engineering'!BK11+'Finance'!BK38 | BL10: ='Marketing'!BL28+'Sales'!BL24+'Customer Success'!BL33+'Engineering'!BL27-'Engineering'!BL11+'Finance'!BL38 | BM10: =IF(COUNT('Marketing'!BM28,'Sales'!BM24,'Customer Success'!BM33,'Engineering'!BM27,'Finance'!BM38,'Engineering'!BM11)=6,'Marketing'!BM28+'Sales'!BM24+'Customer Success'!BM33+'Engineering'!BM27-'Engineering'!BM11+'Finance'!BM38,"") | BN10: ='Marketing'!BN28+'Sales'!BN24+'Customer Success'!BN33+'Engineering'!BN27-'Engineering'!BN11+'Finance'!BN38 | BO10: ='Marketing'!BO28+'Sales'!BO24+'Customer Success'!BO33+'Engineering'!BO27-'Engineering'!BO11+'Finance'!BO38 | BP10: =IF(COUNT('Marketing'!BP28,'Sales'!BP24,'Customer Success'!BP33,'Engineering'!BP27,'Finance'!BP38,'Engineering'!BP11)=6,'Marketing'!BP28+'Sales'!BP24+'Customer Success'!BP33+'Engineering'!BP27-'Engineering'!BP11+'Finance'!BP38,"") | BQ10: ='Marketing'!BQ28+'Sales'!BQ24+'Customer Success'!BQ33+'Engineering'!BQ27-'Engineering'!BQ11+'Finance'!BQ38 | BR10: ='Marketing'!BR28+'Sales'!BR24+'Customer Success'!BR33+'Engineering'!BR27-'Engineering'!BR11+'Finance'!BR38 | BS10: =IF(COUNT('Marketing'!BS28,'Sales'!BS24,'Customer Success'!BS33,'Engineering'!BS27,'Finance'!BS38,'Engineering'!BS11)=6,'Marketing'!BS28+'Sales'!BS24+'Customer Success'!BS33+'Engineering'!BS27-'Engineering'!BS11+'Finance'!BS38,"") | BT10: ='Marketing'!BT28+'Sales'!BT24+'Customer Success'!BT33+'Engineering'!BT27-'Engineering'!BT11+'Finance'!BT38 | BU10: ='Marketing'!BU28+'Sales'!BU24+'Customer Success'!BU33+'Engineering'!BU27-'Engineering'!BU11+'Finance'!BU38 | BV10: =IF(COUNT('Marketing'!BV28,'Sales'!BV24,'Customer Success'!BV33,'Engineering'!BV27,'Finance'!BV38,'Engineering'!BV11)=6,'Marketing'!BV28+'Sales'!BV24+'Customer Success'!BV33+'Engineering'!BV27-'Engineering'!BV11+'Finance'!BV38,"") | BW10: ='Marketing'!BW28+'Sales'!BW24+'Customer Success'!BW33+'Engineering'!BW27-'Engineering'!BW11+'Finance'!BW38 | BX10: ='Marketing'!BX28+'Sales'!BX24+'Customer Success'!BX33+'Engineering'!BX27-'Engineering'!BX11+'Finance'!BX38 | BY10: =IF(COUNT('Marketing'!BY28,'Sales'!BY24,'Customer Success'!BY33,'Engineering'!BY27,'Finance'!BY38,'Engineering'!BY11)=6,'Marketing'!BY28+'Sales'!BY24+'Customer Success'!BY33+'Engineering'!BY27-'Engineering'!BY11+'Finance'!BY38,"") | BZ10: ='Marketing'!BZ28+'Sales'!BZ24+'Customer Success'!BZ33+'Engineering'!BZ27-'Engineering'!BZ11+'Finance'!BZ38 | CA10: ='Marketing'!CA28+'Sales'!CA24+'Customer Success'!CA33+'Engineering'!CA27-'Engineering'!CA11+'Finance'!CA38 | CB10: =IF(COUNT('Marketing'!CB28,'Sales'!CB24,'Customer Success'!CB33,'Engineering'!CB27,'Finance'!CB38,'Engineering'!CB11)=6,'Marketing'!CB28+'Sales'!CB24+'Customer Success'!CB33+'Engineering'!CB27-'Engineering'!CB11+'Finance'!CB38,"") | CC10: ='Marketing'!CC28+'Sales'!CC24+'Customer Success'!CC33+'Engineering'!CC27-'Engineering'!CC11+'Finance'!CC38 | CD10: ='Marketing'!CD28+'Sales'!CD24+'Customer Success'!CD33+'Engineering'!CD27-'Engineering'!CD11+'Finance'!CD38 | CE10: =IF(COUNT('Marketing'!CE28,'Sales'!CE24,'Customer Success'!CE33,'Engineering'!CE27,'Finance'!CE38,'Engineering'!CE11)=6,'Marketing'!CE28+'Sales'!CE24+'Customer Success'!CE33+'Engineering'!CE27-'Engineering'!CE11+'Finance'!CE38,"") | CF10: ='Marketing'!CF28+'Sales'!CF24+'Customer Success'!CF33+'Engineering'!CF27-'Engineering'!CF11+'Finance'!CF38 | CG10: ='Marketing'!CG28+'Sales'!CG24+'Customer Success'!CG33+'Engineering'!CG27-'Engineering'!CG11+'Finance'!CG38 | CH10: =IF(COUNT('Marketing'!CH28,'Sales'!CH24,'Customer Success'!CH33,'Engineering'!CH27,'Finance'!CH38,'Engineering'!CH11)=6,'Marketing'!CH28+'Sales'!CH24+'Customer Success'!CH33+'Engineering'!CH27-'Engineering'!CH11+'Finance'!CH38,"") | CI10: ='Marketing'!CI28+'Sales'!CI24+'Customer Success'!CI33+'Engineering'!CI27-'Engineering'!CI11+'Finance'!CI38 | CJ10: ='Marketing'!CJ28+'Sales'!CJ24+'Customer Success'!CJ33+'Engineering'!CJ27-'Engineering'!CJ11+'Finance'!CJ38 | CK10: =IF(COUNT('Marketing'!CK28,'Sales'!CK24,'Customer Success'!CK33,'Engineering'!CK27,'Finance'!CK38,'Engineering'!CK11)=6,'Marketing'!CK28+'Sales'!CK24+'Customer Success'!CK33+'Engineering'!CK27-'Engineering'!CK11+'Finance'!CK38,"") | CL10: ='Marketing'!CL28+'Sales'!CL24+'Customer Success'!CL33+'Engineering'!CL27-'Engineering'!CL11+'Finance'!CL38 | CM10: ='Marketing'!CM28+'Sales'!CM24+'Customer Success'!CM33+'Engineering'!CM27-'Engineering'!CM11+'Finance'!CM38 | CN10: =IF(COUNT('Marketing'!CN28,'Sales'!CN24,'Customer Success'!CN33,'Engineering'!CN27,'Finance'!CN38,'Engineering'!CN11)=6,'Marketing'!CN28+'Sales'!CN24+'Customer Success'!CN33+'Engineering'!CN27-'Engineering'!CN11+'Finance'!CN38,"") | CO10: ='Marketing'!CO28+'Sales'!CO24+'Customer Success'!CO33+'Engineering'!CO27-'Engineering'!CO11+'Finance'!CO38 | CP10: ='Marketing'!CP28+'Sales'!CP24+'Customer Success'!CP33+'Engineering'!CP27-'Engineering'!CP11+'Finance'!CP38 | CQ10: =IF(COUNT('Marketing'!CQ28,'Sales'!CQ24,'Customer Success'!CQ33,'Engineering'!CQ27,'Finance'!CQ38,'Engineering'!CQ11)=6,'Marketing'!CQ28+'Sales'!CQ24+'Customer Success'!CQ33+'Engineering'!CQ27-'Engineering'!CQ11+'Finance'!CQ38,"") | CR10: ='Marketing'!CR28+'Sales'!CR24+'Customer Success'!CR33+'Engineering'!CR27-'Engineering'!CR11+'Finance'!CR38 | CS10: ='Marketing'!CS28+'Sales'!CS24+'Customer Success'!CS33+'Engineering'!CS27-'Engineering'!CS11+'Finance'!CS38 | CT10: =IF(COUNT('Marketing'!CT28,'Sales'!CT24,'Customer Success'!CT33,'Engineering'!CT27,'Finance'!CT38,'Engineering'!CT11)=6,'Marketing'!CT28+'Sales'!CT24+'Customer Success'!CT33+'Engineering'!CT27-'Engineering'!CT11+'Finance'!CT38,"") | CU10: ='Marketing'!CU28+'Sales'!CU24+'Customer Success'!CU33+'Engineering'!CU27-'Engineering'!CU11+'Finance'!CU38 | CV10: ='Marketing'!CV28+'Sales'!CV24+'Customer Success'!CV33+'Engineering'!CV27-'Engineering'!CV11+'Finance'!CV38 | CW10: =IF(COUNT('Marketing'!CW28,'Sales'!CW24,'Customer Success'!CW33,'Engineering'!CW27,'Finance'!CW38,'Engineering'!CW11)=6,'Marketing'!CW28+'Sales'!CW24+'Customer Success'!CW33+'Engineering'!CW27-'Engineering'!CW11+'Finance'!CW38,"") | CX10: ='Marketing'!CX28+'Sales'!CX24+'Customer Success'!CX33+'Engineering'!CX27-'Engineering'!CX11+'Finance'!CX38 | CY10: ='Marketing'!CY28+'Sales'!CY24+'Customer Success'!CY33+'Engineering'!CY27-'Engineering'!CY11+'Finance'!CY38 | CZ10: =IF(COUNT('Marketing'!CZ28,'Sales'!CZ24,'Customer Success'!CZ33,'Engineering'!CZ27,'Finance'!CZ38,'Engineering'!CZ11)=6,'Marketing'!CZ28+'Sales'!CZ24+'Customer Success'!CZ33+'Engineering'!CZ27-'Engineering'!CZ11+'Finance'!CZ38,"") | DA10: ='Marketing'!DA28+'Sales'!DA24+'Customer Success'!DA33+'Engineering'!DA27-'Engineering'!DA11+'Finance'!DA38 | DB10: ='Marketing'!DB28+'Sales'!DB24+'Customer Success'!DB33+'Engineering'!DB27-'Engineering'!DB11+'Finance'!DB38 | DC10: =IF(COUNT('Marketing'!DC28,'Sales'!DC24,'Customer Success'!DC33,'Engineering'!DC27,'Finance'!DC38,'Engineering'!DC11)=6,'Marketing'!DC28+'Sales'!DC24+'Customer Success'!DC33+'Engineering'!DC27-'Engineering'!DC11+'Finance'!DC38,"") | DD10: ='Marketing'!DD28+'Sales'!DD24+'Customer Success'!DD33+'Engineering'!DD27-'Engineering'!DD11+'Finance'!DD38 | DE10: ='Marketing'!DE28+'Sales'!DE24+'Customer Success'!DE33+'Engineering'!DE27-'Engineering'!DE11+'Finance'!DE38 | DF10: =IF(COUNT('Marketing'!DF28,'Sales'!DF24,'Customer Success'!DF33,'Engineering'!DF27,'Finance'!DF38,'Engineering'!DF11)=6,'Marketing'!DF28+'Sales'!DF24+'Customer Success'!DF33+'Engineering'!DF27-'Engineering'!DF11+'Finance'!DF38,"") | DG10: ='Marketing'!DG28+'Sales'!DG24+'Customer Success'!DG33+'Engineering'!DG27-'Engineering'!DG11+'Finance'!DG38 | DH10: ='Marketing'!DH28+'Sales'!DH24+'Customer Success'!DH33+'Engineering'!DH27-'Engineering'!DH11+'Finance'!DH38 | DI10: =IF(COUNT('Marketing'!DI28,'Sales'!DI24,'Customer Success'!DI33,'Engineering'!DI27,'Finance'!DI38,'Engineering'!DI11)=6,'Marketing'!DI28+'Sales'!DI24+'Customer Success'!DI33+'Engineering'!DI27-'Engineering'!DI11+'Finance'!DI38,"") | DJ10: ='Marketing'!DJ28+'Sales'!DJ24+'Customer Success'!DJ33+'Engineering'!DJ27-'Engineering'!DJ11+'Finance'!DJ38 | DK10: ='Marketing'!DK28+'Sales'!DK24+'Customer Success'!DK33+'Engineering'!DK27-'Engineering'!DK11+'Finance'!DK38 | DL10: =IF(COUNT('Marketing'!DL28,'Sales'!DL24,'Customer Success'!DL33,'Engineering'!DL27,'Finance'!DL38,'Engineering'!DL11)=6,'Marketing'!DL28+'Sales'!DL24+'Customer Success'!DL33+'Engineering'!DL27-'Engineering'!DL11+'Finance'!DL38,"") | DM10: ='Marketing'!DM28+'Sales'!DM24+'Customer Success'!DM33+'Engineering'!DM27-'Engineering'!DM11+'Finance'!DM38 | DN10: ='Marketing'!DN28+'Sales'!DN24+'Customer Success'!DN33+'Engineering'!DN27-'Engineering'!DN11+'Finance'!DN38
A11: Depreciation | B11: =IF(COUNT(AR11,AO11,AL11,AI11,AF11,AC11,Z11,W11,T11,Q11,N11,K11)=0,"",SUM(AR11,AO11,AL11,AI11,AF11,AC11,Z11,W11,T11,Q11,N11,K11)) | C11: =IF(COUNT(AS11,AP11,AM11,AJ11,AG11,AD11,AA11,X11,U11,R11,O11,L11)=0,"",SUM(AS11,AP11,AM11,AJ11,AG11,AD11,AA11,X11,U11,R11,O11,L11)) | D11: =IF(COUNT(AT11,AQ11,AN11,AK11,AH11,AE11,AB11,Y11,V11,S11,P11,M11)=0,"",SUM(AT11,AQ11,AN11,AK11,AH11,AE11,AB11,Y11,V11,S11,P11,M11)) | E11: =IF(COUNT(CB11,BY11,BV11,BS11,BP11,BM11,BJ11,BG11,BD11,BA11,AX11,AU11)=0,"",SUM(CB11,BY11,BV11,BS11,BP11,BM11,BJ11,BG11,BD11,BA11,AX11,AU11)) | F11: =IF(COUNT(CC11,BZ11,BW11,BT11,BQ11,BN11,BK11,BH11,BE11,BB11,AY11,AV11)=0,"",SUM(CC11,BZ11,BW11,BT11,BQ11,BN11,BK11,BH11,BE11,BB11,AY11,AV11)) | G11: =IF(COUNT(CD11,CA11,BX11,BU11,BR11,BO11,BL11,BI11,BF11,BC11,AZ11,AW11)=0,"",SUM(CD11,CA11,BX11,BU11,BR11,BO11,BL11,BI11,BF11,BC11,AZ11,AW11)) | H11: =IF(COUNT(DL11,DI11,DF11,DC11,CZ11,CW11,CT11,CQ11,CN11,CK11,CH11,CE11)=0,"",SUM(DL11,DI11,DF11,DC11,CZ11,CW11,CT11,CQ11,CN11,CK11,CH11,CE11)) | I11: =IF(COUNT(DM11,DJ11,DG11,DD11,DA11,CX11,CU11,CR11,CO11,CL11,CI11,CF11)=0,"",SUM(DM11,DJ11,DG11,DD11,DA11,CX11,CU11,CR11,CO11,CL11,CI11,CF11)) | J11: =IF(COUNT(DN11,DK11,DH11,DE11,DB11,CY11,CV11,CS11,CP11,CM11,CJ11,CG11)=0,"",SUM(DN11,DK11,DH11,DE11,DB11,CY11,CV11,CS11,CP11,CM11,CJ11,CG11)) | K11: =IF(COUNT('Finance'!K20)=1,'Finance'!K20,"") | L11: ='Finance'!L20 | M11: ='Finance'!M20 | N11: =IF(COUNT('Finance'!N20)=1,'Finance'!N20,"") | O11: ='Finance'!O20 | P11: ='Finance'!P20 | Q11: =IF(COUNT('Finance'!Q20)=1,'Finance'!Q20,"") | R11: ='Finance'!R20 | S11: ='Finance'!S20 | T11: =IF(COUNT('Finance'!T20)=1,'Finance'!T20,"") | U11: ='Finance'!U20 | V11: ='Finance'!V20 | W11: =IF(COUNT('Finance'!W20)=1,'Finance'!W20,"") | X11: ='Finance'!X20 | Y11: ='Finance'!Y20 | Z11: =IF(COUNT('Finance'!Z20)=1,'Finance'!Z20,"") | AA11: ='Finance'!AA20 | AB11: ='Finance'!AB20 | AC11: =IF(COUNT('Finance'!AC20)=1,'Finance'!AC20,"") | AD11: ='Finance'!AD20 | AE11: ='Finance'!AE20 | AF11: =IF(COUNT('Finance'!AF20)=1,'Finance'!AF20,"") | AG11: ='Finance'!AG20 | AH11: ='Finance'!AH20 | AI11: =IF(COUNT('Finance'!AI20)=1,'Finance'!AI20,"") | AJ11: ='Finance'!AJ20 | AK11: ='Finance'!AK20 | AL11: =IF(COUNT('Finance'!AL20)=1,'Finance'!AL20,"") | AM11: ='Finance'!AM20 | AN11: ='Finance'!AN20 | AO11: =IF(COUNT('Finance'!AO20)=1,'Finance'!AO20,"") | AP11: ='Finance'!AP20 | AQ11: ='Finance'!AQ20 | AR11: =IF(COUNT('Finance'!AR20)=1,'Finance'!AR20,"") | AS11: ='Finance'!AS20 | AT11: ='Finance'!AT20 | AU11: =IF(COUNT('Finance'!AU20)=1,'Finance'!AU20,"") | AV11: ='Finance'!AV20 | AW11: ='Finance'!AW20 | AX11: =IF(COUNT('Finance'!AX20)=1,'Finance'!AX20,"") | AY11: ='Finance'!AY20 | AZ11: ='Finance'!AZ20 | BA11: =IF(COUNT('Finance'!BA20)=1,'Finance'!BA20,"") | BB11: ='Finance'!BB20 | BC11: ='Finance'!BC20 | BD11: =IF(COUNT('Finance'!BD20)=1,'Finance'!BD20,"") | BE11: ='Finance'!BE20 | BF11: ='Finance'!BF20 | BG11: =IF(COUNT('Finance'!BG20)=1,'Finance'!BG20,"") | BH11: ='Finance'!BH20 | BI11: ='Finance'!BI20 | BJ11: =IF(COUNT('Finance'!BJ20)=1,'Finance'!BJ20,"") | BK11: ='Finance'!BK20 | BL11: ='Finance'!BL20 | BM11: =IF(COUNT('Finance'!BM20)=1,'Finance'!BM20,"") | BN11: ='Finance'!BN20 | BO11: ='Finance'!BO20 | BP11: =IF(COUNT('Finance'!BP20)=1,'Finance'!BP20,"") | BQ11: ='Finance'!BQ20 | BR11: ='Finance'!BR20 | BS11: =IF(COUNT('Finance'!BS20)=1,'Finance'!BS20,"") | BT11: ='Finance'!BT20 | BU11: ='Finance'!BU20 | BV11: =IF(COUNT('Finance'!BV20)=1,'Finance'!BV20,"") | BW11: ='Finance'!BW20 | BX11: ='Finance'!BX20 | BY11: =IF(COUNT('Finance'!BY20)=1,'Finance'!BY20,"") | BZ11: ='Finance'!BZ20 | CA11: ='Finance'!CA20 | CB11: =IF(COUNT('Finance'!CB20)=1,'Finance'!CB20,"") | CC11: ='Finance'!CC20 | CD11: ='Finance'!CD20 | CE11: =IF(COUNT('Finance'!CE20)=1,'Finance'!CE20,"") | CF11: ='Finance'!CF20 | CG11: ='Finance'!CG20 | CH11: =IF(COUNT('Finance'!CH20)=1,'Finance'!CH20,"") | CI11: ='Finance'!CI20 | CJ11: ='Finance'!CJ20 | CK11: =IF(COUNT('Finance'!CK20)=1,'Finance'!CK20,"") | CL11: ='Finance'!CL20 | CM11: ='Finance'!CM20 | CN11: =IF(COUNT('Finance'!CN20)=1,'Finance'!CN20,"") | CO11: ='Finance'!CO20 | CP11: ='Finance'!CP20 | CQ11: =IF(COUNT('Finance'!CQ20)=1,'Finance'!CQ20,"") | CR11: ='Finance'!CR20 | CS11: ='Finance'!CS20 | CT11: =IF(COUNT('Finance'!CT20)=1,'Finance'!CT20,"") | CU11: ='Finance'!CU20 | CV11: ='Finance'!CV20 | CW11: =IF(COUNT('Finance'!CW20)=1,'Finance'!CW20,"") | CX11: ='Finance'!CX20 | CY11: ='Finance'!CY20 | CZ11: =IF(COUNT('Finance'!CZ20)=1,'Finance'!CZ20,"") | DA11: ='Finance'!DA20 | DB11: ='Finance'!DB20 | DC11: =IF(COUNT('Finance'!DC20)=1,'Finance'!DC20,"") | DD11: ='Finance'!DD20 | DE11: ='Finance'!DE20 | DF11: =IF(COUNT('Finance'!DF20)=1,'Finance'!DF20,"") | DG11: ='Finance'!DG20 | DH11: ='Finance'!DH20 | DI11: =IF(COUNT('Finance'!DI20)=1,'Finance'!DI20,"") | DJ11: ='Finance'!DJ20 | DK11: ='Finance'!DK20 | DL11: =IF(COUNT('Finance'!DL20)=1,'Finance'!DL20,"") | DM11: ='Finance'!DM20 | DN11: ='Finance'!DN20
A12: Operating Profit | B12: =IF(COUNT(B8,B10)<2,"",B8-B10-N(B11)) | C12: =IF(COUNT(C8,C10)<2,"",C8-C10-N(C11)) | D12: =IF(COUNT(D8,D10)<2,"",D8-D10-N(D11)) | E12: =IF(COUNT(E8,E10)<2,"",E8-E10-N(E11)) | F12: =IF(COUNT(F8,F10)<2,"",F8-F10-N(F11)) | G12: =IF(COUNT(G8,G10)<2,"",G8-G10-N(G11)) | H12: =IF(COUNT(H8,H10)<2,"",H8-H10-N(H11)) | I12: =IF(COUNT(I8,I10)<2,"",I8-I10-N(I11)) | J12: =IF(COUNT(J8,J10)<2,"",J8-J10-N(J11)) | K12: =IF(COUNT(K8,K10,K11)=3,K8-K10-K11,"") | L12: =L8-L10-L11 | M12: =M8-M10-M11 | N12: =IF(COUNT(N8,N10,N11)=3,N8-N10-N11,"") | O12: =O8-O10-O11 | P12: =P8-P10-P11 | Q12: =IF(COUNT(Q8,Q10,Q11)=3,Q8-Q10-Q11,"") | R12: =R8-R10-R11 | S12: =S8-S10-S11 | T12: =IF(COUNT(T8,T10,T11)=3,T8-T10-T11,"") | U12: =U8-U10-U11 | V12: =V8-V10-V11 | W12: =IF(COUNT(W8,W10,W11)=3,W8-W10-W11,"") | X12: =X8-X10-X11 | Y12: =Y8-Y10-Y11 | Z12: =IF(COUNT(Z8,Z10,Z11)=3,Z8-Z10-Z11,"") | AA12: =AA8-AA10-AA11 | AB12: =AB8-AB10-AB11 | AC12: =IF(COUNT(AC8,AC10,AC11)=3,AC8-AC10-AC11,"") | AD12: =AD8-AD10-AD11 | AE12: =AE8-AE10-AE11 | AF12: =IF(COUNT(AF8,AF10,AF11)=3,AF8-AF10-AF11,"") | AG12: =AG8-AG10-AG11 | AH12: =AH8-AH10-AH11 | AI12: =IF(COUNT(AI8,AI10,AI11)=3,AI8-AI10-AI11,"") | AJ12: =AJ8-AJ10-AJ11 | AK12: =AK8-AK10-AK11 | AL12: =IF(COUNT(AL8,AL10,AL11)=3,AL8-AL10-AL11,"") | AM12: =AM8-AM10-AM11 | AN12: =AN8-AN10-AN11 | AO12: =IF(COUNT(AO8,AO10,AO11)=3,AO8-AO10-AO11,"") | AP12: =AP8-AP10-AP11 | AQ12: =AQ8-AQ10-AQ11 | AR12: =IF(COUNT(AR8,AR10,AR11)=3,AR8-AR10-AR11,"") | AS12: =AS8-AS10-AS11 | AT12: =AT8-AT10-AT11 | AU12: =IF(COUNT(AU8,AU10,AU11)=3,AU8-AU10-AU11,"") | AV12: =AV8-AV10-AV11 | AW12: =AW8-AW10-AW11 | AX12: =IF(COUNT(AX8,AX10,AX11)=3,AX8-AX10-AX11,"") | AY12: =AY8-AY10-AY11 | AZ12: =AZ8-AZ10-AZ11 | BA12: =IF(COUNT(BA8,BA10,BA11)=3,BA8-BA10-BA11,"") | BB12: =BB8-BB10-BB11 | BC12: =BC8-BC10-BC11 | BD12: =IF(COUNT(BD8,BD10,BD11)=3,BD8-BD10-BD11,"") | BE12: =BE8-BE10-BE11 | BF12: =BF8-BF10-BF11 | BG12: =IF(COUNT(BG8,BG10,BG11)=3,BG8-BG10-BG11,"") | BH12: =BH8-BH10-BH11 | BI12: =BI8-BI10-BI11 | BJ12: =IF(COUNT(BJ8,BJ10,BJ11)=3,BJ8-BJ10-BJ11,"") | BK12: =BK8-BK10-BK11 | BL12: =BL8-BL10-BL11 | BM12: =IF(COUNT(BM8,BM10,BM11)=3,BM8-BM10-BM11,"") | BN12: =BN8-BN10-BN11 | BO12: =BO8-BO10-BO11 | BP12: =IF(COUNT(BP8,BP10,BP11)=3,BP8-BP10-BP11,"") | BQ12: =BQ8-BQ10-BQ11 | BR12: =BR8-BR10-BR11 | BS12: =IF(COUNT(BS8,BS10,BS11)=3,BS8-BS10-BS11,"") | BT12: =BT8-BT10-BT11 | BU12: =BU8-BU10-BU11 | BV12: =IF(COUNT(BV8,BV10,BV11)=3,BV8-BV10-BV11,"") | BW12: =BW8-BW10-BW11 | BX12: =BX8-BX10-BX11 | BY12: =IF(COUNT(BY8,BY10,BY11)=3,BY8-BY10-BY11,"") | BZ12: =BZ8-BZ10-BZ11 | CA12: =CA8-CA10-CA11 | CB12: =IF(COUNT(CB8,CB10,CB11)=3,CB8-CB10-CB11,"") | CC12: =CC8-CC10-CC11 | CD12: =CD8-CD10-CD11 | CE12: =IF(COUNT(CE8,CE10,CE11)=3,CE8-CE10-CE11,"") | CF12: =CF8-CF10-CF11 | CG12: =CG8-CG10-CG11 | CH12: =IF(COUNT(CH8,CH10,CH11)=3,CH8-CH10-CH11,"") | CI12: =CI8-CI10-CI11 | CJ12: =CJ8-CJ10-CJ11 | CK12: =IF(COUNT(CK8,CK10,CK11)=3,CK8-CK10-CK11,"") | CL12: =CL8-CL10-CL11 | CM12: =CM8-CM10-CM11 | CN12: =IF(COUNT(CN8,CN10,CN11)=3,CN8-CN10-CN11,"") | CO12: =CO8-CO10-CO11 | CP12: =CP8-CP10-CP11 | CQ12: =IF(COUNT(CQ8,CQ10,CQ11)=3,CQ8-CQ10-CQ11,"") | CR12: =CR8-CR10-CR11 | CS12: =CS8-CS10-CS11 | CT12: =IF(COUNT(CT8,CT10,CT11)=3,CT8-CT10-CT11,"") | CU12: =CU8-CU10-CU11 | CV12: =CV8-CV10-CV11 | CW12: =IF(COUNT(CW8,CW10,CW11)=3,CW8-CW10-CW11,"") | CX12: =CX8-CX10-CX11 | CY12: =CY8-CY10-CY11 | CZ12: =IF(COUNT(CZ8,CZ10,CZ11)=3,CZ8-CZ10-CZ11,"") | DA12: =DA8-DA10-DA11 | DB12: =DB8-DB10-DB11 | DC12: =IF(COUNT(DC8,DC10,DC11)=3,DC8-DC10-DC11,"") | DD12: =DD8-DD10-DD11 | DE12: =DE8-DE10-DE11 | DF12: =IF(COUNT(DF8,DF10,DF11)=3,DF8-DF10-DF11,"") | DG12: =DG8-DG10-DG11 | DH12: =DH8-DH10-DH11 | DI12: =IF(COUNT(DI8,DI10,DI11)=3,DI8-DI10-DI11,"") | DJ12: =DJ8-DJ10-DJ11 | DK12: =DK8-DK10-DK11 | DL12: =IF(COUNT(DL8,DL10,DL11)=3,DL8-DL10-DL11,"") | DM12: =DM8-DM10-DM11 | DN12: =DN8-DN10-DN11
A13: Operating Margin | B13: =IF(N(B7)=0,"",B12/B7) | C13: =IF(N(C7)=0,"",C12/C7) | D13: =IF(N(D7)=0,"",D12/D7) | E13: =IF(N(E7)=0,"",E12/E7) | F13: =IF(N(F7)=0,"",F12/F7) | G13: =IF(N(G7)=0,"",G12/G7) | H13: =IF(N(H7)=0,"",H12/H7) | I13: =IF(N(I7)=0,"",I12/I7) | J13: =IF(N(J7)=0,"",J12/J7) | K13: =IF(COUNT(K7,K12)=2,IF(K7=0,"",K12/K7),"") | L13: =IF(L7=0,"",L12/L7) | M13: =IF(M7=0,"",M12/M7) | N13: =IF(COUNT(N7,N12)=2,IF(N7=0,"",N12/N7),"") | O13: =IF(O7=0,"",O12/O7) | P13: =IF(P7=0,"",P12/P7) | Q13: =IF(COUNT(Q7,Q12)=2,IF(Q7=0,"",Q12/Q7),"") | R13: =IF(R7=0,"",R12/R7) | S13: =IF(S7=0,"",S12/S7) | T13: =IF(COUNT(T7,T12)=2,IF(T7=0,"",T12/T7),"") | U13: =IF(U7=0,"",U12/U7) | V13: =IF(V7=0,"",V12/V7) | W13: =IF(COUNT(W7,W12)=2,IF(W7=0,"",W12/W7),"") | X13: =IF(X7=0,"",X12/X7) | Y13: =IF(Y7=0,"",Y12/Y7) | Z13: =IF(COUNT(Z7,Z12)=2,IF(Z7=0,"",Z12/Z7),"") | AA13: =IF(AA7=0,"",AA12/AA7) | AB13: =IF(AB7=0,"",AB12/AB7) | AC13: =IF(COUNT(AC7,AC12)=2,IF(AC7=0,"",AC12/AC7),"") | AD13: =IF(AD7=0,"",AD12/AD7) | AE13: =IF(AE7=0,"",AE12/AE7) | AF13: =IF(COUNT(AF7,AF12)=2,IF(AF7=0,"",AF12/AF7),"") | AG13: =IF(AG7=0,"",AG12/AG7) | AH13: =IF(AH7=0,"",AH12/AH7) | AI13: =IF(COUNT(AI7,AI12)=2,IF(AI7=0,"",AI12/AI7),"") | AJ13: =IF(AJ7=0,"",AJ12/AJ7) | AK13: =IF(AK7=0,"",AK12/AK7) | AL13: =IF(COUNT(AL7,AL12)=2,IF(AL7=0,"",AL12/AL7),"") | AM13: =IF(AM7=0,"",AM12/AM7) | AN13: =IF(AN7=0,"",AN12/AN7) | AO13: =IF(COUNT(AO7,AO12)=2,IF(AO7=0,"",AO12/AO7),"") | AP13: =IF(AP7=0,"",AP12/AP7) | AQ13: =IF(AQ7=0,"",AQ12/AQ7) | AR13: =IF(COUNT(AR7,AR12)=2,IF(AR7=0,"",AR12/AR7),"") | AS13: =IF(AS7=0,"",AS12/AS7) | AT13: =IF(AT7=0,"",AT12/AT7) | AU13: =IF(COUNT(AU7,AU12)=2,IF(AU7=0,"",AU12/AU7),"") | AV13: =IF(AV7=0,"",AV12/AV7) | AW13: =IF(AW7=0,"",AW12/AW7) | AX13: =IF(COUNT(AX7,AX12)=2,IF(AX7=0,"",AX12/AX7),"") | AY13: =IF(AY7=0,"",AY12/AY7) | AZ13: =IF(AZ7=0,"",AZ12/AZ7) | BA13: =IF(COUNT(BA7,BA12)=2,IF(BA7=0,"",BA12/BA7),"") | BB13: =IF(BB7=0,"",BB12/BB7) | BC13: =IF(BC7=0,"",BC12/BC7) | BD13: =IF(COUNT(BD7,BD12)=2,IF(BD7=0,"",BD12/BD7),"") | BE13: =IF(BE7=0,"",BE12/BE7) | BF13: =IF(BF7=0,"",BF12/BF7) | BG13: =IF(COUNT(BG7,BG12)=2,IF(BG7=0,"",BG12/BG7),"") | BH13: =IF(BH7=0,"",BH12/BH7) | BI13: =IF(BI7=0,"",BI12/BI7) | BJ13: =IF(COUNT(BJ7,BJ12)=2,IF(BJ7=0,"",BJ12/BJ7),"") | BK13: =IF(BK7=0,"",BK12/BK7) | BL13: =IF(BL7=0,"",BL12/BL7) | BM13: =IF(COUNT(BM7,BM12)=2,IF(BM7=0,"",BM12/BM7),"") | BN13: =IF(BN7=0,"",BN12/BN7) | BO13: =IF(BO7=0,"",BO12/BO7) | BP13: =IF(COUNT(BP7,BP12)=2,IF(BP7=0,"",BP12/BP7),"") | BQ13: =IF(BQ7=0,"",BQ12/BQ7) | BR13: =IF(BR7=0,"",BR12/BR7) | BS13: =IF(COUNT(BS7,BS12)=2,IF(BS7=0,"",BS12/BS7),"") | BT13: =IF(BT7=0,"",BT12/BT7) | BU13: =IF(BU7=0,"",BU12/BU7) | BV13: =IF(COUNT(BV7,BV12)=2,IF(BV7=0,"",BV12/BV7),"") | BW13: =IF(BW7=0,"",BW12/BW7) | BX13: =IF(BX7=0,"",BX12/BX7) | BY13: =IF(COUNT(BY7,BY12)=2,IF(BY7=0,"",BY12/BY7),"") | BZ13: =IF(BZ7=0,"",BZ12/BZ7) | CA13: =IF(CA7=0,"",CA12/CA7) | CB13: =IF(COUNT(CB7,CB12)=2,IF(CB7=0,"",CB12/CB7),"") | CC13: =IF(CC7=0,"",CC12/CC7) | CD13: =IF(CD7=0,"",CD12/CD7) | CE13: =IF(COUNT(CE7,CE12)=2,IF(CE7=0,"",CE12/CE7),"") | CF13: =IF(CF7=0,"",CF12/CF7) | CG13: =IF(CG7=0,"",CG12/CG7) | CH13: =IF(COUNT(CH7,CH12)=2,IF(CH7=0,"",CH12/CH7),"") | CI13: =IF(CI7=0,"",CI12/CI7) | CJ13: =IF(CJ7=0,"",CJ12/CJ7) | CK13: =IF(COUNT(CK7,CK12)=2,IF(CK7=0,"",CK12/CK7),"") | CL13: =IF(CL7=0,"",CL12/CL7) | CM13: =IF(CM7=0,"",CM12/CM7) | CN13: =IF(COUNT(CN7,CN12)=2,IF(CN7=0,"",CN12/CN7),"") | CO13: =IF(CO7=0,"",CO12/CO7) | CP13: =IF(CP7=0,"",CP12/CP7) | CQ13: =IF(COUNT(CQ7,CQ12)=2,IF(CQ7=0,"",CQ12/CQ7),"") | CR13: =IF(CR7=0,"",CR12/CR7) | CS13: =IF(CS7=0,"",CS12/CS7) | CT13: =IF(COUNT(CT7,CT12)=2,IF(CT7=0,"",CT12/CT7),"") | CU13: =IF(CU7=0,"",CU12/CU7) | CV13: =IF(CV7=0,"",CV12/CV7) | CW13: =IF(COUNT(CW7,CW12)=2,IF(CW7=0,"",CW12/CW7),"") | CX13: =IF(CX7=0,"",CX12/CX7) | CY13: =IF(CY7=0,"",CY12/CY7) | CZ13: =IF(COUNT(CZ7,CZ12)=2,IF(CZ7=0,"",CZ12/CZ7),"") | DA13: =IF(DA7=0,"",DA12/DA7) | DB13: =IF(DB7=0,"",DB12/DB7) | DC13: =IF(COUNT(DC7,DC12)=2,IF(DC7=0,"",DC12/DC7),"") | DD13: =IF(DD7=0,"",DD12/DD7) | DE13: =IF(DE7=0,"",DE12/DE7) | DF13: =IF(COUNT(DF7,DF12)=2,IF(DF7=0,"",DF12/DF7),"") | DG13: =IF(DG7=0,"",DG12/DG7) | DH13: =IF(DH7=0,"",DH12/DH7) | DI13: =IF(COUNT(DI7,DI12)=2,IF(DI7=0,"",DI12/DI7),"") | DJ13: =IF(DJ7=0,"",DJ12/DJ7) | DK13: =IF(DK7=0,"",DK12/DK7) | DL13: =IF(COUNT(DL7,DL12)=2,IF(DL7=0,"",DL12/DL7),"") | DM13: =IF(DM7=0,"",DM12/DM7) | DN13: =IF(DN7=0,"",DN12/DN7)
A14: Income Tax | B14: =IF(COUNT(AR14,AO14,AL14,AI14,AF14,AC14,Z14,W14,T14,Q14,N14,K14)=0,"",SUM(AR14,AO14,AL14,AI14,AF14,AC14,Z14,W14,T14,Q14,N14,K14)) | C14: =IF(COUNT(AS14,AP14,AM14,AJ14,AG14,AD14,AA14,X14,U14,R14,O14,L14)=0,"",SUM(AS14,AP14,AM14,AJ14,AG14,AD14,AA14,X14,U14,R14,O14,L14)) | D14: =IF(COUNT(AT14,AQ14,AN14,AK14,AH14,AE14,AB14,Y14,V14,S14,P14,M14)=0,"",SUM(AT14,AQ14,AN14,AK14,AH14,AE14,AB14,Y14,V14,S14,P14,M14)) | E14: =IF(COUNT(CB14,BY14,BV14,BS14,BP14,BM14,BJ14,BG14,BD14,BA14,AX14,AU14)=0,"",SUM(CB14,BY14,BV14,BS14,BP14,BM14,BJ14,BG14,BD14,BA14,AX14,AU14)) | F14: =IF(COUNT(CC14,BZ14,BW14,BT14,BQ14,BN14,BK14,BH14,BE14,BB14,AY14,AV14)=0,"",SUM(CC14,BZ14,BW14,BT14,BQ14,BN14,BK14,BH14,BE14,BB14,AY14,AV14)) | G14: =IF(COUNT(CD14,CA14,BX14,BU14,BR14,BO14,BL14,BI14,BF14,BC14,AZ14,AW14)=0,"",SUM(CD14,CA14,BX14,BU14,BR14,BO14,BL14,BI14,BF14,BC14,AZ14,AW14)) | H14: =IF(COUNT(DL14,DI14,DF14,DC14,CZ14,CW14,CT14,CQ14,CN14,CK14,CH14,CE14)=0,"",SUM(DL14,DI14,DF14,DC14,CZ14,CW14,CT14,CQ14,CN14,CK14,CH14,CE14)) | I14: =IF(COUNT(DM14,DJ14,DG14,DD14,DA14,CX14,CU14,CR14,CO14,CL14,CI14,CF14)=0,"",SUM(DM14,DJ14,DG14,DD14,DA14,CX14,CU14,CR14,CO14,CL14,CI14,CF14)) | J14: =IF(COUNT(DN14,DK14,DH14,DE14,DB14,CY14,CV14,CS14,CP14,CM14,CJ14,CG14)=0,"",SUM(DN14,DK14,DH14,DE14,DB14,CY14,CV14,CS14,CP14,CM14,CJ14,CG14)) | K14: =IF(COUNT('Finance'!K16)=1,'Finance'!K16,"") | L14: ='Finance'!L16 | M14: ='Finance'!M16 | N14: =IF(COUNT('Finance'!N16)=1,'Finance'!N16,"") | O14: ='Finance'!O16 | P14: ='Finance'!P16 | Q14: =IF(COUNT('Finance'!Q16)=1,'Finance'!Q16,"") | R14: ='Finance'!R16 | S14: ='Finance'!S16 | T14: =IF(COUNT('Finance'!T16)=1,'Finance'!T16,"") | U14: ='Finance'!U16 | V14: ='Finance'!V16 | W14: =IF(COUNT('Finance'!W16)=1,'Finance'!W16,"") | X14: ='Finance'!X16 | Y14: ='Finance'!Y16 | Z14: =IF(COUNT('Finance'!Z16)=1,'Finance'!Z16,"") | AA14: ='Finance'!AA16 | AB14: ='Finance'!AB16 | AC14: =IF(COUNT('Finance'!AC16)=1,'Finance'!AC16,"") | AD14: ='Finance'!AD16 | AE14: ='Finance'!AE16 | AF14: =IF(COUNT('Finance'!AF16)=1,'Finance'!AF16,"") | AG14: ='Finance'!AG16 | AH14: ='Finance'!AH16 | AI14: =IF(COUNT('Finance'!AI16)=1,'Finance'!AI16,"") | AJ14: ='Finance'!AJ16 | AK14: ='Finance'!AK16 | AL14: =IF(COUNT('Finance'!AL16)=1,'Finance'!AL16,"") | AM14: ='Finance'!AM16 | AN14: ='Finance'!AN16 | AO14: =IF(COUNT('Finance'!AO16)=1,'Finance'!AO16,"") | AP14: ='Finance'!AP16 | AQ14: ='Finance'!AQ16 | AR14: =IF(COUNT('Finance'!AR16)=1,'Finance'!AR16,"") | AS14: ='Finance'!AS16 | AT14: ='Finance'!AT16 | AU14: =IF(COUNT('Finance'!AU16)=1,'Finance'!AU16,"") | AV14: ='Finance'!AV16 | AW14: ='Finance'!AW16 | AX14: =IF(COUNT('Finance'!AX16)=1,'Finance'!AX16,"") | AY14: ='Finance'!AY16 | AZ14: ='Finance'!AZ16 | BA14: =IF(COUNT('Finance'!BA16)=1,'Finance'!BA16,"") | BB14: ='Finance'!BB16 | BC14: ='Finance'!BC16 | BD14: =IF(COUNT('Finance'!BD16)=1,'Finance'!BD16,"") | BE14: ='Finance'!BE16 | BF14: ='Finance'!BF16 | BG14: =IF(COUNT('Finance'!BG16)=1,'Finance'!BG16,"") | BH14: ='Finance'!BH16 | BI14: ='Finance'!BI16 | BJ14: =IF(COUNT('Finance'!BJ16)=1,'Finance'!BJ16,"") | BK14: ='Finance'!BK16 | BL14: ='Finance'!BL16 | BM14: =IF(COUNT('Finance'!BM16)=1,'Finance'!BM16,"") | BN14: ='Finance'!BN16 | BO14: ='Finance'!BO16 | BP14: =IF(COUNT('Finance'!BP16)=1,'Finance'!BP16,"") | BQ14: ='Finance'!BQ16 | BR14: ='Finance'!BR16 | BS14: =IF(COUNT('Finance'!BS16)=1,'Finance'!BS16,"") | BT14: ='Finance'!BT16 | BU14: ='Finance'!BU16 | BV14: =IF(COUNT('Finance'!BV16)=1,'Finance'!BV16,"") | BW14: ='Finance'!BW16 | BX14: ='Finance'!BX16 | BY14: =IF(COUNT('Finance'!BY16)=1,'Finance'!BY16,"") | BZ14: ='Finance'!BZ16 | CA14: ='Finance'!CA16 | CB14: =IF(COUNT('Finance'!CB16)=1,'Finance'!CB16,"") | CC14: ='Finance'!CC16 | CD14: ='Finance'!CD16 | CE14: =IF(COUNT('Finance'!CE16)=1,'Finance'!CE16,"") | CF14: ='Finance'!CF16 | CG14: ='Finance'!CG16 | CH14: =IF(COUNT('Finance'!CH16)=1,'Finance'!CH16,"") | CI14: ='Finance'!CI16 | CJ14: ='Finance'!CJ16 | CK14: =IF(COUNT('Finance'!CK16)=1,'Finance'!CK16,"") | CL14: ='Finance'!CL16 | CM14: ='Finance'!CM16 | CN14: =IF(COUNT('Finance'!CN16)=1,'Finance'!CN16,"") | CO14: ='Finance'!CO16 | CP14: ='Finance'!CP16 | CQ14: =IF(COUNT('Finance'!CQ16)=1,'Finance'!CQ16,"") | CR14: ='Finance'!CR16 | CS14: ='Finance'!CS16 | CT14: =IF(COUNT('Finance'!CT16)=1,'Finance'!CT16,"") | CU14: ='Finance'!CU16 | CV14: ='Finance'!CV16 | CW14: =IF(COUNT('Finance'!CW16)=1,'Finance'!CW16,"") | CX14: ='Finance'!CX16 | CY14: ='Finance'!CY16 | CZ14: =IF(COUNT('Finance'!CZ16)=1,'Finance'!CZ16,"") | DA14: ='Finance'!DA16 | DB14: ='Finance'!DB16 | DC14: =IF(COUNT('Finance'!DC16)=1,'Finance'!DC16,"") | DD14: ='Finance'!DD16 | DE14: ='Finance'!DE16 | DF14: =IF(COUNT('Finance'!DF16)=1,'Finance'!DF16,"") | DG14: ='Finance'!DG16 | DH14: ='Finance'!DH16 | DI14: =IF(COUNT('Finance'!DI16)=1,'Finance'!DI16,"") | DJ14: ='Finance'!DJ16 | DK14: ='Finance'!DK16 | DL14: =IF(COUNT('Finance'!DL16)=1,'Finance'!DL16,"") | DM14: ='Finance'!DM16 | DN14: ='Finance'!DN16
A15: Net Profit | B15: =IF(COUNT(B12)=0,"",B12-N(B14)) | C15: =IF(COUNT(C12)=0,"",C12-N(C14)) | D15: =IF(COUNT(D12)=0,"",D12-N(D14)) | E15: =IF(COUNT(E12)=0,"",E12-N(E14)) | F15: =IF(COUNT(F12)=0,"",F12-N(F14)) | G15: =IF(COUNT(G12)=0,"",G12-N(G14)) | H15: =IF(COUNT(H12)=0,"",H12-N(H14)) | I15: =IF(COUNT(I12)=0,"",I12-N(I14)) | J15: =IF(COUNT(J12)=0,"",J12-N(J14)) | K15: =IF(COUNT(K12,K14)=2,K12-K14,"") | L15: =L12-L14 | M15: =M12-M14 | N15: =IF(COUNT(N12,N14)=2,N12-N14,"") | O15: =O12-O14 | P15: =P12-P14 | Q15: =IF(COUNT(Q12,Q14)=2,Q12-Q14,"") | R15: =R12-R14 | S15: =S12-S14 | T15: =IF(COUNT(T12,T14)=2,T12-T14,"") | U15: =U12-U14 | V15: =V12-V14 | W15: =IF(COUNT(W12,W14)=2,W12-W14,"") | X15: =X12-X14 | Y15: =Y12-Y14 | Z15: =IF(COUNT(Z12,Z14)=2,Z12-Z14,"") | AA15: =AA12-AA14 | AB15: =AB12-AB14 | AC15: =IF(COUNT(AC12,AC14)=2,AC12-AC14,"") | AD15: =AD12-AD14 | AE15: =AE12-AE14 | AF15: =IF(COUNT(AF12,AF14)=2,AF12-AF14,"") | AG15: =AG12-AG14 | AH15: =AH12-AH14 | AI15: =IF(COUNT(AI12,AI14)=2,AI12-AI14,"") | AJ15: =AJ12-AJ14 | AK15: =AK12-AK14 | AL15: =IF(COUNT(AL12,AL14)=2,AL12-AL14,"") | AM15: =AM12-AM14 | AN15: =AN12-AN14 | AO15: =IF(COUNT(AO12,AO14)=2,AO12-AO14,"") | AP15: =AP12-AP14 | AQ15: =AQ12-AQ14 | AR15: =IF(COUNT(AR12,AR14)=2,AR12-AR14,"") | AS15: =AS12-AS14 | AT15: =AT12-AT14 | AU15: =IF(COUNT(AU12,AU14)=2,AU12-AU14,"") | AV15: =AV12-AV14 | AW15: =AW12-AW14 | AX15: =IF(COUNT(AX12,AX14)=2,AX12-AX14,"") | AY15: =AY12-AY14 | AZ15: =AZ12-AZ14 | BA15: =IF(COUNT(BA12,BA14)=2,BA12-BA14,"") | BB15: =BB12-BB14 | BC15: =BC12-BC14 | BD15: =IF(COUNT(BD12,BD14)=2,BD12-BD14,"") | BE15: =BE12-BE14 | BF15: =BF12-BF14 | BG15: =IF(COUNT(BG12,BG14)=2,BG12-BG14,"") | BH15: =BH12-BH14 | BI15: =BI12-BI14 | BJ15: =IF(COUNT(BJ12,BJ14)=2,BJ12-BJ14,"") | BK15: =BK12-BK14 | BL15: =BL12-BL14 | BM15: =IF(COUNT(BM12,BM14)=2,BM12-BM14,"") | BN15: =BN12-BN14 | BO15: =BO12-BO14 | BP15: =IF(COUNT(BP12,BP14)=2,BP12-BP14,"") | BQ15: =BQ12-BQ14 | BR15: =BR12-BR14 | BS15: =IF(COUNT(BS12,BS14)=2,BS12-BS14,"") | BT15: =BT12-BT14 | BU15: =BU12-BU14 | BV15: =IF(COUNT(BV12,BV14)=2,BV12-BV14,"") | BW15: =BW12-BW14 | BX15: =BX12-BX14 | BY15: =IF(COUNT(BY12,BY14)=2,BY12-BY14,"") | BZ15: =BZ12-BZ14 | CA15: =CA12-CA14 | CB15: =IF(COUNT(CB12,CB14)=2,CB12-CB14,"") | CC15: =CC12-CC14 | CD15: =CD12-CD14 | CE15: =IF(COUNT(CE12,CE14)=2,CE12-CE14,"") | CF15: =CF12-CF14 | CG15: =CG12-CG14 | CH15: =IF(COUNT(CH12,CH14)=2,CH12-CH14,"") | CI15: =CI12-CI14 | CJ15: =CJ12-CJ14 | CK15: =IF(COUNT(CK12,CK14)=2,CK12-CK14,"") | CL15: =CL12-CL14 | CM15: =CM12-CM14 | CN15: =IF(COUNT(CN12,CN14)=2,CN12-CN14,"") | CO15: =CO12-CO14 | CP15: =CP12-CP14 | CQ15: =IF(COUNT(CQ12,CQ14)=2,CQ12-CQ14,"") | CR15: =CR12-CR14 | CS15: =CS12-CS14 | CT15: =IF(COUNT(CT12,CT14)=2,CT12-CT14,"") | CU15: =CU12-CU14 | CV15: =CV12-CV14 | CW15: =IF(COUNT(CW12,CW14)=2,CW12-CW14,"") | CX15: =CX12-CX14 | CY15: =CY12-CY14 | CZ15: =IF(COUNT(CZ12,CZ14)=2,CZ12-CZ14,"") | DA15: =DA12-DA14 | DB15: =DB12-DB14 | DC15: =IF(COUNT(DC12,DC14)=2,DC12-DC14,"") | DD15: =DD12-DD14 | DE15: =DE12-DE14 | DF15: =IF(COUNT(DF12,DF14)=2,DF12-DF14,"") | DG15: =DG12-DG14 | DH15: =DH12-DH14 | DI15: =IF(COUNT(DI12,DI14)=2,DI12-DI14,"") | DJ15: =DJ12-DJ14 | DK15: =DK12-DK14 | DL15: =IF(COUNT(DL12,DL14)=2,DL12-DL14,"") | DM15: =DM12-DM14 | DN15: =DN12-DN14
A16: Customers, End of Month | B16: =IF(K16<>"",K16,IF(N16<>"",N16,IF(Q16<>"",Q16,IF(T16<>"",T16,IF(W16<>"",W16,IF(Z16<>"",Z16,IF(AC16<>"",AC16,IF(AF16<>"",AF16,IF(AI16<>"",AI16,IF(AL16<>"",AL16,IF(AO16<>"",AO16,IF(AR16<>"",AR16,"")))))))))))) | C16: =IF(L16<>"",L16,IF(O16<>"",O16,IF(R16<>"",R16,IF(U16<>"",U16,IF(X16<>"",X16,IF(AA16<>"",AA16,IF(AD16<>"",AD16,IF(AG16<>"",AG16,IF(AJ16<>"",AJ16,IF(AM16<>"",AM16,IF(AP16<>"",AP16,IF(AS16<>"",AS16,"")))))))))))) | D16: =IF(M16<>"",M16,IF(P16<>"",P16,IF(S16<>"",S16,IF(V16<>"",V16,IF(Y16<>"",Y16,IF(AB16<>"",AB16,IF(AE16<>"",AE16,IF(AH16<>"",AH16,IF(AK16<>"",AK16,IF(AN16<>"",AN16,IF(AQ16<>"",AQ16,IF(AT16<>"",AT16,"")))))))))))) | E16: =IF(AU16<>"",AU16,IF(AX16<>"",AX16,IF(BA16<>"",BA16,IF(BD16<>"",BD16,IF(BG16<>"",BG16,IF(BJ16<>"",BJ16,IF(BM16<>"",BM16,IF(BP16<>"",BP16,IF(BS16<>"",BS16,IF(BV16<>"",BV16,IF(BY16<>"",BY16,IF(CB16<>"",CB16,"")))))))))))) | F16: =IF(AV16<>"",AV16,IF(AY16<>"",AY16,IF(BB16<>"",BB16,IF(BE16<>"",BE16,IF(BH16<>"",BH16,IF(BK16<>"",BK16,IF(BN16<>"",BN16,IF(BQ16<>"",BQ16,IF(BT16<>"",BT16,IF(BW16<>"",BW16,IF(BZ16<>"",BZ16,IF(CC16<>"",CC16,"")))))))))))) | G16: =IF(AW16<>"",AW16,IF(AZ16<>"",AZ16,IF(BC16<>"",BC16,IF(BF16<>"",BF16,IF(BI16<>"",BI16,IF(BL16<>"",BL16,IF(BO16<>"",BO16,IF(BR16<>"",BR16,IF(BU16<>"",BU16,IF(BX16<>"",BX16,IF(CA16<>"",CA16,IF(CD16<>"",CD16,"")))))))))))) | H16: =IF(CE16<>"",CE16,IF(CH16<>"",CH16,IF(CK16<>"",CK16,IF(CN16<>"",CN16,IF(CQ16<>"",CQ16,IF(CT16<>"",CT16,IF(CW16<>"",CW16,IF(CZ16<>"",CZ16,IF(DC16<>"",DC16,IF(DF16<>"",DF16,IF(DI16<>"",DI16,IF(DL16<>"",DL16,"")))))))))))) | I16: =IF(CF16<>"",CF16,IF(CI16<>"",CI16,IF(CL16<>"",CL16,IF(CO16<>"",CO16,IF(CR16<>"",CR16,IF(CU16<>"",CU16,IF(CX16<>"",CX16,IF(DA16<>"",DA16,IF(DD16<>"",DD16,IF(DG16<>"",DG16,IF(DJ16<>"",DJ16,IF(DM16<>"",DM16,"")))))))))))) | J16: =IF(CG16<>"",CG16,IF(CJ16<>"",CJ16,IF(CM16<>"",CM16,IF(CP16<>"",CP16,IF(CS16<>"",CS16,IF(CV16<>"",CV16,IF(CY16<>"",CY16,IF(DB16<>"",DB16,IF(DE16<>"",DE16,IF(DH16<>"",DH16,IF(DK16<>"",DK16,IF(DN16<>"",DN16,"")))))))))))) | K16: =IF(COUNT('Summary'!N16,'Sales'!K6,'Customer Success'!K17)=3,'Summary'!N16+'Sales'!K6-'Customer Success'!K17,"") | L16: ='Summary'!O16+'Sales'!L6-'Customer Success'!L17 | M16: ='Summary'!P16+'Sales'!M6-'Customer Success'!M17 | N16: =IF(COUNT('Summary'!Q16,'Sales'!N6,'Customer Success'!N17)=3,'Summary'!Q16+'Sales'!N6-'Customer Success'!N17,"") | O16: ='Summary'!R16+'Sales'!O6-'Customer Success'!O17 | P16: ='Summary'!S16+'Sales'!P6-'Customer Success'!P17 | Q16: =IF(COUNT('Summary'!T16,'Sales'!Q6,'Customer Success'!Q17)=3,'Summary'!T16+'Sales'!Q6-'Customer Success'!Q17,"") | R16: ='Summary'!U16+'Sales'!R6-'Customer Success'!R17 | S16: ='Summary'!V16+'Sales'!S6-'Customer Success'!S17 | T16: =IF(COUNT('Summary'!W16,'Sales'!T6,'Customer Success'!T17)=3,'Summary'!W16+'Sales'!T6-'Customer Success'!T17,"") | U16: ='Summary'!X16+'Sales'!U6-'Customer Success'!U17 | V16: ='Summary'!Y16+'Sales'!V6-'Customer Success'!V17 | W16: =IF(COUNT('Summary'!Z16,'Sales'!W6,'Customer Success'!W17)=3,'Summary'!Z16+'Sales'!W6-'Customer Success'!W17,"") | X16: ='Summary'!AA16+'Sales'!X6-'Customer Success'!X17 | Y16: ='Summary'!AB16+'Sales'!Y6-'Customer Success'!Y17 | Z16: =IF(COUNT('Summary'!AC16,'Sales'!Z6,'Customer Success'!Z17)=3,'Summary'!AC16+'Sales'!Z6-'Customer Success'!Z17,"") | AA16: ='Summary'!AD16+'Sales'!AA6-'Customer Success'!AA17 | AB16: ='Summary'!AE16+'Sales'!AB6-'Customer Success'!AB17 | AC16: =IF(COUNT('Summary'!AF16,'Sales'!AC6,'Customer Success'!AC17)=3,'Summary'!AF16+'Sales'!AC6-'Customer Success'!AC17,"") | AD16: ='Summary'!AG16+'Sales'!AD6-'Customer Success'!AD17 | AE16: ='Summary'!AH16+'Sales'!AE6-'Customer Success'!AE17 | AF16: =IF(COUNT('Summary'!AI16,'Sales'!AF6,'Customer Success'!AF17)=3,'Summary'!AI16+'Sales'!AF6-'Customer Success'!AF17,"") | AG16: ='Summary'!AJ16+'Sales'!AG6-'Customer Success'!AG17 | AH16: ='Summary'!AK16+'Sales'!AH6-'Customer Success'!AH17 | AI16: =IF(COUNT('Summary'!AL16,'Sales'!AI6,'Customer Success'!AI17)=3,'Summary'!AL16+'Sales'!AI6-'Customer Success'!AI17,"") | AJ16: ='Summary'!AM16+'Sales'!AJ6-'Customer Success'!AJ17 | AK16: ='Summary'!AN16+'Sales'!AK6-'Customer Success'!AK17 | AL16: =IF(COUNT('Summary'!AO16,'Sales'!AL6,'Customer Success'!AL17)=3,'Summary'!AO16+'Sales'!AL6-'Customer Success'!AL17,"") | AM16: ='Summary'!AP16+'Sales'!AM6-'Customer Success'!AM17 | AN16: ='Summary'!AQ16+'Sales'!AN6-'Customer Success'!AN17 | AO16: =IF(COUNT('Summary'!AR16,'Sales'!AO6,'Customer Success'!AO17)=3,'Summary'!AR16+'Sales'!AO6-'Customer Success'!AO17,"") | AP16: ='Summary'!AS16+'Sales'!AP6-'Customer Success'!AP17 | AQ16: ='Summary'!AT16+'Sales'!AQ6-'Customer Success'!AQ17 | AR16: =IF(COUNT('Summary'!AU16,'Sales'!AR6,'Customer Success'!AR17)=3,'Summary'!AU16+'Sales'!AR6-'Customer Success'!AR17,"") | AS16: ='Summary'!AV16+'Sales'!AS6-'Customer Success'!AS17 | AT16: ='Summary'!AW16+'Sales'!AT6-'Customer Success'!AT17 | AU16: =IF(COUNT('Summary'!AX16,'Sales'!AU6,'Customer Success'!AU17)=3,'Summary'!AX16+'Sales'!AU6-'Customer Success'!AU17,"") | AV16: ='Summary'!AY16+'Sales'!AV6-'Customer Success'!AV17 | AW16: ='Summary'!AZ16+'Sales'!AW6-'Customer Success'!AW17 | AX16: =IF(COUNT('Summary'!BA16,'Sales'!AX6,'Customer Success'!AX17)=3,'Summary'!BA16+'Sales'!AX6-'Customer Success'!AX17,"") | AY16: ='Summary'!BB16+'Sales'!AY6-'Customer Success'!AY17 | AZ16: ='Summary'!BC16+'Sales'!AZ6-'Customer Success'!AZ17 | BA16: =IF(COUNT('Summary'!BD16,'Sales'!BA6,'Customer Success'!BA17)=3,'Summary'!BD16+'Sales'!BA6-'Customer Success'!BA17,"") | BB16: ='Summary'!BE16+'Sales'!BB6-'Customer Success'!BB17 | BC16: ='Summary'!BF16+'Sales'!BC6-'Customer Success'!BC17 | BD16: =IF(COUNT('Summary'!BG16,'Sales'!BD6,'Customer Success'!BD17)=3,'Summary'!BG16+'Sales'!BD6-'Customer Success'!BD17,"") | BE16: ='Summary'!BH16+'Sales'!BE6-'Customer Success'!BE17 | BF16: ='Summary'!BI16+'Sales'!BF6-'Customer Success'!BF17 | BG16: =IF(COUNT('Summary'!BJ16,'Sales'!BG6,'Customer Success'!BG17)=3,'Summary'!BJ16+'Sales'!BG6-'Customer Success'!BG17,"") | BH16: ='Summary'!BK16+'Sales'!BH6-'Customer Success'!BH17 | BI16: ='Summary'!BL16+'Sales'!BI6-'Customer Success'!BI17 | BJ16: =IF(COUNT('Summary'!BM16,'Sales'!BJ6,'Customer Success'!BJ17)=3,'Summary'!BM16+'Sales'!BJ6-'Customer Success'!BJ17,"") | BK16: ='Summary'!BN16+'Sales'!BK6-'Customer Success'!BK17 | BL16: ='Summary'!BO16+'Sales'!BL6-'Customer Success'!BL17 | BM16: =IF(COUNT('Summary'!BP16,'Sales'!BM6,'Customer Success'!BM17)=3,'Summary'!BP16+'Sales'!BM6-'Customer Success'!BM17,"") | BN16: ='Summary'!BQ16+'Sales'!BN6-'Customer Success'!BN17 | BO16: ='Summary'!BR16+'Sales'!BO6-'Customer Success'!BO17 | BP16: =IF(COUNT('Summary'!BS16,'Sales'!BP6,'Customer Success'!BP17)=3,'Summary'!BS16+'Sales'!BP6-'Customer Success'!BP17,"") | BQ16: ='Summary'!BT16+'Sales'!BQ6-'Customer Success'!BQ17 | BR16: ='Summary'!BU16+'Sales'!BR6-'Customer Success'!BR17 | BS16: =IF(COUNT('Summary'!BV16,'Sales'!BS6,'Customer Success'!BS17)=3,'Summary'!BV16+'Sales'!BS6-'Customer Success'!BS17,"") | BT16: ='Summary'!BW16+'Sales'!BT6-'Customer Success'!BT17 | BU16: ='Summary'!BX16+'Sales'!BU6-'Customer Success'!BU17 | BV16: =IF(COUNT('Summary'!BY16,'Sales'!BV6,'Customer Success'!BV17)=3,'Summary'!BY16+'Sales'!BV6-'Customer Success'!BV17,"") | BW16: ='Summary'!BZ16+'Sales'!BW6-'Customer Success'!BW17 | BX16: ='Summary'!CA16+'Sales'!BX6-'Customer Success'!BX17 | BY16: =IF(COUNT('Summary'!CB16,'Sales'!BY6,'Customer Success'!BY17)=3,'Summary'!CB16+'Sales'!BY6-'Customer Success'!BY17,"") | BZ16: ='Summary'!CC16+'Sales'!BZ6-'Customer Success'!BZ17 | CA16: ='Summary'!CD16+'Sales'!CA6-'Customer Success'!CA17 | CB16: =IF(COUNT('Summary'!CE16,'Sales'!CB6,'Customer Success'!CB17)=3,'Summary'!CE16+'Sales'!CB6-'Customer Success'!CB17,"") | CC16: ='Summary'!CF16+'Sales'!CC6-'Customer Success'!CC17 | CD16: ='Summary'!CG16+'Sales'!CD6-'Customer Success'!CD17 | CE16: =IF(COUNT('Summary'!CH16,'Sales'!CE6,'Customer Success'!CE17)=3,'Summary'!CH16+'Sales'!CE6-'Customer Success'!CE17,"") | CF16: ='Summary'!CI16+'Sales'!CF6-'Customer Success'!CF17 | CG16: ='Summary'!CJ16+'Sales'!CG6-'Customer Success'!CG17 | CH16: =IF(COUNT('Summary'!CK16,'Sales'!CH6,'Customer Success'!CH17)=3,'Summary'!CK16+'Sales'!CH6-'Customer Success'!CH17,"") | CI16: ='Summary'!CL16+'Sales'!CI6-'Customer Success'!CI17 | CJ16: ='Summary'!CM16+'Sales'!CJ6-'Customer Success'!CJ17 | CK16: =IF(COUNT('Summary'!CN16,'Sales'!CK6,'Customer Success'!CK17)=3,'Summary'!CN16+'Sales'!CK6-'Customer Success'!CK17,"") | CL16: ='Summary'!CO16+'Sales'!CL6-'Customer Success'!CL17 | CM16: ='Summary'!CP16+'Sales'!CM6-'Customer Success'!CM17 | CN16: =IF(COUNT('Summary'!CQ16,'Sales'!CN6,'Customer Success'!CN17)=3,'Summary'!CQ16+'Sales'!CN6-'Customer Success'!CN17,"") | CO16: ='Summary'!CR16+'Sales'!CO6-'Customer Success'!CO17 | CP16: ='Summary'!CS16+'Sales'!CP6-'Customer Success'!CP17 | CQ16: =IF(COUNT('Summary'!CT16,'Sales'!CQ6,'Customer Success'!CQ17)=3,'Summary'!CT16+'Sales'!CQ6-'Customer Success'!CQ17,"") | CR16: ='Summary'!CU16+'Sales'!CR6-'Customer Success'!CR17 | CS16: ='Summary'!CV16+'Sales'!CS6-'Customer Success'!CS17 | CT16: =IF(COUNT('Summary'!CW16,'Sales'!CT6,'Customer Success'!CT17)=3,'Summary'!CW16+'Sales'!CT6-'Customer Success'!CT17,"") | CU16: ='Summary'!CX16+'Sales'!CU6-'Customer Success'!CU17 | CV16: ='Summary'!CY16+'Sales'!CV6-'Customer Success'!CV17 | CW16: =IF(COUNT('Summary'!CZ16,'Sales'!CW6,'Customer Success'!CW17)=3,'Summary'!CZ16+'Sales'!CW6-'Customer Success'!CW17,"") | CX16: ='Summary'!DA16+'Sales'!CX6-'Customer Success'!CX17 | CY16: ='Summary'!DB16+'Sales'!CY6-'Customer Success'!CY17 | CZ16: =IF(COUNT('Summary'!DC16,'Sales'!CZ6,'Customer Success'!CZ17)=3,'Summary'!DC16+'Sales'!CZ6-'Customer Success'!CZ17,"") | DA16: ='Summary'!DD16+'Sales'!DA6-'Customer Success'!DA17 | DB16: ='Summary'!DE16+'Sales'!DB6-'Customer Success'!DB17 | DC16: =IF(COUNT('Summary'!DF16,'Sales'!DC6,'Customer Success'!DC17)=3,'Summary'!DF16+'Sales'!DC6-'Customer Success'!DC17,"") | DD16: ='Summary'!DG16+'Sales'!DD6-'Customer Success'!DD17 | DE16: ='Summary'!DH16+'Sales'!DE6-'Customer Success'!DE17 | DF16: =IF(COUNT('Summary'!DI16,'Sales'!DF6,'Customer Success'!DF17)=3,'Summary'!DI16+'Sales'!DF6-'Customer Success'!DF17,"") | DG16: ='Summary'!DJ16+'Sales'!DG6-'Customer Success'!DG17 | DH16: ='Summary'!DK16+'Sales'!DH6-'Customer Success'!DH17 | DI16: =IF(COUNT('Summary'!DL16,'Sales'!DI6,'Customer Success'!DI17)=3,'Summary'!DL16+'Sales'!DI6-'Customer Success'!DI17,"") | DJ16: ='Summary'!DM16+'Sales'!DJ6-'Customer Success'!DJ17 | DK16: ='Summary'!DN16+'Sales'!DK6-'Customer Success'!DK17 | DL16: =IF(COUNT(Finance!$B$62,'Sales'!DL6,'Customer Success'!DL17)=3,Finance!$B$62+'Sales'!DL6-'Customer Success'!DL17,"") | DM16: =Finance!$B$62+'Sales'!DM6-'Customer Success'!DM17 | DN16: =Finance!$B$62+'Sales'!DN6-'Customer Success'!DN17
A17: Average Revenue per Customer | B17: =IF(N(B16)=0,"",B6/B16) | C17: =IF(N(C16)=0,"",C6/C16) | D17: =IF(N(D16)=0,"",D6/D16) | E17: =IF(N(E16)=0,"",E6/E16) | F17: =IF(N(F16)=0,"",F6/F16) | G17: =IF(N(G16)=0,"",G6/G16) | H17: =IF(N(H16)=0,"",H6/H16) | I17: =IF(N(I16)=0,"",I6/I16) | J17: =IF(N(J16)=0,"",J6/J16) | K17: =IF(COUNT(K6,K16)=2,IF(N(K16)=0,"",K6/K16),"") | L17: =IF(N(L16)=0,"",L6/L16) | M17: =IF(N(M16)=0,"",M6/M16) | N17: =IF(COUNT(N6,N16)=2,IF(N(N16)=0,"",N6/N16),"") | O17: =IF(N(O16)=0,"",O6/O16) | P17: =IF(N(P16)=0,"",P6/P16) | Q17: =IF(COUNT(Q6,Q16)=2,IF(N(Q16)=0,"",Q6/Q16),"") | R17: =IF(N(R16)=0,"",R6/R16) | S17: =IF(N(S16)=0,"",S6/S16) | T17: =IF(COUNT(T6,T16)=2,IF(N(T16)=0,"",T6/T16),"") | U17: =IF(N(U16)=0,"",U6/U16) | V17: =IF(N(V16)=0,"",V6/V16) | W17: =IF(COUNT(W6,W16)=2,IF(N(W16)=0,"",W6/W16),"") | X17: =IF(N(X16)=0,"",X6/X16) | Y17: =IF(N(Y16)=0,"",Y6/Y16) | Z17: =IF(COUNT(Z6,Z16)=2,IF(N(Z16)=0,"",Z6/Z16),"") | AA17: =IF(N(AA16)=0,"",AA6/AA16) | AB17: =IF(N(AB16)=0,"",AB6/AB16) | AC17: =IF(COUNT(AC6,AC16)=2,IF(N(AC16)=0,"",AC6/AC16),"") | AD17: =IF(N(AD16)=0,"",AD6/AD16) | AE17: =IF(N(AE16)=0,"",AE6/AE16) | AF17: =IF(COUNT(AF6,AF16)=2,IF(N(AF16)=0,"",AF6/AF16),"") | AG17: =IF(N(AG16)=0,"",AG6/AG16) | AH17: =IF(N(AH16)=0,"",AH6/AH16) | AI17: =IF(COUNT(AI6,AI16)=2,IF(N(AI16)=0,"",AI6/AI16),"") | AJ17: =IF(N(AJ16)=0,"",AJ6/AJ16) | AK17: =IF(N(AK16)=0,"",AK6/AK16) | AL17: =IF(COUNT(AL6,AL16)=2,IF(N(AL16)=0,"",AL6/AL16),"") | AM17: =IF(N(AM16)=0,"",AM6/AM16) | AN17: =IF(N(AN16)=0,"",AN6/AN16) | AO17: =IF(COUNT(AO6,AO16)=2,IF(N(AO16)=0,"",AO6/AO16),"") | AP17: =IF(N(AP16)=0,"",AP6/AP16) | AQ17: =IF(N(AQ16)=0,"",AQ6/AQ16) | AR17: =IF(COUNT(AR6,AR16)=2,IF(N(AR16)=0,"",AR6/AR16),"") | AS17: =IF(N(AS16)=0,"",AS6/AS16) | AT17: =IF(N(AT16)=0,"",AT6/AT16) | AU17: =IF(COUNT(AU6,AU16)=2,IF(N(AU16)=0,"",AU6/AU16),"") | AV17: =IF(N(AV16)=0,"",AV6/AV16) | AW17: =IF(N(AW16)=0,"",AW6/AW16) | AX17: =IF(COUNT(AX6,AX16)=2,IF(N(AX16)=0,"",AX6/AX16),"") | AY17: =IF(N(AY16)=0,"",AY6/AY16) | AZ17: =IF(N(AZ16)=0,"",AZ6/AZ16) | BA17: =IF(COUNT(BA6,BA16)=2,IF(N(BA16)=0,"",BA6/BA16),"") | BB17: =IF(N(BB16)=0,"",BB6/BB16) | BC17: =IF(N(BC16)=0,"",BC6/BC16) | BD17: =IF(COUNT(BD6,BD16)=2,IF(N(BD16)=0,"",BD6/BD16),"") | BE17: =IF(N(BE16)=0,"",BE6/BE16) | BF17: =IF(N(BF16)=0,"",BF6/BF16) | BG17: =IF(COUNT(BG6,BG16)=2,IF(N(BG16)=0,"",BG6/BG16),"") | BH17: =IF(N(BH16)=0,"",BH6/BH16) | BI17: =IF(N(BI16)=0,"",BI6/BI16) | BJ17: =IF(COUNT(BJ6,BJ16)=2,IF(N(BJ16)=0,"",BJ6/BJ16),"") | BK17: =IF(N(BK16)=0,"",BK6/BK16) | BL17: =IF(N(BL16)=0,"",BL6/BL16) | BM17: =IF(COUNT(BM6,BM16)=2,IF(N(BM16)=0,"",BM6/BM16),"") | BN17: =IF(N(BN16)=0,"",BN6/BN16) | BO17: =IF(N(BO16)=0,"",BO6/BO16) | BP17: =IF(COUNT(BP6,BP16)=2,IF(N(BP16)=0,"",BP6/BP16),"") | BQ17: =IF(N(BQ16)=0,"",BQ6/BQ16) | BR17: =IF(N(BR16)=0,"",BR6/BR16) | BS17: =IF(COUNT(BS6,BS16)=2,IF(N(BS16)=0,"",BS6/BS16),"") | BT17: =IF(N(BT16)=0,"",BT6/BT16) | BU17: =IF(N(BU16)=0,"",BU6/BU16) | BV17: =IF(COUNT(BV6,BV16)=2,IF(N(BV16)=0,"",BV6/BV16),"") | BW17: =IF(N(BW16)=0,"",BW6/BW16) | BX17: =IF(N(BX16)=0,"",BX6/BX16) | BY17: =IF(COUNT(BY6,BY16)=2,IF(N(BY16)=0,"",BY6/BY16),"") | BZ17: =IF(N(BZ16)=0,"",BZ6/BZ16) | CA17: =IF(N(CA16)=0,"",CA6/CA16) | CB17: =IF(COUNT(CB6,CB16)=2,IF(N(CB16)=0,"",CB6/CB16),"") | CC17: =IF(N(CC16)=0,"",CC6/CC16) | CD17: =IF(N(CD16)=0,"",CD6/CD16) | CE17: =IF(COUNT(CE6,CE16)=2,IF(N(CE16)=0,"",CE6/CE16),"") | CF17: =IF(N(CF16)=0,"",CF6/CF16) | CG17: =IF(N(CG16)=0,"",CG6/CG16) | CH17: =IF(COUNT(CH6,CH16)=2,IF(N(CH16)=0,"",CH6/CH16),"") | CI17: =IF(N(CI16)=0,"",CI6/CI16) | CJ17: =IF(N(CJ16)=0,"",CJ6/CJ16) | CK17: =IF(COUNT(CK6,CK16)=2,IF(N(CK16)=0,"",CK6/CK16),"") | CL17: =IF(N(CL16)=0,"",CL6/CL16) | CM17: =IF(N(CM16)=0,"",CM6/CM16) | CN17: =IF(COUNT(CN6,CN16)=2,IF(N(CN16)=0,"",CN6/CN16),"") | CO17: =IF(N(CO16)=0,"",CO6/CO16) | CP17: =IF(N(CP16)=0,"",CP6/CP16) | CQ17: =IF(COUNT(CQ6,CQ16)=2,IF(N(CQ16)=0,"",CQ6/CQ16),"") | CR17: =IF(N(CR16)=0,"",CR6/CR16) | CS17: =IF(N(CS16)=0,"",CS6/CS16) | CT17: =IF(COUNT(CT6,CT16)=2,IF(N(CT16)=0,"",CT6/CT16),"") | CU17: =IF(N(CU16)=0,"",CU6/CU16) | CV17: =IF(N(CV16)=0,"",CV6/CV16) | CW17: =IF(COUNT(CW6,CW16)=2,IF(N(CW16)=0,"",CW6/CW16),"") | CX17: =IF(N(CX16)=0,"",CX6/CX16) | CY17: =IF(N(CY16)=0,"",CY6/CY16) | CZ17: =IF(COUNT(CZ6,CZ16)=2,IF(N(CZ16)=0,"",CZ6/CZ16),"") | DA17: =IF(N(DA16)=0,"",DA6/DA16) | DB17: =IF(N(DB16)=0,"",DB6/DB16) | DC17: =IF(COUNT(DC6,DC16)=2,IF(N(DC16)=0,"",DC6/DC16),"") | DD17: =IF(N(DD16)=0,"",DD6/DD16) | DE17: =IF(N(DE16)=0,"",DE6/DE16) | DF17: =IF(COUNT(DF6,DF16)=2,IF(N(DF16)=0,"",DF6/DF16),"") | DG17: =IF(N(DG16)=0,"",DG6/DG16) | DH17: =IF(N(DH16)=0,"",DH6/DH16) | DI17: =IF(COUNT(DI6,DI16)=2,IF(N(DI16)=0,"",DI6/DI16),"") | DJ17: =IF(N(DJ16)=0,"",DJ6/DJ16) | DK17: =IF(N(DK16)=0,"",DK6/DK16) | DL17: =IF(COUNT(DL6,DL16)=2,IF(N(DL16)=0,"",DL6/DL16),"") | DM17: =IF(N(DM16)=0,"",DM6/DM16) | DN17: =IF(N(DN16)=0,"",DN6/DN16)
A18: Profit per Customer | B18: =IF(COUNT(AR12,AO12,AL12,AI12,AF12,AC12,Z12,W12,T12,Q12,N12,K12)=0,"",IF(N(B16)=0,"",SUM(AR12,AO12,AL12,AI12,AF12,AC12,Z12,W12,T12,Q12,N12,K12)/COUNT(AR12,AO12,AL12,AI12,AF12,AC12,Z12,W12,T12,Q12,N12,K12)*12/B16)) | C18: =IF(COUNT(AS12,AP12,AM12,AJ12,AG12,AD12,AA12,X12,U12,R12,O12,L12)=0,"",IF(N(C16)=0,"",SUM(AS12,AP12,AM12,AJ12,AG12,AD12,AA12,X12,U12,R12,O12,L12)/COUNT(AS12,AP12,AM12,AJ12,AG12,AD12,AA12,X12,U12,R12,O12,L12)*12/C16)) | D18: =IF(COUNT(AT12,AQ12,AN12,AK12,AH12,AE12,AB12,Y12,V12,S12,P12,M12)=0,"",IF(N(D16)=0,"",SUM(AT12,AQ12,AN12,AK12,AH12,AE12,AB12,Y12,V12,S12,P12,M12)/COUNT(AT12,AQ12,AN12,AK12,AH12,AE12,AB12,Y12,V12,S12,P12,M12)*12/D16)) | E18: =IF(COUNT(CB12,BY12,BV12,BS12,BP12,BM12,BJ12,BG12,BD12,BA12,AX12,AU12)=0,"",IF(N(E16)=0,"",SUM(CB12,BY12,BV12,BS12,BP12,BM12,BJ12,BG12,BD12,BA12,AX12,AU12)/COUNT(CB12,BY12,BV12,BS12,BP12,BM12,BJ12,BG12,BD12,BA12,AX12,AU12)*12/E16)) | F18: =IF(COUNT(CC12,BZ12,BW12,BT12,BQ12,BN12,BK12,BH12,BE12,BB12,AY12,AV12)=0,"",IF(N(F16)=0,"",SUM(CC12,BZ12,BW12,BT12,BQ12,BN12,BK12,BH12,BE12,BB12,AY12,AV12)/COUNT(CC12,BZ12,BW12,BT12,BQ12,BN12,BK12,BH12,BE12,BB12,AY12,AV12)*12/F16)) | G18: =IF(COUNT(CD12,CA12,BX12,BU12,BR12,BO12,BL12,BI12,BF12,BC12,AZ12,AW12)=0,"",IF(N(G16)=0,"",SUM(CD12,CA12,BX12,BU12,BR12,BO12,BL12,BI12,BF12,BC12,AZ12,AW12)/COUNT(CD12,CA12,BX12,BU12,BR12,BO12,BL12,BI12,BF12,BC12,AZ12,AW12)*12/G16)) | H18: =IF(COUNT(DL12,DI12,DF12,DC12,CZ12,CW12,CT12,CQ12,CN12,CK12,CH12,CE12)=0,"",IF(N(H16)=0,"",SUM(DL12,DI12,DF12,DC12,CZ12,CW12,CT12,CQ12,CN12,CK12,CH12,CE12)/COUNT(DL12,DI12,DF12,DC12,CZ12,CW12,CT12,CQ12,CN12,CK12,CH12,CE12)*12/H16)) | I18: =IF(COUNT(DM12,DJ12,DG12,DD12,DA12,CX12,CU12,CR12,CO12,CL12,CI12,CF12)=0,"",IF(N(I16)=0,"",SUM(DM12,DJ12,DG12,DD12,DA12,CX12,CU12,CR12,CO12,CL12,CI12,CF12)/COUNT(DM12,DJ12,DG12,DD12,DA12,CX12,CU12,CR12,CO12,CL12,CI12,CF12)*12/I16)) | J18: =IF(COUNT(DN12,DK12,DH12,DE12,DB12,CY12,CV12,CS12,CP12,CM12,CJ12,CG12)=0,"",IF(N(J16)=0,"",SUM(DN12,DK12,DH12,DE12,DB12,CY12,CV12,CS12,CP12,CM12,CJ12,CG12)/COUNT(DN12,DK12,DH12,DE12,DB12,CY12,CV12,CS12,CP12,CM12,CJ12,CG12)*12/J16)) | K18: =IF(COUNT(AR12,AO12,AL12,AI12,AF12,AC12,Z12,W12,T12,Q12,N12,K12)=0,"",IF(N(K16)=0,"",SUM(AR12,AO12,AL12,AI12,AF12,AC12,Z12,W12,T12,Q12,N12,K12)/COUNT(AR12,AO12,AL12,AI12,AF12,AC12,Z12,W12,T12,Q12,N12,K12)*12/K16)) | L18: =IF(COUNT(AS12,AP12,AM12,AJ12,AG12,AD12,AA12,X12,U12,R12,O12,L12)=0,"",IF(N(L16)=0,"",SUM(AS12,AP12,AM12,AJ12,AG12,AD12,AA12,X12,U12,R12,O12,L12)/COUNT(AS12,AP12,AM12,AJ12,AG12,AD12,AA12,X12,U12,R12,O12,L12)*12/L16)) | M18: =IF(COUNT(AT12,AQ12,AN12,AK12,AH12,AE12,AB12,Y12,V12,S12,P12,M12)=0,"",IF(N(M16)=0,"",SUM(AT12,AQ12,AN12,AK12,AH12,AE12,AB12,Y12,V12,S12,P12,M12)/COUNT(AT12,AQ12,AN12,AK12,AH12,AE12,AB12,Y12,V12,S12,P12,M12)*12/M16)) | N18: =IF(COUNT(AU12,AR12,AO12,AL12,AI12,AF12,AC12,Z12,W12,T12,Q12,N12)=0,"",IF(N(N16)=0,"",SUM(AU12,AR12,AO12,AL12,AI12,AF12,AC12,Z12,W12,T12,Q12,N12)/COUNT(AU12,AR12,AO12,AL12,AI12,AF12,AC12,Z12,W12,T12,Q12,N12)*12/N16)) | O18: =IF(COUNT(AV12,AS12,AP12,AM12,AJ12,AG12,AD12,AA12,X12,U12,R12,O12)=0,"",IF(N(O16)=0,"",SUM(AV12,AS12,AP12,AM12,AJ12,AG12,AD12,AA12,X12,U12,R12,O12)/COUNT(AV12,AS12,AP12,AM12,AJ12,AG12,AD12,AA12,X12,U12,R12,O12)*12/O16)) | P18: =IF(COUNT(AW12,AT12,AQ12,AN12,AK12,AH12,AE12,AB12,Y12,V12,S12,P12)=0,"",IF(N(P16)=0,"",SUM(AW12,AT12,AQ12,AN12,AK12,AH12,AE12,AB12,Y12,V12,S12,P12)/COUNT(AW12,AT12,AQ12,AN12,AK12,AH12,AE12,AB12,Y12,V12,S12,P12)*12/P16)) | Q18: =IF(COUNT(AX12,AU12,AR12,AO12,AL12,AI12,AF12,AC12,Z12,W12,T12,Q12)=0,"",IF(N(Q16)=0,"",SUM(AX12,AU12,AR12,AO12,AL12,AI12,AF12,AC12,Z12,W12,T12,Q12)/COUNT(AX12,AU12,AR12,AO12,AL12,AI12,AF12,AC12,Z12,W12,T12,Q12)*12/Q16)) | R18: =IF(COUNT(AY12,AV12,AS12,AP12,AM12,AJ12,AG12,AD12,AA12,X12,U12,R12)=0,"",IF(N(R16)=0,"",SUM(AY12,AV12,AS12,AP12,AM12,AJ12,AG12,AD12,AA12,X12,U12,R12)/COUNT(AY12,AV12,AS12,AP12,AM12,AJ12,AG12,AD12,AA12,X12,U12,R12)*12/R16)) | ... CG18: =IF(COUNT(DN12,DK12,DH12,DE12,DB12,CY12,CV12,CS12,CP12,CM12,CJ12,CG12)=0,"",IF(N(CG16)=0,"",SUM(DN12,DK12,DH12,DE12,DB12,CY12,CV12,CS12,CP12,CM12,CJ12,CG12)/COUNT(DN12,DK12,DH12,DE12,DB12,CY12,CV12,CS12,CP12,CM12,CJ12,CG12)*12/CG16)) | CH18: =IF(COUNT(DL12,DI12,DF12,DC12,CZ12,CW12,CT12,CQ12,CN12,CK12,CH12)=0,"",IF(N(CH16)=0,"",SUM(DL12,DI12,DF12,DC12,CZ12,CW12,CT12,CQ12,CN12,CK12,CH12)/COUNT(DL12,DI12,DF12,DC12,CZ12,CW12,CT12,CQ12,CN12,CK12,CH12)*12/CH16)) | CI18: =IF(COUNT(DM12,DJ12,DG12,DD12,DA12,CX12,CU12,CR12,CO12,CL12,CI12)=0,"",IF(N(CI16)=0,"",SUM(DM12,DJ12,DG12,DD12,DA12,CX12,CU12,CR12,CO12,CL12,CI12)/COUNT(DM12,DJ12,DG12,DD12,DA12,CX12,CU12,CR12,CO12,CL12,CI12)*12/CI16)) | CJ18: =IF(COUNT(DN12,DK12,DH12,DE12,DB12,CY12,CV12,CS12,CP12,CM12,CJ12)=0,"",IF(N(CJ16)=0,"",SUM(DN12,DK12,DH12,DE12,DB12,CY12,CV12,CS12,CP12,CM12,CJ12)/COUNT(DN12,DK12,DH12,DE12,DB12,CY12,CV12,CS12,CP12,CM12,CJ12)*12/CJ16)) | CK18: =IF(COUNT(DL12,DI12,DF12,DC12,CZ12,CW12,CT12,CQ12,CN12,CK12)=0,"",IF(N(CK16)=0,"",SUM(DL12,DI12,DF12,DC12,CZ12,CW12,CT12,CQ12,CN12,CK12)/COUNT(DL12,DI12,DF12,DC12,CZ12,CW12,CT12,CQ12,CN12,CK12)*12/CK16)) | CL18: =IF(COUNT(DM12,DJ12,DG12,DD12,DA12,CX12,CU12,CR12,CO12,CL12)=0,"",IF(N(CL16)=0,"",SUM(DM12,DJ12,DG12,DD12,DA12,CX12,CU12,CR12,CO12,CL12)/COUNT(DM12,DJ12,DG12,DD12,DA12,CX12,CU12,CR12,CO12,CL12)*12/CL16)) | CM18: =IF(COUNT(DN12,DK12,DH12,DE12,DB12,CY12,CV12,CS12,CP12,CM12)=0,"",IF(N(CM16)=0,"",SUM(DN12,DK12,DH12,DE12,DB12,CY12,CV12,CS12,CP12,CM12)/COUNT(DN12,DK12,DH12,DE12,DB12,CY12,CV12,CS12,CP12,CM12)*12/CM16)) | CN18: =IF(COUNT(DL12,DI12,DF12,DC12,CZ12,CW12,CT12,CQ12,CN12)=0,"",IF(N(CN16)=0,"",SUM(DL12,DI12,DF12,DC12,CZ12,CW12,CT12,CQ12,CN12)/COUNT(DL12,DI12,DF12,DC12,CZ12,CW12,CT12,CQ12,CN12)*12/CN16)) | CO18: =IF(COUNT(DM12,DJ12,DG12,DD12,DA12,CX12,CU12,CR12,CO12)=0,"",IF(N(CO16)=0,"",SUM(DM12,DJ12,DG12,DD12,DA12,CX12,CU12,CR12,CO12)/COUNT(DM12,DJ12,DG12,DD12,DA12,CX12,CU12,CR12,CO12)*12/CO16)) | CP18: =IF(COUNT(DN12,DK12,DH12,DE12,DB12,CY12,CV12,CS12,CP12)=0,"",IF(N(CP16)=0,"",SUM(DN12,DK12,DH12,DE12,DB12,CY12,CV12,CS12,CP12)/COUNT(DN12,DK12,DH12,DE12,DB12,CY12,CV12,CS12,CP12)*12/CP16)) | CQ18: =IF(COUNT(DL12,DI12,DF12,DC12,CZ12,CW12,CT12,CQ12)=0,"",IF(N(CQ16)=0,"",SUM(DL12,DI12,DF12,DC12,CZ12,CW12,CT12,CQ12)/COUNT(DL12,DI12,DF12,DC12,CZ12,CW12,CT12,CQ12)*12/CQ16)) | CR18: =IF(COUNT(DM12,DJ12,DG12,DD12,DA12,CX12,CU12,CR12)=0,"",IF(N(CR16)=0,"",SUM(DM12,DJ12,DG12,DD12,DA12,CX12,CU12,CR12)/COUNT(DM12,DJ12,DG12,DD12,DA12,CX12,CU12,CR12)*12/CR16)) | CS18: =IF(COUNT(DN12,DK12,DH12,DE12,DB12,CY12,CV12,CS12)=0,"",IF(N(CS16)=0,"",SUM(DN12,DK12,DH12,DE12,DB12,CY12,CV12,CS12)/COUNT(DN12,DK12,DH12,DE12,DB12,CY12,CV12,CS12)*12/CS16)) | CT18: =IF(COUNT(DL12,DI12,DF12,DC12,CZ12,CW12,CT12)=0,"",IF(N(CT16)=0,"",SUM(DL12,DI12,DF12,DC12,CZ12,CW12,CT12)/COUNT(DL12,DI12,DF12,DC12,CZ12,CW12,CT12)*12/CT16)) | CU18: =IF(COUNT(DM12,DJ12,DG12,DD12,DA12,CX12,CU12)=0,"",IF(N(CU16)=0,"",SUM(DM12,DJ12,DG12,DD12,DA12,CX12,CU12)/COUNT(DM12,DJ12,DG12,DD12,DA12,CX12,CU12)*12/CU16)) | CV18: =IF(COUNT(DN12,DK12,DH12,DE12,DB12,CY12,CV12)=0,"",IF(N(CV16)=0,"",SUM(DN12,DK12,DH12,DE12,DB12,CY12,CV12)/COUNT(DN12,DK12,DH12,DE12,DB12,CY12,CV12)*12/CV16)) | CW18: =IF(COUNT(DL12,DI12,DF12,DC12,CZ12,CW12)=0,"",IF(N(CW16)=0,"",SUM(DL12,DI12,DF12,DC12,CZ12,CW12)/COUNT(DL12,DI12,DF12,DC12,CZ12,CW12)*12/CW16)) | CX18: =IF(COUNT(DM12,DJ12,DG12,DD12,DA12,CX12)=0,"",IF(N(CX16)=0,"",SUM(DM12,DJ12,DG12,DD12,DA12,CX12)/COUNT(DM12,DJ12,DG12,DD12,DA12,CX12)*12/CX16)) | CY18: =IF(COUNT(DN12,DK12,DH12,DE12,DB12,CY12)=0,"",IF(N(CY16)=0,"",SUM(DN12,DK12,DH12,DE12,DB12,CY12)/COUNT(DN12,DK12,DH12,DE12,DB12,CY12)*12/CY16)) | CZ18: =IF(COUNT(DL12,DI12,DF12,DC12,CZ12)=0,"",IF(N(CZ16)=0,"",SUM(DL12,DI12,DF12,DC12,CZ12)/COUNT(DL12,DI12,DF12,DC12,CZ12)*12/CZ16)) | DA18: =IF(COUNT(DM12,DJ12,DG12,DD12,DA12)=0,"",IF(N(DA16)=0,"",SUM(DM12,DJ12,DG12,DD12,DA12)/COUNT(DM12,DJ12,DG12,DD12,DA12)*12/DA16)) | DB18: =IF(COUNT(DN12,DK12,DH12,DE12,DB12)=0,"",IF(N(DB16)=0,"",SUM(DN12,DK12,DH12,DE12,DB12)/COUNT(DN12,DK12,DH12,DE12,DB12)*12/DB16)) | DC18: =IF(COUNT(DL12,DI12,DF12,DC12)=0,"",IF(N(DC16)=0,"",SUM(DL12,DI12,DF12,DC12)/COUNT(DL12,DI12,DF12,DC12)*12/DC16)) | DD18: =IF(COUNT(DM12,DJ12,DG12,DD12)=0,"",IF(N(DD16)=0,"",SUM(DM12,DJ12,DG12,DD12)/COUNT(DM12,DJ12,DG12,DD12)*12/DD16)) | DE18: =IF(COUNT(DN12,DK12,DH12,DE12)=0,"",IF(N(DE16)=0,"",SUM(DN12,DK12,DH12,DE12)/COUNT(DN12,DK12,DH12,DE12)*12/DE16)) | DF18: =IF(COUNT(DL12,DI12,DF12)=0,"",IF(N(DF16)=0,"",SUM(DL12,DI12,DF12)/COUNT(DL12,DI12,DF12)*12/DF16)) | DG18: =IF(COUNT(DM12,DJ12,DG12)=0,"",IF(N(DG16)=0,"",SUM(DM12,DJ12,DG12)/COUNT(DM12,DJ12,DG12)*12/DG16)) | DH18: =IF(COUNT(DN12,DK12,DH12)=0,"",IF(N(DH16)=0,"",SUM(DN12,DK12,DH12)/COUNT(DN12,DK12,DH12)*12/DH16)) | DI18: =IF(COUNT(DL12,DI12)=0,"",IF(N(DI16)=0,"",SUM(DL12,DI12)/COUNT(DL12,DI12)*12/DI16)) | DJ18: =IF(COUNT(DM12,DJ12)=0,"",IF(N(DJ16)=0,"",SUM(DM12,DJ12)/COUNT(DM12,DJ12)*12/DJ16)) | DK18: =IF(COUNT(DN12,DK12)=0,"",IF(N(DK16)=0,"",SUM(DN12,DK12)/COUNT(DN12,DK12)*12/DK16)) | DL18: =IF(COUNT(DL12)=0,"",IF(N(DL16)=0,"",SUM(DL12)/COUNT(DL12)*12/DL16)) | DM18: =IF(COUNT(DM12)=0,"",IF(N(DM16)=0,"",SUM(DM12)/COUNT(DM12)*12/DM16)) | DN18: =IF(COUNT(DN12)=0,"",IF(N(DN16)=0,"",SUM(DN12)/COUNT(DN12)*12/DN16))
A19: People | B19: =IF(K19<>"",K19,IF(N19<>"",N19,IF(Q19<>"",Q19,IF(T19<>"",T19,IF(W19<>"",W19,IF(Z19<>"",Z19,IF(AC19<>"",AC19,IF(AF19<>"",AF19,IF(AI19<>"",AI19,IF(AL19<>"",AL19,IF(AO19<>"",AO19,IF(AR19<>"",AR19,"")))))))))))) | C19: =IF(L19<>"",L19,IF(O19<>"",O19,IF(R19<>"",R19,IF(U19<>"",U19,IF(X19<>"",X19,IF(AA19<>"",AA19,IF(AD19<>"",AD19,IF(AG19<>"",AG19,IF(AJ19<>"",AJ19,IF(AM19<>"",AM19,IF(AP19<>"",AP19,IF(AS19<>"",AS19,"")))))))))))) | D19: =IF(M19<>"",M19,IF(P19<>"",P19,IF(S19<>"",S19,IF(V19<>"",V19,IF(Y19<>"",Y19,IF(AB19<>"",AB19,IF(AE19<>"",AE19,IF(AH19<>"",AH19,IF(AK19<>"",AK19,IF(AN19<>"",AN19,IF(AQ19<>"",AQ19,IF(AT19<>"",AT19,"")))))))))))) | E19: =IF(AU19<>"",AU19,IF(AX19<>"",AX19,IF(BA19<>"",BA19,IF(BD19<>"",BD19,IF(BG19<>"",BG19,IF(BJ19<>"",BJ19,IF(BM19<>"",BM19,IF(BP19<>"",BP19,IF(BS19<>"",BS19,IF(BV19<>"",BV19,IF(BY19<>"",BY19,IF(CB19<>"",CB19,"")))))))))))) | F19: =IF(AV19<>"",AV19,IF(AY19<>"",AY19,IF(BB19<>"",BB19,IF(BE19<>"",BE19,IF(BH19<>"",BH19,IF(BK19<>"",BK19,IF(BN19<>"",BN19,IF(BQ19<>"",BQ19,IF(BT19<>"",BT19,IF(BW19<>"",BW19,IF(BZ19<>"",BZ19,IF(CC19<>"",CC19,"")))))))))))) | G19: =IF(AW19<>"",AW19,IF(AZ19<>"",AZ19,IF(BC19<>"",BC19,IF(BF19<>"",BF19,IF(BI19<>"",BI19,IF(BL19<>"",BL19,IF(BO19<>"",BO19,IF(BR19<>"",BR19,IF(BU19<>"",BU19,IF(BX19<>"",BX19,IF(CA19<>"",CA19,IF(CD19<>"",CD19,"")))))))))))) | H19: =IF(CE19<>"",CE19,IF(CH19<>"",CH19,IF(CK19<>"",CK19,IF(CN19<>"",CN19,IF(CQ19<>"",CQ19,IF(CT19<>"",CT19,IF(CW19<>"",CW19,IF(CZ19<>"",CZ19,IF(DC19<>"",DC19,IF(DF19<>"",DF19,IF(DI19<>"",DI19,IF(DL19<>"",DL19,"")))))))))))) | I19: =IF(CF19<>"",CF19,IF(CI19<>"",CI19,IF(CL19<>"",CL19,IF(CO19<>"",CO19,IF(CR19<>"",CR19,IF(CU19<>"",CU19,IF(CX19<>"",CX19,IF(DA19<>"",DA19,IF(DD19<>"",DD19,IF(DG19<>"",DG19,IF(DJ19<>"",DJ19,IF(DM19<>"",DM19,"")))))))))))) | J19: =IF(CG19<>"",CG19,IF(CJ19<>"",CJ19,IF(CM19<>"",CM19,IF(CP19<>"",CP19,IF(CS19<>"",CS19,IF(CV19<>"",CV19,IF(CY19<>"",CY19,IF(DB19<>"",DB19,IF(DE19<>"",DE19,IF(DH19<>"",DH19,IF(DK19<>"",DK19,IF(DN19<>"",DN19,"")))))))))))) | K19: =IF(COUNT('Marketing'!K39,'Sales'!K52,'Customer Success'!K48,'Support'!K42,'Engineering'!K47,'Finance'!K50)=6,'Marketing'!K39+'Sales'!K52+'Customer Success'!K48+'Support'!K42+'Engineering'!K47+'Finance'!K50,"") | L19: ='Marketing'!L39+'Sales'!L52+'Customer Success'!L48+'Support'!L42+'Engineering'!L47+'Finance'!L50 | M19: ='Marketing'!M39+'Sales'!M52+'Customer Success'!M48+'Support'!M42+'Engineering'!M47+'Finance'!M50 | N19: =IF(COUNT('Marketing'!N39,'Sales'!N52,'Customer Success'!N48,'Support'!N42,'Engineering'!N47,'Finance'!N50)=6,'Marketing'!N39+'Sales'!N52+'Customer Success'!N48+'Support'!N42+'Engineering'!N47+'Finance'!N50,"") | O19: ='Marketing'!O39+'Sales'!O52+'Customer Success'!O48+'Support'!O42+'Engineering'!O47+'Finance'!O50 | P19: ='Marketing'!P39+'Sales'!P52+'Customer Success'!P48+'Support'!P42+'Engineering'!P47+'Finance'!P50 | Q19: =IF(COUNT('Marketing'!Q39,'Sales'!Q52,'Customer Success'!Q48,'Support'!Q42,'Engineering'!Q47,'Finance'!Q50)=6,'Marketing'!Q39+'Sales'!Q52+'Customer Success'!Q48+'Support'!Q42+'Engineering'!Q47+'Finance'!Q50,"") | R19: ='Marketing'!R39+'Sales'!R52+'Customer Success'!R48+'Support'!R42+'Engineering'!R47+'Finance'!R50 | S19: ='Marketing'!S39+'Sales'!S52+'Customer Success'!S48+'Support'!S42+'Engineering'!S47+'Finance'!S50 | T19: =IF(COUNT('Marketing'!T39,'Sales'!T52,'Customer Success'!T48,'Support'!T42,'Engineering'!T47,'Finance'!T50)=6,'Marketing'!T39+'Sales'!T52+'Customer Success'!T48+'Support'!T42+'Engineering'!T47+'Finance'!T50,"") | U19: ='Marketing'!U39+'Sales'!U52+'Customer Success'!U48+'Support'!U42+'Engineering'!U47+'Finance'!U50 | V19: ='Marketing'!V39+'Sales'!V52+'Customer Success'!V48+'Support'!V42+'Engineering'!V47+'Finance'!V50 | W19: =IF(COUNT('Marketing'!W39,'Sales'!W52,'Customer Success'!W48,'Support'!W42,'Engineering'!W47,'Finance'!W50)=6,'Marketing'!W39+'Sales'!W52+'Customer Success'!W48+'Support'!W42+'Engineering'!W47+'Finance'!W50,"") | X19: ='Marketing'!X39+'Sales'!X52+'Customer Success'!X48+'Support'!X42+'Engineering'!X47+'Finance'!X50 | Y19: ='Marketing'!Y39+'Sales'!Y52+'Customer Success'!Y48+'Support'!Y42+'Engineering'!Y47+'Finance'!Y50 | Z19: =IF(COUNT('Marketing'!Z39,'Sales'!Z52,'Customer Success'!Z48,'Support'!Z42,'Engineering'!Z47,'Finance'!Z50)=6,'Marketing'!Z39+'Sales'!Z52+'Customer Success'!Z48+'Support'!Z42+'Engineering'!Z47+'Finance'!Z50,"") | AA19: ='Marketing'!AA39+'Sales'!AA52+'Customer Success'!AA48+'Support'!AA42+'Engineering'!AA47+'Finance'!AA50 | AB19: ='Marketing'!AB39+'Sales'!AB52+'Customer Success'!AB48+'Support'!AB42+'Engineering'!AB47+'Finance'!AB50 | AC19: =IF(COUNT('Marketing'!AC39,'Sales'!AC52,'Customer Success'!AC48,'Support'!AC42,'Engineering'!AC47,'Finance'!AC50)=6,'Marketing'!AC39+'Sales'!AC52+'Customer Success'!AC48+'Support'!AC42+'Engineering'!AC47+'Finance'!AC50,"") | AD19: ='Marketing'!AD39+'Sales'!AD52+'Customer Success'!AD48+'Support'!AD42+'Engineering'!AD47+'Finance'!AD50 | AE19: ='Marketing'!AE39+'Sales'!AE52+'Customer Success'!AE48+'Support'!AE42+'Engineering'!AE47+'Finance'!AE50 | AF19: =IF(COUNT('Marketing'!AF39,'Sales'!AF52,'Customer Success'!AF48,'Support'!AF42,'Engineering'!AF47,'Finance'!AF50)=6,'Marketing'!AF39+'Sales'!AF52+'Customer Success'!AF48+'Support'!AF42+'Engineering'!AF47+'Finance'!AF50,"") | AG19: ='Marketing'!AG39+'Sales'!AG52+'Customer Success'!AG48+'Support'!AG42+'Engineering'!AG47+'Finance'!AG50 | AH19: ='Marketing'!AH39+'Sales'!AH52+'Customer Success'!AH48+'Support'!AH42+'Engineering'!AH47+'Finance'!AH50 | AI19: =IF(COUNT('Marketing'!AI39,'Sales'!AI52,'Customer Success'!AI48,'Support'!AI42,'Engineering'!AI47,'Finance'!AI50)=6,'Marketing'!AI39+'Sales'!AI52+'Customer Success'!AI48+'Support'!AI42+'Engineering'!AI47+'Finance'!AI50,"") | AJ19: ='Marketing'!AJ39+'Sales'!AJ52+'Customer Success'!AJ48+'Support'!AJ42+'Engineering'!AJ47+'Finance'!AJ50 | AK19: ='Marketing'!AK39+'Sales'!AK52+'Customer Success'!AK48+'Support'!AK42+'Engineering'!AK47+'Finance'!AK50 | AL19: =IF(COUNT('Marketing'!AL39,'Sales'!AL52,'Customer Success'!AL48,'Support'!AL42,'Engineering'!AL47,'Finance'!AL50)=6,'Marketing'!AL39+'Sales'!AL52+'Customer Success'!AL48+'Support'!AL42+'Engineering'!AL47+'Finance'!AL50,"") | AM19: ='Marketing'!AM39+'Sales'!AM52+'Customer Success'!AM48+'Support'!AM42+'Engineering'!AM47+'Finance'!AM50 | AN19: ='Marketing'!AN39+'Sales'!AN52+'Customer Success'!AN48+'Support'!AN42+'Engineering'!AN47+'Finance'!AN50 | AO19: =IF(COUNT('Marketing'!AO39,'Sales'!AO52,'Customer Success'!AO48,'Support'!AO42,'Engineering'!AO47,'Finance'!AO50)=6,'Marketing'!AO39+'Sales'!AO52+'Customer Success'!AO48+'Support'!AO42+'Engineering'!AO47+'Finance'!AO50,"") | AP19: ='Marketing'!AP39+'Sales'!AP52+'Customer Success'!AP48+'Support'!AP42+'Engineering'!AP47+'Finance'!AP50 | AQ19: ='Marketing'!AQ39+'Sales'!AQ52+'Customer Success'!AQ48+'Support'!AQ42+'Engineering'!AQ47+'Finance'!AQ50 | AR19: =IF(COUNT('Marketing'!AR39,'Sales'!AR52,'Customer Success'!AR48,'Support'!AR42,'Engineering'!AR47,'Finance'!AR50)=6,'Marketing'!AR39+'Sales'!AR52+'Customer Success'!AR48+'Support'!AR42+'Engineering'!AR47+'Finance'!AR50,"") | AS19: ='Marketing'!AS39+'Sales'!AS52+'Customer Success'!AS48+'Support'!AS42+'Engineering'!AS47+'Finance'!AS50 | AT19: ='Marketing'!AT39+'Sales'!AT52+'Customer Success'!AT48+'Support'!AT42+'Engineering'!AT47+'Finance'!AT50 | AU19: =IF(COUNT('Marketing'!AU39,'Sales'!AU52,'Customer Success'!AU48,'Support'!AU42,'Engineering'!AU47,'Finance'!AU50)=6,'Marketing'!AU39+'Sales'!AU52+'Customer Success'!AU48+'Support'!AU42+'Engineering'!AU47+'Finance'!AU50,"") | AV19: ='Marketing'!AV39+'Sales'!AV52+'Customer Success'!AV48+'Support'!AV42+'Engineering'!AV47+'Finance'!AV50 | AW19: ='Marketing'!AW39+'Sales'!AW52+'Customer Success'!AW48+'Support'!AW42+'Engineering'!AW47+'Finance'!AW50 | AX19: =IF(COUNT('Marketing'!AX39,'Sales'!AX52,'Customer Success'!AX48,'Support'!AX42,'Engineering'!AX47,'Finance'!AX50)=6,'Marketing'!AX39+'Sales'!AX52+'Customer Success'!AX48+'Support'!AX42+'Engineering'!AX47+'Finance'!AX50,"") | AY19: ='Marketing'!AY39+'Sales'!AY52+'Customer Success'!AY48+'Support'!AY42+'Engineering'!AY47+'Finance'!AY50 | AZ19: ='Marketing'!AZ39+'Sales'!AZ52+'Customer Success'!AZ48+'Support'!AZ42+'Engineering'!AZ47+'Finance'!AZ50 | BA19: =IF(COUNT('Marketing'!BA39,'Sales'!BA52,'Customer Success'!BA48,'Support'!BA42,'Engineering'!BA47,'Finance'!BA50)=6,'Marketing'!BA39+'Sales'!BA52+'Customer Success'!BA48+'Support'!BA42+'Engineering'!BA47+'Finance'!BA50,"") | BB19: ='Marketing'!BB39+'Sales'!BB52+'Customer Success'!BB48+'Support'!BB42+'Engineering'!BB47+'Finance'!BB50 | BC19: ='Marketing'!BC39+'Sales'!BC52+'Customer Success'!BC48+'Support'!BC42+'Engineering'!BC47+'Finance'!BC50 | BD19: =IF(COUNT('Marketing'!BD39,'Sales'!BD52,'Customer Success'!BD48,'Support'!BD42,'Engineering'!BD47,'Finance'!BD50)=6,'Marketing'!BD39+'Sales'!BD52+'Customer Success'!BD48+'Support'!BD42+'Engineering'!BD47+'Finance'!BD50,"") | BE19: ='Marketing'!BE39+'Sales'!BE52+'Customer Success'!BE48+'Support'!BE42+'Engineering'!BE47+'Finance'!BE50 | BF19: ='Marketing'!BF39+'Sales'!BF52+'Customer Success'!BF48+'Support'!BF42+'Engineering'!BF47+'Finance'!BF50 | BG19: =IF(COUNT('Marketing'!BG39,'Sales'!BG52,'Customer Success'!BG48,'Support'!BG42,'Engineering'!BG47,'Finance'!BG50)=6,'Marketing'!BG39+'Sales'!BG52+'Customer Success'!BG48+'Support'!BG42+'Engineering'!BG47+'Finance'!BG50,"") | BH19: ='Marketing'!BH39+'Sales'!BH52+'Customer Success'!BH48+'Support'!BH42+'Engineering'!BH47+'Finance'!BH50 | BI19: ='Marketing'!BI39+'Sales'!BI52+'Customer Success'!BI48+'Support'!BI42+'Engineering'!BI47+'Finance'!BI50 | BJ19: =IF(COUNT('Marketing'!BJ39,'Sales'!BJ52,'Customer Success'!BJ48,'Support'!BJ42,'Engineering'!BJ47,'Finance'!BJ50)=6,'Marketing'!BJ39+'Sales'!BJ52+'Customer Success'!BJ48+'Support'!BJ42+'Engineering'!BJ47+'Finance'!BJ50,"") | BK19: ='Marketing'!BK39+'Sales'!BK52+'Customer Success'!BK48+'Support'!BK42+'Engineering'!BK47+'Finance'!BK50 | BL19: ='Marketing'!BL39+'Sales'!BL52+'Customer Success'!BL48+'Support'!BL42+'Engineering'!BL47+'Finance'!BL50 | BM19: =IF(COUNT('Marketing'!BM39,'Sales'!BM52,'Customer Success'!BM48,'Support'!BM42,'Engineering'!BM47,'Finance'!BM50)=6,'Marketing'!BM39+'Sales'!BM52+'Customer Success'!BM48+'Support'!BM42+'Engineering'!BM47+'Finance'!BM50,"") | BN19: ='Marketing'!BN39+'Sales'!BN52+'Customer Success'!BN48+'Support'!BN42+'Engineering'!BN47+'Finance'!BN50 | BO19: ='Marketing'!BO39+'Sales'!BO52+'Customer Success'!BO48+'Support'!BO42+'Engineering'!BO47+'Finance'!BO50 | BP19: =IF(COUNT('Marketing'!BP39,'Sales'!BP52,'Customer Success'!BP48,'Support'!BP42,'Engineering'!BP47,'Finance'!BP50)=6,'Marketing'!BP39+'Sales'!BP52+'Customer Success'!BP48+'Support'!BP42+'Engineering'!BP47+'Finance'!BP50,"") | BQ19: ='Marketing'!BQ39+'Sales'!BQ52+'Customer Success'!BQ48+'Support'!BQ42+'Engineering'!BQ47+'Finance'!BQ50 | BR19: ='Marketing'!BR39+'Sales'!BR52+'Customer Success'!BR48+'Support'!BR42+'Engineering'!BR47+'Finance'!BR50 | BS19: =IF(COUNT('Marketing'!BS39,'Sales'!BS52,'Customer Success'!BS48,'Support'!BS42,'Engineering'!BS47,'Finance'!BS50)=6,'Marketing'!BS39+'Sales'!BS52+'Customer Success'!BS48+'Support'!BS42+'Engineering'!BS47+'Finance'!BS50,"") | BT19: ='Marketing'!BT39+'Sales'!BT52+'Customer Success'!BT48+'Support'!BT42+'Engineering'!BT47+'Finance'!BT50 | BU19: ='Marketing'!BU39+'Sales'!BU52+'Customer Success'!BU48+'Support'!BU42+'Engineering'!BU47+'Finance'!BU50 | BV19: =IF(COUNT('Marketing'!BV39,'Sales'!BV52,'Customer Success'!BV48,'Support'!BV42,'Engineering'!BV47,'Finance'!BV50)=6,'Marketing'!BV39+'Sales'!BV52+'Customer Success'!BV48+'Support'!BV42+'Engineering'!BV47+'Finance'!BV50,"") | BW19: ='Marketing'!BW39+'Sales'!BW52+'Customer Success'!BW48+'Support'!BW42+'Engineering'!BW47+'Finance'!BW50 | BX19: ='Marketing'!BX39+'Sales'!BX52+'Customer Success'!BX48+'Support'!BX42+'Engineering'!BX47+'Finance'!BX50 | BY19: =IF(COUNT('Marketing'!BY39,'Sales'!BY52,'Customer Success'!BY48,'Support'!BY42,'Engineering'!BY47,'Finance'!BY50)=6,'Marketing'!BY39+'Sales'!BY52+'Customer Success'!BY48+'Support'!BY42+'Engineering'!BY47+'Finance'!BY50,"") | BZ19: ='Marketing'!BZ39+'Sales'!BZ52+'Customer Success'!BZ48+'Support'!BZ42+'Engineering'!BZ47+'Finance'!BZ50 | CA19: ='Marketing'!CA39+'Sales'!CA52+'Customer Success'!CA48+'Support'!CA42+'Engineering'!CA47+'Finance'!CA50 | CB19: =IF(COUNT('Marketing'!CB39,'Sales'!CB52,'Customer Success'!CB48,'Support'!CB42,'Engineering'!CB47,'Finance'!CB50)=6,'Marketing'!CB39+'Sales'!CB52+'Customer Success'!CB48+'Support'!CB42+'Engineering'!CB47+'Finance'!CB50,"") | CC19: ='Marketing'!CC39+'Sales'!CC52+'Customer Success'!CC48+'Support'!CC42+'Engineering'!CC47+'Finance'!CC50 | CD19: ='Marketing'!CD39+'Sales'!CD52+'Customer Success'!CD48+'Support'!CD42+'Engineering'!CD47+'Finance'!CD50 | CE19: =IF(COUNT('Marketing'!CE39,'Sales'!CE52,'Customer Success'!CE48,'Support'!CE42,'Engineering'!CE47,'Finance'!CE50)=6,'Marketing'!CE39+'Sales'!CE52+'Customer Success'!CE48+'Support'!CE42+'Engineering'!CE47+'Finance'!CE50,"") | CF19: ='Marketing'!CF39+'Sales'!CF52+'Customer Success'!CF48+'Support'!CF42+'Engineering'!CF47+'Finance'!CF50 | CG19: ='Marketing'!CG39+'Sales'!CG52+'Customer Success'!CG48+'Support'!CG42+'Engineering'!CG47+'Finance'!CG50 | CH19: =IF(COUNT('Marketing'!CH39,'Sales'!CH52,'Customer Success'!CH48,'Support'!CH42,'Engineering'!CH47,'Finance'!CH50)=6,'Marketing'!CH39+'Sales'!CH52+'Customer Success'!CH48+'Support'!CH42+'Engineering'!CH47+'Finance'!CH50,"") | CI19: ='Marketing'!CI39+'Sales'!CI52+'Customer Success'!CI48+'Support'!CI42+'Engineering'!CI47+'Finance'!CI50 | CJ19: ='Marketing'!CJ39+'Sales'!CJ52+'Customer Success'!CJ48+'Support'!CJ42+'Engineering'!CJ47+'Finance'!CJ50 | CK19: =IF(COUNT('Marketing'!CK39,'Sales'!CK52,'Customer Success'!CK48,'Support'!CK42,'Engineering'!CK47,'Finance'!CK50)=6,'Marketing'!CK39+'Sales'!CK52+'Customer Success'!CK48+'Support'!CK42+'Engineering'!CK47+'Finance'!CK50,"") | CL19: ='Marketing'!CL39+'Sales'!CL52+'Customer Success'!CL48+'Support'!CL42+'Engineering'!CL47+'Finance'!CL50 | CM19: ='Marketing'!CM39+'Sales'!CM52+'Customer Success'!CM48+'Support'!CM42+'Engineering'!CM47+'Finance'!CM50 | CN19: =IF(COUNT('Marketing'!CN39,'Sales'!CN52,'Customer Success'!CN48,'Support'!CN42,'Engineering'!CN47,'Finance'!CN50)=6,'Marketing'!CN39+'Sales'!CN52+'Customer Success'!CN48+'Support'!CN42+'Engineering'!CN47+'Finance'!CN50,"") | CO19: ='Marketing'!CO39+'Sales'!CO52+'Customer Success'!CO48+'Support'!CO42+'Engineering'!CO47+'Finance'!CO50 | CP19: ='Marketing'!CP39+'Sales'!CP52+'Customer Success'!CP48+'Support'!CP42+'Engineering'!CP47+'Finance'!CP50 | CQ19: =IF(COUNT('Marketing'!CQ39,'Sales'!CQ52,'Customer Success'!CQ48,'Support'!CQ42,'Engineering'!CQ47,'Finance'!CQ50)=6,'Marketing'!CQ39+'Sales'!CQ52+'Customer Success'!CQ48+'Support'!CQ42+'Engineering'!CQ47+'Finance'!CQ50,"") | CR19: ='Marketing'!CR39+'Sales'!CR52+'Customer Success'!CR48+'Support'!CR42+'Engineering'!CR47+'Finance'!CR50 | CS19: ='Marketing'!CS39+'Sales'!CS52+'Customer Success'!CS48+'Support'!CS42+'Engineering'!CS47+'Finance'!CS50 | CT19: =IF(COUNT('Marketing'!CT39,'Sales'!CT52,'Customer Success'!CT48,'Support'!CT42,'Engineering'!CT47,'Finance'!CT50)=6,'Marketing'!CT39+'Sales'!CT52+'Customer Success'!CT48+'Support'!CT42+'Engineering'!CT47+'Finance'!CT50,"") | CU19: ='Marketing'!CU39+'Sales'!CU52+'Customer Success'!CU48+'Support'!CU42+'Engineering'!CU47+'Finance'!CU50 | CV19: ='Marketing'!CV39+'Sales'!CV52+'Customer Success'!CV48+'Support'!CV42+'Engineering'!CV47+'Finance'!CV50 | CW19: =IF(COUNT('Marketing'!CW39,'Sales'!CW52,'Customer Success'!CW48,'Support'!CW42,'Engineering'!CW47,'Finance'!CW50)=6,'Marketing'!CW39+'Sales'!CW52+'Customer Success'!CW48+'Support'!CW42+'Engineering'!CW47+'Finance'!CW50,"") | CX19: ='Marketing'!CX39+'Sales'!CX52+'Customer Success'!CX48+'Support'!CX42+'Engineering'!CX47+'Finance'!CX50 | CY19: ='Marketing'!CY39+'Sales'!CY52+'Customer Success'!CY48+'Support'!CY42+'Engineering'!CY47+'Finance'!CY50 | CZ19: =IF(COUNT('Marketing'!CZ39,'Sales'!CZ52,'Customer Success'!CZ48,'Support'!CZ42,'Engineering'!CZ47,'Finance'!CZ50)=6,'Marketing'!CZ39+'Sales'!CZ52+'Customer Success'!CZ48+'Support'!CZ42+'Engineering'!CZ47+'Finance'!CZ50,"") | DA19: ='Marketing'!DA39+'Sales'!DA52+'Customer Success'!DA48+'Support'!DA42+'Engineering'!DA47+'Finance'!DA50 | DB19: ='Marketing'!DB39+'Sales'!DB52+'Customer Success'!DB48+'Support'!DB42+'Engineering'!DB47+'Finance'!DB50 | DC19: =IF(COUNT('Marketing'!DC39,'Sales'!DC52,'Customer Success'!DC48,'Support'!DC42,'Engineering'!DC47,'Finance'!DC50)=6,'Marketing'!DC39+'Sales'!DC52+'Customer Success'!DC48+'Support'!DC42+'Engineering'!DC47+'Finance'!DC50,"") | DD19: ='Marketing'!DD39+'Sales'!DD52+'Customer Success'!DD48+'Support'!DD42+'Engineering'!DD47+'Finance'!DD50 | DE19: ='Marketing'!DE39+'Sales'!DE52+'Customer Success'!DE48+'Support'!DE42+'Engineering'!DE47+'Finance'!DE50 | DF19: =IF(COUNT('Marketing'!DF39,'Sales'!DF52,'Customer Success'!DF48,'Support'!DF42,'Engineering'!DF47,'Finance'!DF50)=6,'Marketing'!DF39+'Sales'!DF52+'Customer Success'!DF48+'Support'!DF42+'Engineering'!DF47+'Finance'!DF50,"") | DG19: ='Marketing'!DG39+'Sales'!DG52+'Customer Success'!DG48+'Support'!DG42+'Engineering'!DG47+'Finance'!DG50 | DH19: ='Marketing'!DH39+'Sales'!DH52+'Customer Success'!DH48+'Support'!DH42+'Engineering'!DH47+'Finance'!DH50 | DI19: =IF(COUNT('Marketing'!DI39,'Sales'!DI52,'Customer Success'!DI48,'Support'!DI42,'Engineering'!DI47,'Finance'!DI50)=6,'Marketing'!DI39+'Sales'!DI52+'Customer Success'!DI48+'Support'!DI42+'Engineering'!DI47+'Finance'!DI50,"") | DJ19: ='Marketing'!DJ39+'Sales'!DJ52+'Customer Success'!DJ48+'Support'!DJ42+'Engineering'!DJ47+'Finance'!DJ50 | DK19: ='Marketing'!DK39+'Sales'!DK52+'Customer Success'!DK48+'Support'!DK42+'Engineering'!DK47+'Finance'!DK50 | DL19: =IF(COUNT('Marketing'!DL39,'Sales'!DL52,'Customer Success'!DL48,'Support'!DL42,'Engineering'!DL47,'Finance'!DL50)=6,'Marketing'!DL39+'Sales'!DL52+'Customer Success'!DL48+'Support'!DL42+'Engineering'!DL47+'Finance'!DL50,"") | DM19: ='Marketing'!DM39+'Sales'!DM52+'Customer Success'!DM48+'Support'!DM42+'Engineering'!DM47+'Finance'!DM50 | DN19: ='Marketing'!DN39+'Sales'!DN52+'Customer Success'!DN48+'Support'!DN42+'Engineering'!DN47+'Finance'!DN50
A20: Closing Cash | B20: =IF(K20<>"",K20,IF(N20<>"",N20,IF(Q20<>"",Q20,IF(T20<>"",T20,IF(W20<>"",W20,IF(Z20<>"",Z20,IF(AC20<>"",AC20,IF(AF20<>"",AF20,IF(AI20<>"",AI20,IF(AL20<>"",AL20,IF(AO20<>"",AO20,IF(AR20<>"",AR20,"")))))))))))) | C20: =IF(L20<>"",L20,IF(O20<>"",O20,IF(R20<>"",R20,IF(U20<>"",U20,IF(X20<>"",X20,IF(AA20<>"",AA20,IF(AD20<>"",AD20,IF(AG20<>"",AG20,IF(AJ20<>"",AJ20,IF(AM20<>"",AM20,IF(AP20<>"",AP20,IF(AS20<>"",AS20,"")))))))))))) | D20: =IF(M20<>"",M20,IF(P20<>"",P20,IF(S20<>"",S20,IF(V20<>"",V20,IF(Y20<>"",Y20,IF(AB20<>"",AB20,IF(AE20<>"",AE20,IF(AH20<>"",AH20,IF(AK20<>"",AK20,IF(AN20<>"",AN20,IF(AQ20<>"",AQ20,IF(AT20<>"",AT20,"")))))))))))) | E20: =IF(AU20<>"",AU20,IF(AX20<>"",AX20,IF(BA20<>"",BA20,IF(BD20<>"",BD20,IF(BG20<>"",BG20,IF(BJ20<>"",BJ20,IF(BM20<>"",BM20,IF(BP20<>"",BP20,IF(BS20<>"",BS20,IF(BV20<>"",BV20,IF(BY20<>"",BY20,IF(CB20<>"",CB20,"")))))))))))) | F20: =IF(AV20<>"",AV20,IF(AY20<>"",AY20,IF(BB20<>"",BB20,IF(BE20<>"",BE20,IF(BH20<>"",BH20,IF(BK20<>"",BK20,IF(BN20<>"",BN20,IF(BQ20<>"",BQ20,IF(BT20<>"",BT20,IF(BW20<>"",BW20,IF(BZ20<>"",BZ20,IF(CC20<>"",CC20,"")))))))))))) | G20: =IF(AW20<>"",AW20,IF(AZ20<>"",AZ20,IF(BC20<>"",BC20,IF(BF20<>"",BF20,IF(BI20<>"",BI20,IF(BL20<>"",BL20,IF(BO20<>"",BO20,IF(BR20<>"",BR20,IF(BU20<>"",BU20,IF(BX20<>"",BX20,IF(CA20<>"",CA20,IF(CD20<>"",CD20,"")))))))))))) | H20: =IF(CE20<>"",CE20,IF(CH20<>"",CH20,IF(CK20<>"",CK20,IF(CN20<>"",CN20,IF(CQ20<>"",CQ20,IF(CT20<>"",CT20,IF(CW20<>"",CW20,IF(CZ20<>"",CZ20,IF(DC20<>"",DC20,IF(DF20<>"",DF20,IF(DI20<>"",DI20,IF(DL20<>"",DL20,"")))))))))))) | I20: =IF(CF20<>"",CF20,IF(CI20<>"",CI20,IF(CL20<>"",CL20,IF(CO20<>"",CO20,IF(CR20<>"",CR20,IF(CU20<>"",CU20,IF(CX20<>"",CX20,IF(DA20<>"",DA20,IF(DD20<>"",DD20,IF(DG20<>"",DG20,IF(DJ20<>"",DJ20,IF(DM20<>"",DM20,"")))))))))))) | J20: =IF(CG20<>"",CG20,IF(CJ20<>"",CJ20,IF(CM20<>"",CM20,IF(CP20<>"",CP20,IF(CS20<>"",CS20,IF(CV20<>"",CV20,IF(CY20<>"",CY20,IF(DB20<>"",DB20,IF(DE20<>"",DE20,IF(DH20<>"",DH20,IF(DK20<>"",DK20,IF(DN20<>"",DN20,"")))))))))))) | K20: =IF(COUNT('Finance'!K11)=1,'Finance'!K11,"") | L20: ='Finance'!L11 | M20: ='Finance'!M11 | N20: =IF(COUNT('Finance'!N11)=1,'Finance'!N11,"") | O20: ='Finance'!O11 | P20: ='Finance'!P11 | Q20: =IF(COUNT('Finance'!Q11)=1,'Finance'!Q11,"") | R20: ='Finance'!R11 | S20: ='Finance'!S11 | T20: =IF(COUNT('Finance'!T11)=1,'Finance'!T11,"") | U20: ='Finance'!U11 | V20: ='Finance'!V11 | W20: =IF(COUNT('Finance'!W11)=1,'Finance'!W11,"") | X20: ='Finance'!X11 | Y20: ='Finance'!Y11 | Z20: =IF(COUNT('Finance'!Z11)=1,'Finance'!Z11,"") | AA20: ='Finance'!AA11 | AB20: ='Finance'!AB11 | AC20: =IF(COUNT('Finance'!AC11)=1,'Finance'!AC11,"") | AD20: ='Finance'!AD11 | AE20: ='Finance'!AE11 | AF20: =IF(COUNT('Finance'!AF11)=1,'Finance'!AF11,"") | AG20: ='Finance'!AG11 | AH20: ='Finance'!AH11 | AI20: =IF(COUNT('Finance'!AI11)=1,'Finance'!AI11,"") | AJ20: ='Finance'!AJ11 | AK20: ='Finance'!AK11 | AL20: =IF(COUNT('Finance'!AL11)=1,'Finance'!AL11,"") | AM20: ='Finance'!AM11 | AN20: ='Finance'!AN11 | AO20: =IF(COUNT('Finance'!AO11)=1,'Finance'!AO11,"") | AP20: ='Finance'!AP11 | AQ20: ='Finance'!AQ11 | AR20: =IF(COUNT('Finance'!AR11)=1,'Finance'!AR11,"") | AS20: ='Finance'!AS11 | AT20: ='Finance'!AT11 | AU20: =IF(COUNT('Finance'!AU11)=1,'Finance'!AU11,"") | AV20: ='Finance'!AV11 | AW20: ='Finance'!AW11 | AX20: =IF(COUNT('Finance'!AX11)=1,'Finance'!AX11,"") | AY20: ='Finance'!AY11 | AZ20: ='Finance'!AZ11 | BA20: =IF(COUNT('Finance'!BA11)=1,'Finance'!BA11,"") | BB20: ='Finance'!BB11 | BC20: ='Finance'!BC11 | BD20: =IF(COUNT('Finance'!BD11)=1,'Finance'!BD11,"") | BE20: ='Finance'!BE11 | BF20: ='Finance'!BF11 | BG20: =IF(COUNT('Finance'!BG11)=1,'Finance'!BG11,"") | BH20: ='Finance'!BH11 | BI20: ='Finance'!BI11 | BJ20: =IF(COUNT('Finance'!BJ11)=1,'Finance'!BJ11,"") | BK20: ='Finance'!BK11 | BL20: ='Finance'!BL11 | BM20: =IF(COUNT('Finance'!BM11)=1,'Finance'!BM11,"") | BN20: ='Finance'!BN11 | BO20: ='Finance'!BO11 | BP20: =IF(COUNT('Finance'!BP11)=1,'Finance'!BP11,"") | BQ20: ='Finance'!BQ11 | BR20: ='Finance'!BR11 | BS20: =IF(COUNT('Finance'!BS11)=1,'Finance'!BS11,"") | BT20: ='Finance'!BT11 | BU20: ='Finance'!BU11 | BV20: =IF(COUNT('Finance'!BV11)=1,'Finance'!BV11,"") | BW20: ='Finance'!BW11 | BX20: ='Finance'!BX11 | BY20: =IF(COUNT('Finance'!BY11)=1,'Finance'!BY11,"") | BZ20: ='Finance'!BZ11 | CA20: ='Finance'!CA11 | CB20: =IF(COUNT('Finance'!CB11)=1,'Finance'!CB11,"") | CC20: ='Finance'!CC11 | CD20: ='Finance'!CD11 | CE20: =IF(COUNT('Finance'!CE11)=1,'Finance'!CE11,"") | CF20: ='Finance'!CF11 | CG20: ='Finance'!CG11 | CH20: =IF(COUNT('Finance'!CH11)=1,'Finance'!CH11,"") | CI20: ='Finance'!CI11 | CJ20: ='Finance'!CJ11 | CK20: =IF(COUNT('Finance'!CK11)=1,'Finance'!CK11,"") | CL20: ='Finance'!CL11 | CM20: ='Finance'!CM11 | CN20: =IF(COUNT('Finance'!CN11)=1,'Finance'!CN11,"") | CO20: ='Finance'!CO11 | CP20: ='Finance'!CP11 | CQ20: =IF(COUNT('Finance'!CQ11)=1,'Finance'!CQ11,"") | CR20: ='Finance'!CR11 | CS20: ='Finance'!CS11 | CT20: =IF(COUNT('Finance'!CT11)=1,'Finance'!CT11,"") | CU20: ='Finance'!CU11 | CV20: ='Finance'!CV11 | CW20: =IF(COUNT('Finance'!CW11)=1,'Finance'!CW11,"") | CX20: ='Finance'!CX11 | CY20: ='Finance'!CY11 | CZ20: =IF(COUNT('Finance'!CZ11)=1,'Finance'!CZ11,"") | DA20: ='Finance'!DA11 | DB20: ='Finance'!DB11 | DC20: =IF(COUNT('Finance'!DC11)=1,'Finance'!DC11,"") | DD20: ='Finance'!DD11 | DE20: ='Finance'!DE11 | DF20: =IF(COUNT('Finance'!DF11)=1,'Finance'!DF11,"") | DG20: ='Finance'!DG11 | DH20: ='Finance'!DH11 | DI20: =IF(COUNT('Finance'!DI11)=1,'Finance'!DI11,"") | DJ20: ='Finance'!DJ11 | DK20: ='Finance'!DK11 | DL20: =IF(COUNT('Finance'!DL11)=1,'Finance'!DL11,"") | DM20: ='Finance'!DM11 | DN20: ='Finance'!DN11
A21: Reserve in Months | B21: =IF(K21<>"",K21,IF(N21<>"",N21,IF(Q21<>"",Q21,IF(T21<>"",T21,IF(W21<>"",W21,IF(Z21<>"",Z21,IF(AC21<>"",AC21,IF(AF21<>"",AF21,IF(AI21<>"",AI21,IF(AL21<>"",AL21,IF(AO21<>"",AO21,IF(AR21<>"",AR21,"")))))))))))) | C21: =IF(L21<>"",L21,IF(O21<>"",O21,IF(R21<>"",R21,IF(U21<>"",U21,IF(X21<>"",X21,IF(AA21<>"",AA21,IF(AD21<>"",AD21,IF(AG21<>"",AG21,IF(AJ21<>"",AJ21,IF(AM21<>"",AM21,IF(AP21<>"",AP21,IF(AS21<>"",AS21,"")))))))))))) | D21: =IF(M21<>"",M21,IF(P21<>"",P21,IF(S21<>"",S21,IF(V21<>"",V21,IF(Y21<>"",Y21,IF(AB21<>"",AB21,IF(AE21<>"",AE21,IF(AH21<>"",AH21,IF(AK21<>"",AK21,IF(AN21<>"",AN21,IF(AQ21<>"",AQ21,IF(AT21<>"",AT21,"")))))))))))) | E21: =IF(AU21<>"",AU21,IF(AX21<>"",AX21,IF(BA21<>"",BA21,IF(BD21<>"",BD21,IF(BG21<>"",BG21,IF(BJ21<>"",BJ21,IF(BM21<>"",BM21,IF(BP21<>"",BP21,IF(BS21<>"",BS21,IF(BV21<>"",BV21,IF(BY21<>"",BY21,IF(CB21<>"",CB21,"")))))))))))) | F21: =IF(AV21<>"",AV21,IF(AY21<>"",AY21,IF(BB21<>"",BB21,IF(BE21<>"",BE21,IF(BH21<>"",BH21,IF(BK21<>"",BK21,IF(BN21<>"",BN21,IF(BQ21<>"",BQ21,IF(BT21<>"",BT21,IF(BW21<>"",BW21,IF(BZ21<>"",BZ21,IF(CC21<>"",CC21,"")))))))))))) | G21: =IF(AW21<>"",AW21,IF(AZ21<>"",AZ21,IF(BC21<>"",BC21,IF(BF21<>"",BF21,IF(BI21<>"",BI21,IF(BL21<>"",BL21,IF(BO21<>"",BO21,IF(BR21<>"",BR21,IF(BU21<>"",BU21,IF(BX21<>"",BX21,IF(CA21<>"",CA21,IF(CD21<>"",CD21,"")))))))))))) | H21: =IF(CE21<>"",CE21,IF(CH21<>"",CH21,IF(CK21<>"",CK21,IF(CN21<>"",CN21,IF(CQ21<>"",CQ21,IF(CT21<>"",CT21,IF(CW21<>"",CW21,IF(CZ21<>"",CZ21,IF(DC21<>"",DC21,IF(DF21<>"",DF21,IF(DI21<>"",DI21,IF(DL21<>"",DL21,"")))))))))))) | I21: =IF(CF21<>"",CF21,IF(CI21<>"",CI21,IF(CL21<>"",CL21,IF(CO21<>"",CO21,IF(CR21<>"",CR21,IF(CU21<>"",CU21,IF(CX21<>"",CX21,IF(DA21<>"",DA21,IF(DD21<>"",DD21,IF(DG21<>"",DG21,IF(DJ21<>"",DJ21,IF(DM21<>"",DM21,"")))))))))))) | J21: =IF(CG21<>"",CG21,IF(CJ21<>"",CJ21,IF(CM21<>"",CM21,IF(CP21<>"",CP21,IF(CS21<>"",CS21,IF(CV21<>"",CV21,IF(CY21<>"",CY21,IF(DB21<>"",DB21,IF(DE21<>"",DE21,IF(DH21<>"",DH21,IF(DK21<>"",DK21,IF(DN21<>"",DN21,"")))))))))))) | K21: =IF(COUNT('Finance'!K12)=1,'Finance'!K12,"") | L21: ='Finance'!L12 | M21: ='Finance'!M12 | N21: =IF(COUNT('Finance'!N12)=1,'Finance'!N12,"") | O21: ='Finance'!O12 | P21: ='Finance'!P12 | Q21: =IF(COUNT('Finance'!Q12)=1,'Finance'!Q12,"") | R21: ='Finance'!R12 | S21: ='Finance'!S12 | T21: =IF(COUNT('Finance'!T12)=1,'Finance'!T12,"") | U21: ='Finance'!U12 | V21: ='Finance'!V12 | W21: =IF(COUNT('Finance'!W12)=1,'Finance'!W12,"") | X21: ='Finance'!X12 | Y21: ='Finance'!Y12 | Z21: =IF(COUNT('Finance'!Z12)=1,'Finance'!Z12,"") | AA21: ='Finance'!AA12 | AB21: ='Finance'!AB12 | AC21: =IF(COUNT('Finance'!AC12)=1,'Finance'!AC12,"") | AD21: ='Finance'!AD12 | AE21: ='Finance'!AE12 | AF21: =IF(COUNT('Finance'!AF12)=1,'Finance'!AF12,"") | AG21: ='Finance'!AG12 | AH21: ='Finance'!AH12 | AI21: =IF(COUNT('Finance'!AI12)=1,'Finance'!AI12,"") | AJ21: ='Finance'!AJ12 | AK21: ='Finance'!AK12 | AL21: =IF(COUNT('Finance'!AL12)=1,'Finance'!AL12,"") | AM21: ='Finance'!AM12 | AN21: ='Finance'!AN12 | AO21: =IF(COUNT('Finance'!AO12)=1,'Finance'!AO12,"") | AP21: ='Finance'!AP12 | AQ21: ='Finance'!AQ12 | AR21: =IF(COUNT('Finance'!AR12)=1,'Finance'!AR12,"") | AS21: ='Finance'!AS12 | AT21: ='Finance'!AT12 | AU21: =IF(COUNT('Finance'!AU12)=1,'Finance'!AU12,"") | AV21: ='Finance'!AV12 | AW21: ='Finance'!AW12 | AX21: =IF(COUNT('Finance'!AX12)=1,'Finance'!AX12,"") | AY21: ='Finance'!AY12 | AZ21: ='Finance'!AZ12 | BA21: =IF(COUNT('Finance'!BA12)=1,'Finance'!BA12,"") | BB21: ='Finance'!BB12 | BC21: ='Finance'!BC12 | BD21: =IF(COUNT('Finance'!BD12)=1,'Finance'!BD12,"") | BE21: ='Finance'!BE12 | BF21: ='Finance'!BF12 | BG21: =IF(COUNT('Finance'!BG12)=1,'Finance'!BG12,"") | BH21: ='Finance'!BH12 | BI21: ='Finance'!BI12 | BJ21: =IF(COUNT('Finance'!BJ12)=1,'Finance'!BJ12,"") | BK21: ='Finance'!BK12 | BL21: ='Finance'!BL12 | BM21: =IF(COUNT('Finance'!BM12)=1,'Finance'!BM12,"") | BN21: ='Finance'!BN12 | BO21: ='Finance'!BO12 | BP21: =IF(COUNT('Finance'!BP12)=1,'Finance'!BP12,"") | BQ21: ='Finance'!BQ12 | BR21: ='Finance'!BR12 | BS21: =IF(COUNT('Finance'!BS12)=1,'Finance'!BS12,"") | BT21: ='Finance'!BT12 | BU21: ='Finance'!BU12 | BV21: =IF(COUNT('Finance'!BV12)=1,'Finance'!BV12,"") | BW21: ='Finance'!BW12 | BX21: ='Finance'!BX12 | BY21: =IF(COUNT('Finance'!BY12)=1,'Finance'!BY12,"") | BZ21: ='Finance'!BZ12 | CA21: ='Finance'!CA12 | CB21: =IF(COUNT('Finance'!CB12)=1,'Finance'!CB12,"") | CC21: ='Finance'!CC12 | CD21: ='Finance'!CD12 | CE21: =IF(COUNT('Finance'!CE12)=1,'Finance'!CE12,"") | CF21: ='Finance'!CF12 | CG21: ='Finance'!CG12 | CH21: =IF(COUNT('Finance'!CH12)=1,'Finance'!CH12,"") | CI21: ='Finance'!CI12 | CJ21: ='Finance'!CJ12 | CK21: =IF(COUNT('Finance'!CK12)=1,'Finance'!CK12,"") | CL21: ='Finance'!CL12 | CM21: ='Finance'!CM12 | CN21: =IF(COUNT('Finance'!CN12)=1,'Finance'!CN12,"") | CO21: ='Finance'!CO12 | CP21: ='Finance'!CP12 | CQ21: =IF(COUNT('Finance'!CQ12)=1,'Finance'!CQ12,"") | CR21: ='Finance'!CR12 | CS21: ='Finance'!CS12 | CT21: =IF(COUNT('Finance'!CT12)=1,'Finance'!CT12,"") | CU21: ='Finance'!CU12 | CV21: ='Finance'!CV12 | CW21: =IF(COUNT('Finance'!CW12)=1,'Finance'!CW12,"") | CX21: ='Finance'!CX12 | CY21: ='Finance'!CY12 | CZ21: =IF(COUNT('Finance'!CZ12)=1,'Finance'!CZ12,"") | DA21: ='Finance'!DA12 | DB21: ='Finance'!DB12 | DC21: =IF(COUNT('Finance'!DC12)=1,'Finance'!DC12,"") | DD21: ='Finance'!DD12 | DE21: ='Finance'!DE12 | DF21: =IF(COUNT('Finance'!DF12)=1,'Finance'!DF12,"") | DG21: ='Finance'!DG12 | DH21: ='Finance'!DH12 | DI21: =IF(COUNT('Finance'!DI12)=1,'Finance'!DI12,"") | DJ21: ='Finance'!DJ12 | DK21: ='Finance'!DK12 | DL21: =IF(COUNT('Finance'!DL12)=1,'Finance'!DL12,"") | DM21: ='Finance'!DM12 | DN21: ='Finance'!DN12
A22: Growth Efficiency | B22: =IF(OR(N(SUM('Marketing'!AR28,'Sales'!AR24,'Marketing'!AO28,'Sales'!AO24,'Marketing'!AL28,'Sales'!AL24,'Marketing'!AI28,'Sales'!AI24,'Marketing'!AF28,'Sales'!AF24,'Marketing'!AC28,'Sales'!AC24,'Marketing'!Z28,'Sales'!Z24,'Marketing'!W28,'Sales'!W24,'Marketing'!T28,'Sales'!T24,'Marketing'!Q28,'Sales'!Q24,'Marketing'!N28,'Sales'!N24,'Marketing'!K28,'Sales'!K24))=0,N(B4)=0),"",B4*12/(SUM('Marketing'!AR28,'Sales'!AR24,'Marketing'!AO28,'Sales'!AO24,'Marketing'!AL28,'Sales'!AL24,'Marketing'!AI28,'Sales'!AI24,'Marketing'!AF28,'Sales'!AF24,'Marketing'!AC28,'Sales'!AC24,'Marketing'!Z28,'Sales'!Z24,'Marketing'!W28,'Sales'!W24,'Marketing'!T28,'Sales'!T24,'Marketing'!Q28,'Sales'!Q24,'Marketing'!N28,'Sales'!N24,'Marketing'!K28,'Sales'!K24))) | C22: =IF(OR(N(SUM('Marketing'!AS28,'Sales'!AS24,'Marketing'!AP28,'Sales'!AP24,'Marketing'!AM28,'Sales'!AM24,'Marketing'!AJ28,'Sales'!AJ24,'Marketing'!AG28,'Sales'!AG24,'Marketing'!AD28,'Sales'!AD24,'Marketing'!AA28,'Sales'!AA24,'Marketing'!X28,'Sales'!X24,'Marketing'!U28,'Sales'!U24,'Marketing'!R28,'Sales'!R24,'Marketing'!O28,'Sales'!O24,'Marketing'!L28,'Sales'!L24))=0,N(C4)=0),"",C4*12/(SUM('Marketing'!AS28,'Sales'!AS24,'Marketing'!AP28,'Sales'!AP24,'Marketing'!AM28,'Sales'!AM24,'Marketing'!AJ28,'Sales'!AJ24,'Marketing'!AG28,'Sales'!AG24,'Marketing'!AD28,'Sales'!AD24,'Marketing'!AA28,'Sales'!AA24,'Marketing'!X28,'Sales'!X24,'Marketing'!U28,'Sales'!U24,'Marketing'!R28,'Sales'!R24,'Marketing'!O28,'Sales'!O24,'Marketing'!L28,'Sales'!L24))) | D22: =IF(OR(N(SUM('Marketing'!AT28,'Sales'!AT24,'Marketing'!AQ28,'Sales'!AQ24,'Marketing'!AN28,'Sales'!AN24,'Marketing'!AK28,'Sales'!AK24,'Marketing'!AH28,'Sales'!AH24,'Marketing'!AE28,'Sales'!AE24,'Marketing'!AB28,'Sales'!AB24,'Marketing'!Y28,'Sales'!Y24,'Marketing'!V28,'Sales'!V24,'Marketing'!S28,'Sales'!S24,'Marketing'!P28,'Sales'!P24,'Marketing'!M28,'Sales'!M24))=0,N(D4)=0),"",D4*12/(SUM('Marketing'!AT28,'Sales'!AT24,'Marketing'!AQ28,'Sales'!AQ24,'Marketing'!AN28,'Sales'!AN24,'Marketing'!AK28,'Sales'!AK24,'Marketing'!AH28,'Sales'!AH24,'Marketing'!AE28,'Sales'!AE24,'Marketing'!AB28,'Sales'!AB24,'Marketing'!Y28,'Sales'!Y24,'Marketing'!V28,'Sales'!V24,'Marketing'!S28,'Sales'!S24,'Marketing'!P28,'Sales'!P24,'Marketing'!M28,'Sales'!M24))) | E22: =IF(OR(N(SUM('Marketing'!CB28,'Sales'!CB24,'Marketing'!BY28,'Sales'!BY24,'Marketing'!BV28,'Sales'!BV24,'Marketing'!BS28,'Sales'!BS24,'Marketing'!BP28,'Sales'!BP24,'Marketing'!BM28,'Sales'!BM24,'Marketing'!BJ28,'Sales'!BJ24,'Marketing'!BG28,'Sales'!BG24,'Marketing'!BD28,'Sales'!BD24,'Marketing'!BA28,'Sales'!BA24,'Marketing'!AX28,'Sales'!AX24,'Marketing'!AU28,'Sales'!AU24))=0,N(E4)=0),"",E4*12/(SUM('Marketing'!CB28,'Sales'!CB24,'Marketing'!BY28,'Sales'!BY24,'Marketing'!BV28,'Sales'!BV24,'Marketing'!BS28,'Sales'!BS24,'Marketing'!BP28,'Sales'!BP24,'Marketing'!BM28,'Sales'!BM24,'Marketing'!BJ28,'Sales'!BJ24,'Marketing'!BG28,'Sales'!BG24,'Marketing'!BD28,'Sales'!BD24,'Marketing'!BA28,'Sales'!BA24,'Marketing'!AX28,'Sales'!AX24,'Marketing'!AU28,'Sales'!AU24))) | F22: =IF(OR(N(SUM('Marketing'!CC28,'Sales'!CC24,'Marketing'!BZ28,'Sales'!BZ24,'Marketing'!BW28,'Sales'!BW24,'Marketing'!BT28,'Sales'!BT24,'Marketing'!BQ28,'Sales'!BQ24,'Marketing'!BN28,'Sales'!BN24,'Marketing'!BK28,'Sales'!BK24,'Marketing'!BH28,'Sales'!BH24,'Marketing'!BE28,'Sales'!BE24,'Marketing'!BB28,'Sales'!BB24,'Marketing'!AY28,'Sales'!AY24,'Marketing'!AV28,'Sales'!AV24))=0,N(F4)=0),"",F4*12/(SUM('Marketing'!CC28,'Sales'!CC24,'Marketing'!BZ28,'Sales'!BZ24,'Marketing'!BW28,'Sales'!BW24,'Marketing'!BT28,'Sales'!BT24,'Marketing'!BQ28,'Sales'!BQ24,'Marketing'!BN28,'Sales'!BN24,'Marketing'!BK28,'Sales'!BK24,'Marketing'!BH28,'Sales'!BH24,'Marketing'!BE28,'Sales'!BE24,'Marketing'!BB28,'Sales'!BB24,'Marketing'!AY28,'Sales'!AY24,'Marketing'!AV28,'Sales'!AV24))) | G22: =IF(OR(N(SUM('Marketing'!CD28,'Sales'!CD24,'Marketing'!CA28,'Sales'!CA24,'Marketing'!BX28,'Sales'!BX24,'Marketing'!BU28,'Sales'!BU24,'Marketing'!BR28,'Sales'!BR24,'Marketing'!BO28,'Sales'!BO24,'Marketing'!BL28,'Sales'!BL24,'Marketing'!BI28,'Sales'!BI24,'Marketing'!BF28,'Sales'!BF24,'Marketing'!BC28,'Sales'!BC24,'Marketing'!AZ28,'Sales'!AZ24,'Marketing'!AW28,'Sales'!AW24))=0,N(G4)=0),"",G4*12/(SUM('Marketing'!CD28,'Sales'!CD24,'Marketing'!CA28,'Sales'!CA24,'Marketing'!BX28,'Sales'!BX24,'Marketing'!BU28,'Sales'!BU24,'Marketing'!BR28,'Sales'!BR24,'Marketing'!BO28,'Sales'!BO24,'Marketing'!BL28,'Sales'!BL24,'Marketing'!BI28,'Sales'!BI24,'Marketing'!BF28,'Sales'!BF24,'Marketing'!BC28,'Sales'!BC24,'Marketing'!AZ28,'Sales'!AZ24,'Marketing'!AW28,'Sales'!AW24))) | H22: =IF(OR(N(SUM('Marketing'!DL28,'Sales'!DL24,'Marketing'!DI28,'Sales'!DI24,'Marketing'!DF28,'Sales'!DF24,'Marketing'!DC28,'Sales'!DC24,'Marketing'!CZ28,'Sales'!CZ24,'Marketing'!CW28,'Sales'!CW24,'Marketing'!CT28,'Sales'!CT24,'Marketing'!CQ28,'Sales'!CQ24,'Marketing'!CN28,'Sales'!CN24,'Marketing'!CK28,'Sales'!CK24,'Marketing'!CH28,'Sales'!CH24,'Marketing'!CE28,'Sales'!CE24))=0,N(H4)=0),"",H4*12/(SUM('Marketing'!DL28,'Sales'!DL24,'Marketing'!DI28,'Sales'!DI24,'Marketing'!DF28,'Sales'!DF24,'Marketing'!DC28,'Sales'!DC24,'Marketing'!CZ28,'Sales'!CZ24,'Marketing'!CW28,'Sales'!CW24,'Marketing'!CT28,'Sales'!CT24,'Marketing'!CQ28,'Sales'!CQ24,'Marketing'!CN28,'Sales'!CN24,'Marketing'!CK28,'Sales'!CK24,'Marketing'!CH28,'Sales'!CH24,'Marketing'!CE28,'Sales'!CE24))) | I22: =IF(OR(N(SUM('Marketing'!DM28,'Sales'!DM24,'Marketing'!DJ28,'Sales'!DJ24,'Marketing'!DG28,'Sales'!DG24,'Marketing'!DD28,'Sales'!DD24,'Marketing'!DA28,'Sales'!DA24,'Marketing'!CX28,'Sales'!CX24,'Marketing'!CU28,'Sales'!CU24,'Marketing'!CR28,'Sales'!CR24,'Marketing'!CO28,'Sales'!CO24,'Marketing'!CL28,'Sales'!CL24,'Marketing'!CI28,'Sales'!CI24,'Marketing'!CF28,'Sales'!CF24))=0,N(I4)=0),"",I4*12/(SUM('Marketing'!DM28,'Sales'!DM24,'Marketing'!DJ28,'Sales'!DJ24,'Marketing'!DG28,'Sales'!DG24,'Marketing'!DD28,'Sales'!DD24,'Marketing'!DA28,'Sales'!DA24,'Marketing'!CX28,'Sales'!CX24,'Marketing'!CU28,'Sales'!CU24,'Marketing'!CR28,'Sales'!CR24,'Marketing'!CO28,'Sales'!CO24,'Marketing'!CL28,'Sales'!CL24,'Marketing'!CI28,'Sales'!CI24,'Marketing'!CF28,'Sales'!CF24))) | J22: =IF(OR(N(SUM('Marketing'!DN28,'Sales'!DN24,'Marketing'!DK28,'Sales'!DK24,'Marketing'!DH28,'Sales'!DH24,'Marketing'!DE28,'Sales'!DE24,'Marketing'!DB28,'Sales'!DB24,'Marketing'!CY28,'Sales'!CY24,'Marketing'!CV28,'Sales'!CV24,'Marketing'!CS28,'Sales'!CS24,'Marketing'!CP28,'Sales'!CP24,'Marketing'!CM28,'Sales'!CM24,'Marketing'!CJ28,'Sales'!CJ24,'Marketing'!CG28,'Sales'!CG24))=0,N(J4)=0),"",J4*12/(SUM('Marketing'!DN28,'Sales'!DN24,'Marketing'!DK28,'Sales'!DK24,'Marketing'!DH28,'Sales'!DH24,'Marketing'!DE28,'Sales'!DE24,'Marketing'!DB28,'Sales'!DB24,'Marketing'!CY28,'Sales'!CY24,'Marketing'!CV28,'Sales'!CV24,'Marketing'!CS28,'Sales'!CS24,'Marketing'!CP28,'Sales'!CP24,'Marketing'!CM28,'Sales'!CM24,'Marketing'!CJ28,'Sales'!CJ24,'Marketing'!CG28,'Sales'!CG24))) | K22: =IF(COUNT(K4,'Marketing'!N28,'Sales'!N24)=3,IF(N(SUM('Marketing'!N28,'Sales'!N24))=0,"",K4*12/(SUM('Marketing'!N28,'Sales'!N24))),"") | L22: =IF(N(SUM('Marketing'!O28,'Sales'!O24))=0,"",L4*12/(SUM('Marketing'!O28,'Sales'!O24))) | M22: =IF(N(SUM('Marketing'!P28,'Sales'!P24))=0,"",M4*12/(SUM('Marketing'!P28,'Sales'!P24))) | N22: =IF(COUNT(N4,'Marketing'!Q28,'Sales'!Q24)=3,IF(N(SUM('Marketing'!Q28,'Sales'!Q24))=0,"",N4*12/(SUM('Marketing'!Q28,'Sales'!Q24))),"") | O22: =IF(N(SUM('Marketing'!R28,'Sales'!R24))=0,"",O4*12/(SUM('Marketing'!R28,'Sales'!R24))) | P22: =IF(N(SUM('Marketing'!S28,'Sales'!S24))=0,"",P4*12/(SUM('Marketing'!S28,'Sales'!S24))) | Q22: =IF(COUNT(Q4,'Marketing'!T28,'Sales'!T24)=3,IF(N(SUM('Marketing'!T28,'Sales'!T24))=0,"",Q4*12/(SUM('Marketing'!T28,'Sales'!T24))),"") | R22: =IF(N(SUM('Marketing'!U28,'Sales'!U24))=0,"",R4*12/(SUM('Marketing'!U28,'Sales'!U24))) | S22: =IF(N(SUM('Marketing'!V28,'Sales'!V24))=0,"",S4*12/(SUM('Marketing'!V28,'Sales'!V24))) | T22: =IF(COUNT(T4,'Marketing'!W28,'Sales'!W24)=3,IF(N(SUM('Marketing'!W28,'Sales'!W24))=0,"",T4*12/(SUM('Marketing'!W28,'Sales'!W24))),"") | U22: =IF(N(SUM('Marketing'!X28,'Sales'!X24))=0,"",U4*12/(SUM('Marketing'!X28,'Sales'!X24))) | V22: =IF(N(SUM('Marketing'!Y28,'Sales'!Y24))=0,"",V4*12/(SUM('Marketing'!Y28,'Sales'!Y24))) | W22: =IF(COUNT(W4,'Marketing'!Z28,'Sales'!Z24)=3,IF(N(SUM('Marketing'!Z28,'Sales'!Z24))=0,"",W4*12/(SUM('Marketing'!Z28,'Sales'!Z24))),"") | X22: =IF(N(SUM('Marketing'!AA28,'Sales'!AA24))=0,"",X4*12/(SUM('Marketing'!AA28,'Sales'!AA24))) | Y22: =IF(N(SUM('Marketing'!AB28,'Sales'!AB24))=0,"",Y4*12/(SUM('Marketing'!AB28,'Sales'!AB24))) | Z22: =IF(COUNT(Z4,'Marketing'!AC28,'Sales'!AC24)=3,IF(N(SUM('Marketing'!AC28,'Sales'!AC24))=0,"",Z4*12/(SUM('Marketing'!AC28,'Sales'!AC24))),"") | AA22: =IF(N(SUM('Marketing'!AD28,'Sales'!AD24))=0,"",AA4*12/(SUM('Marketing'!AD28,'Sales'!AD24))) | AB22: =IF(N(SUM('Marketing'!AE28,'Sales'!AE24))=0,"",AB4*12/(SUM('Marketing'!AE28,'Sales'!AE24))) | AC22: =IF(COUNT(AC4,'Marketing'!AF28,'Sales'!AF24)=3,IF(N(SUM('Marketing'!AF28,'Sales'!AF24))=0,"",AC4*12/(SUM('Marketing'!AF28,'Sales'!AF24))),"") | AD22: =IF(N(SUM('Marketing'!AG28,'Sales'!AG24))=0,"",AD4*12/(SUM('Marketing'!AG28,'Sales'!AG24))) | AE22: =IF(N(SUM('Marketing'!AH28,'Sales'!AH24))=0,"",AE4*12/(SUM('Marketing'!AH28,'Sales'!AH24))) | AF22: =IF(COUNT(AF4,'Marketing'!AI28,'Sales'!AI24)=3,IF(N(SUM('Marketing'!AI28,'Sales'!AI24))=0,"",AF4*12/(SUM('Marketing'!AI28,'Sales'!AI24))),"") | AG22: =IF(N(SUM('Marketing'!AJ28,'Sales'!AJ24))=0,"",AG4*12/(SUM('Marketing'!AJ28,'Sales'!AJ24))) | AH22: =IF(N(SUM('Marketing'!AK28,'Sales'!AK24))=0,"",AH4*12/(SUM('Marketing'!AK28,'Sales'!AK24))) | AI22: =IF(COUNT(AI4,'Marketing'!AL28,'Sales'!AL24)=3,IF(N(SUM('Marketing'!AL28,'Sales'!AL24))=0,"",AI4*12/(SUM('Marketing'!AL28,'Sales'!AL24))),"") | AJ22: =IF(N(SUM('Marketing'!AM28,'Sales'!AM24))=0,"",AJ4*12/(SUM('Marketing'!AM28,'Sales'!AM24))) | AK22: =IF(N(SUM('Marketing'!AN28,'Sales'!AN24))=0,"",AK4*12/(SUM('Marketing'!AN28,'Sales'!AN24))) | AL22: =IF(COUNT(AL4,'Marketing'!AO28,'Sales'!AO24)=3,IF(N(SUM('Marketing'!AO28,'Sales'!AO24))=0,"",AL4*12/(SUM('Marketing'!AO28,'Sales'!AO24))),"") | AM22: =IF(N(SUM('Marketing'!AP28,'Sales'!AP24))=0,"",AM4*12/(SUM('Marketing'!AP28,'Sales'!AP24))) | AN22: =IF(N(SUM('Marketing'!AQ28,'Sales'!AQ24))=0,"",AN4*12/(SUM('Marketing'!AQ28,'Sales'!AQ24))) | AO22: =IF(COUNT(AO4,'Marketing'!AR28,'Sales'!AR24)=3,IF(N(SUM('Marketing'!AR28,'Sales'!AR24))=0,"",AO4*12/(SUM('Marketing'!AR28,'Sales'!AR24))),"") | AP22: =IF(N(SUM('Marketing'!AS28,'Sales'!AS24))=0,"",AP4*12/(SUM('Marketing'!AS28,'Sales'!AS24))) | AQ22: =IF(N(SUM('Marketing'!AT28,'Sales'!AT24))=0,"",AQ4*12/(SUM('Marketing'!AT28,'Sales'!AT24))) | AR22: =IF(COUNT(AR4,'Marketing'!AU28,'Sales'!AU24)=3,IF(N(SUM('Marketing'!AU28,'Sales'!AU24))=0,"",AR4*12/(SUM('Marketing'!AU28,'Sales'!AU24))),"") | AS22: =IF(N(SUM('Marketing'!AV28,'Sales'!AV24))=0,"",AS4*12/(SUM('Marketing'!AV28,'Sales'!AV24))) | AT22: =IF(N(SUM('Marketing'!AW28,'Sales'!AW24))=0,"",AT4*12/(SUM('Marketing'!AW28,'Sales'!AW24))) | AU22: =IF(COUNT(AU4,'Marketing'!AX28,'Sales'!AX24)=3,IF(N(SUM('Marketing'!AX28,'Sales'!AX24))=0,"",AU4*12/(SUM('Marketing'!AX28,'Sales'!AX24))),"") | AV22: =IF(N(SUM('Marketing'!AY28,'Sales'!AY24))=0,"",AV4*12/(SUM('Marketing'!AY28,'Sales'!AY24))) | AW22: =IF(N(SUM('Marketing'!AZ28,'Sales'!AZ24))=0,"",AW4*12/(SUM('Marketing'!AZ28,'Sales'!AZ24))) | AX22: =IF(COUNT(AX4,'Marketing'!BA28,'Sales'!BA24)=3,IF(N(SUM('Marketing'!BA28,'Sales'!BA24))=0,"",AX4*12/(SUM('Marketing'!BA28,'Sales'!BA24))),"") | AY22: =IF(N(SUM('Marketing'!BB28,'Sales'!BB24))=0,"",AY4*12/(SUM('Marketing'!BB28,'Sales'!BB24))) | AZ22: =IF(N(SUM('Marketing'!BC28,'Sales'!BC24))=0,"",AZ4*12/(SUM('Marketing'!BC28,'Sales'!BC24))) | BA22: =IF(COUNT(BA4,'Marketing'!BD28,'Sales'!BD24)=3,IF(N(SUM('Marketing'!BD28,'Sales'!BD24))=0,"",BA4*12/(SUM('Marketing'!BD28,'Sales'!BD24))),"") | BB22: =IF(N(SUM('Marketing'!BE28,'Sales'!BE24))=0,"",BB4*12/(SUM('Marketing'!BE28,'Sales'!BE24))) | BC22: =IF(N(SUM('Marketing'!BF28,'Sales'!BF24))=0,"",BC4*12/(SUM('Marketing'!BF28,'Sales'!BF24))) | BD22: =IF(COUNT(BD4,'Marketing'!BG28,'Sales'!BG24)=3,IF(N(SUM('Marketing'!BG28,'Sales'!BG24))=0,"",BD4*12/(SUM('Marketing'!BG28,'Sales'!BG24))),"") | BE22: =IF(N(SUM('Marketing'!BH28,'Sales'!BH24))=0,"",BE4*12/(SUM('Marketing'!BH28,'Sales'!BH24))) | BF22: =IF(N(SUM('Marketing'!BI28,'Sales'!BI24))=0,"",BF4*12/(SUM('Marketing'!BI28,'Sales'!BI24))) | BG22: =IF(COUNT(BG4,'Marketing'!BJ28,'Sales'!BJ24)=3,IF(N(SUM('Marketing'!BJ28,'Sales'!BJ24))=0,"",BG4*12/(SUM('Marketing'!BJ28,'Sales'!BJ24))),"") | BH22: =IF(N(SUM('Marketing'!BK28,'Sales'!BK24))=0,"",BH4*12/(SUM('Marketing'!BK28,'Sales'!BK24))) | BI22: =IF(N(SUM('Marketing'!BL28,'Sales'!BL24))=0,"",BI4*12/(SUM('Marketing'!BL28,'Sales'!BL24))) | BJ22: =IF(COUNT(BJ4,'Marketing'!BM28,'Sales'!BM24)=3,IF(N(SUM('Marketing'!BM28,'Sales'!BM24))=0,"",BJ4*12/(SUM('Marketing'!BM28,'Sales'!BM24))),"") | BK22: =IF(N(SUM('Marketing'!BN28,'Sales'!BN24))=0,"",BK4*12/(SUM('Marketing'!BN28,'Sales'!BN24))) | BL22: =IF(N(SUM('Marketing'!BO28,'Sales'!BO24))=0,"",BL4*12/(SUM('Marketing'!BO28,'Sales'!BO24))) | BM22: =IF(COUNT(BM4,'Marketing'!BP28,'Sales'!BP24)=3,IF(N(SUM('Marketing'!BP28,'Sales'!BP24))=0,"",BM4*12/(SUM('Marketing'!BP28,'Sales'!BP24))),"") | BN22: =IF(N(SUM('Marketing'!BQ28,'Sales'!BQ24))=0,"",BN4*12/(SUM('Marketing'!BQ28,'Sales'!BQ24))) | BO22: =IF(N(SUM('Marketing'!BR28,'Sales'!BR24))=0,"",BO4*12/(SUM('Marketing'!BR28,'Sales'!BR24))) | BP22: =IF(COUNT(BP4,'Marketing'!BS28,'Sales'!BS24)=3,IF(N(SUM('Marketing'!BS28,'Sales'!BS24))=0,"",BP4*12/(SUM('Marketing'!BS28,'Sales'!BS24))),"") | BQ22: =IF(N(SUM('Marketing'!BT28,'Sales'!BT24))=0,"",BQ4*12/(SUM('Marketing'!BT28,'Sales'!BT24))) | BR22: =IF(N(SUM('Marketing'!BU28,'Sales'!BU24))=0,"",BR4*12/(SUM('Marketing'!BU28,'Sales'!BU24))) | BS22: =IF(COUNT(BS4,'Marketing'!BV28,'Sales'!BV24)=3,IF(N(SUM('Marketing'!BV28,'Sales'!BV24))=0,"",BS4*12/(SUM('Marketing'!BV28,'Sales'!BV24))),"") | BT22: =IF(N(SUM('Marketing'!BW28,'Sales'!BW24))=0,"",BT4*12/(SUM('Marketing'!BW28,'Sales'!BW24))) | BU22: =IF(N(SUM('Marketing'!BX28,'Sales'!BX24))=0,"",BU4*12/(SUM('Marketing'!BX28,'Sales'!BX24))) | BV22: =IF(COUNT(BV4,'Marketing'!BY28,'Sales'!BY24)=3,IF(N(SUM('Marketing'!BY28,'Sales'!BY24))=0,"",BV4*12/(SUM('Marketing'!BY28,'Sales'!BY24))),"") | BW22: =IF(N(SUM('Marketing'!BZ28,'Sales'!BZ24))=0,"",BW4*12/(SUM('Marketing'!BZ28,'Sales'!BZ24))) | BX22: =IF(N(SUM('Marketing'!CA28,'Sales'!CA24))=0,"",BX4*12/(SUM('Marketing'!CA28,'Sales'!CA24))) | BY22: =IF(COUNT(BY4,'Marketing'!CB28,'Sales'!CB24)=3,IF(N(SUM('Marketing'!CB28,'Sales'!CB24))=0,"",BY4*12/(SUM('Marketing'!CB28,'Sales'!CB24))),"") | BZ22: =IF(N(SUM('Marketing'!CC28,'Sales'!CC24))=0,"",BZ4*12/(SUM('Marketing'!CC28,'Sales'!CC24))) | CA22: =IF(N(SUM('Marketing'!CD28,'Sales'!CD24))=0,"",CA4*12/(SUM('Marketing'!CD28,'Sales'!CD24))) | CB22: =IF(COUNT(CB4,'Marketing'!CE28,'Sales'!CE24)=3,IF(N(SUM('Marketing'!CE28,'Sales'!CE24))=0,"",CB4*12/(SUM('Marketing'!CE28,'Sales'!CE24))),"") | CC22: =IF(N(SUM('Marketing'!CF28,'Sales'!CF24))=0,"",CC4*12/(SUM('Marketing'!CF28,'Sales'!CF24))) | CD22: =IF(N(SUM('Marketing'!CG28,'Sales'!CG24))=0,"",CD4*12/(SUM('Marketing'!CG28,'Sales'!CG24))) | CE22: =IF(COUNT(CE4,'Marketing'!CH28,'Sales'!CH24)=3,IF(N(SUM('Marketing'!CH28,'Sales'!CH24))=0,"",CE4*12/(SUM('Marketing'!CH28,'Sales'!CH24))),"") | CF22: =IF(N(SUM('Marketing'!CI28,'Sales'!CI24))=0,"",CF4*12/(SUM('Marketing'!CI28,'Sales'!CI24))) | CG22: =IF(N(SUM('Marketing'!CJ28,'Sales'!CJ24))=0,"",CG4*12/(SUM('Marketing'!CJ28,'Sales'!CJ24))) | CH22: =IF(COUNT(CH4,'Marketing'!CK28,'Sales'!CK24)=3,IF(N(SUM('Marketing'!CK28,'Sales'!CK24))=0,"",CH4*12/(SUM('Marketing'!CK28,'Sales'!CK24))),"") | CI22: =IF(N(SUM('Marketing'!CL28,'Sales'!CL24))=0,"",CI4*12/(SUM('Marketing'!CL28,'Sales'!CL24))) | CJ22: =IF(N(SUM('Marketing'!CM28,'Sales'!CM24))=0,"",CJ4*12/(SUM('Marketing'!CM28,'Sales'!CM24))) | CK22: =IF(COUNT(CK4,'Marketing'!CN28,'Sales'!CN24)=3,IF(N(SUM('Marketing'!CN28,'Sales'!CN24))=0,"",CK4*12/(SUM('Marketing'!CN28,'Sales'!CN24))),"") | CL22: =IF(N(SUM('Marketing'!CO28,'Sales'!CO24))=0,"",CL4*12/(SUM('Marketing'!CO28,'Sales'!CO24))) | CM22: =IF(N(SUM('Marketing'!CP28,'Sales'!CP24))=0,"",CM4*12/(SUM('Marketing'!CP28,'Sales'!CP24))) | CN22: =IF(COUNT(CN4,'Marketing'!CQ28,'Sales'!CQ24)=3,IF(N(SUM('Marketing'!CQ28,'Sales'!CQ24))=0,"",CN4*12/(SUM('Marketing'!CQ28,'Sales'!CQ24))),"") | CO22: =IF(N(SUM('Marketing'!CR28,'Sales'!CR24))=0,"",CO4*12/(SUM('Marketing'!CR28,'Sales'!CR24))) | CP22: =IF(N(SUM('Marketing'!CS28,'Sales'!CS24))=0,"",CP4*12/(SUM('Marketing'!CS28,'Sales'!CS24))) | CQ22: =IF(COUNT(CQ4,'Marketing'!CT28,'Sales'!CT24)=3,IF(N(SUM('Marketing'!CT28,'Sales'!CT24))=0,"",CQ4*12/(SUM('Marketing'!CT28,'Sales'!CT24))),"") | CR22: =IF(N(SUM('Marketing'!CU28,'Sales'!CU24))=0,"",CR4*12/(SUM('Marketing'!CU28,'Sales'!CU24))) | CS22: =IF(N(SUM('Marketing'!CV28,'Sales'!CV24))=0,"",CS4*12/(SUM('Marketing'!CV28,'Sales'!CV24))) | CT22: =IF(COUNT(CT4,'Marketing'!CW28,'Sales'!CW24)=3,IF(N(SUM('Marketing'!CW28,'Sales'!CW24))=0,"",CT4*12/(SUM('Marketing'!CW28,'Sales'!CW24))),"") | CU22: =IF(N(SUM('Marketing'!CX28,'Sales'!CX24))=0,"",CU4*12/(SUM('Marketing'!CX28,'Sales'!CX24))) | CV22: =IF(N(SUM('Marketing'!CY28,'Sales'!CY24))=0,"",CV4*12/(SUM('Marketing'!CY28,'Sales'!CY24))) | CW22: =IF(COUNT(CW4,'Marketing'!CZ28,'Sales'!CZ24)=3,IF(N(SUM('Marketing'!CZ28,'Sales'!CZ24))=0,"",CW4*12/(SUM('Marketing'!CZ28,'Sales'!CZ24))),"") | CX22: =IF(N(SUM('Marketing'!DA28,'Sales'!DA24))=0,"",CX4*12/(SUM('Marketing'!DA28,'Sales'!DA24))) | CY22: =IF(N(SUM('Marketing'!DB28,'Sales'!DB24))=0,"",CY4*12/(SUM('Marketing'!DB28,'Sales'!DB24))) | CZ22: =IF(COUNT(CZ4,'Marketing'!DC28,'Sales'!DC24)=3,IF(N(SUM('Marketing'!DC28,'Sales'!DC24))=0,"",CZ4*12/(SUM('Marketing'!DC28,'Sales'!DC24))),"") | DA22: =IF(N(SUM('Marketing'!DD28,'Sales'!DD24))=0,"",DA4*12/(SUM('Marketing'!DD28,'Sales'!DD24))) | DB22: =IF(N(SUM('Marketing'!DE28,'Sales'!DE24))=0,"",DB4*12/(SUM('Marketing'!DE28,'Sales'!DE24))) | DC22: =IF(COUNT(DC4,'Marketing'!DF28,'Sales'!DF24)=3,IF(N(SUM('Marketing'!DF28,'Sales'!DF24))=0,"",DC4*12/(SUM('Marketing'!DF28,'Sales'!DF24))),"") | DD22: =IF(N(SUM('Marketing'!DG28,'Sales'!DG24))=0,"",DD4*12/(SUM('Marketing'!DG28,'Sales'!DG24))) | DE22: =IF(N(SUM('Marketing'!DH28,'Sales'!DH24))=0,"",DE4*12/(SUM('Marketing'!DH28,'Sales'!DH24))) | DF22: =IF(COUNT(DF4,'Marketing'!DI28,'Sales'!DI24)=3,IF(N(SUM('Marketing'!DI28,'Sales'!DI24))=0,"",DF4*12/(SUM('Marketing'!DI28,'Sales'!DI24))),"") | DG22: =IF(N(SUM('Marketing'!DJ28,'Sales'!DJ24))=0,"",DG4*12/(SUM('Marketing'!DJ28,'Sales'!DJ24))) | DH22: =IF(N(SUM('Marketing'!DK28,'Sales'!DK24))=0,"",DH4*12/(SUM('Marketing'!DK28,'Sales'!DK24))) | DI22: =IF(COUNT(DI4,'Marketing'!DL28,'Sales'!DL24)=3,IF(N(SUM('Marketing'!DL28,'Sales'!DL24))=0,"",DI4*12/(SUM('Marketing'!DL28,'Sales'!DL24))),"") | DJ22: =IF(N(SUM('Marketing'!DM28,'Sales'!DM24))=0,"",DJ4*12/(SUM('Marketing'!DM28,'Sales'!DM24))) | DK22: =IF(N(SUM('Marketing'!DN28,'Sales'!DN24))=0,"",DK4*12/(SUM('Marketing'!DN28,'Sales'!DN24))) | DL22: =IF(COUNT(DL4,'Marketing'!DL28,'Sales'!DL24)=3,IF(N(SUM('Marketing'!DL28,'Sales'!DL24))=0,"",DL4*12/(SUM('Marketing'!DL28,'Sales'!DL24))),"") | DM22: =IF(N(SUM('Marketing'!DM28,'Sales'!DM24))=0,"",DM4*12/(SUM('Marketing'!DM28,'Sales'!DM24))) | DN22: =IF(N(SUM('Marketing'!DN28,'Sales'!DN24))=0,"",DN4*12/(SUM('Marketing'!DN28,'Sales'!DN24)))
A23: Rule of 40 | B23: =IF(OR(N(IF(AR3<>"",AR3,IF(AO3<>"",AO3,IF(AL3<>"",AL3,IF(AI3<>"",AI3,IF(AF3<>"",AF3,IF(AC3<>"",AC3,IF(Z3<>"",Z3,IF(W3<>"",W3,IF(T3<>"",T3,IF(Q3<>"",Q3,IF(N3<>"",N3,IF(K3<>"",K3,"")))))))))))))=0,N(B7)=0),"",B6/N(IF(AR3<>"",AR3,IF(AO3<>"",AO3,IF(AL3<>"",AL3,IF(AI3<>"",AI3,IF(AF3<>"",AF3,IF(AC3<>"",AC3,IF(Z3<>"",Z3,IF(W3<>"",W3,IF(T3<>"",T3,IF(Q3<>"",Q3,IF(N3<>"",N3,IF(K3<>"",K3,"")))))))))))))-1+B12/B7) | C23: =IF(OR(N(IF(AS3<>"",AS3,IF(AP3<>"",AP3,IF(AM3<>"",AM3,IF(AJ3<>"",AJ3,IF(AG3<>"",AG3,IF(AD3<>"",AD3,IF(AA3<>"",AA3,IF(X3<>"",X3,IF(U3<>"",U3,IF(R3<>"",R3,IF(O3<>"",O3,IF(L3<>"",L3,"")))))))))))))=0,N(C7)=0),"",C6/N(IF(AS3<>"",AS3,IF(AP3<>"",AP3,IF(AM3<>"",AM3,IF(AJ3<>"",AJ3,IF(AG3<>"",AG3,IF(AD3<>"",AD3,IF(AA3<>"",AA3,IF(X3<>"",X3,IF(U3<>"",U3,IF(R3<>"",R3,IF(O3<>"",O3,IF(L3<>"",L3,"")))))))))))))-1+C12/C7) | D23: =IF(OR(N(IF(AT3<>"",AT3,IF(AQ3<>"",AQ3,IF(AN3<>"",AN3,IF(AK3<>"",AK3,IF(AH3<>"",AH3,IF(AE3<>"",AE3,IF(AB3<>"",AB3,IF(Y3<>"",Y3,IF(V3<>"",V3,IF(S3<>"",S3,IF(P3<>"",P3,IF(M3<>"",M3,"")))))))))))))=0,N(D7)=0),"",D6/N(IF(AT3<>"",AT3,IF(AQ3<>"",AQ3,IF(AN3<>"",AN3,IF(AK3<>"",AK3,IF(AH3<>"",AH3,IF(AE3<>"",AE3,IF(AB3<>"",AB3,IF(Y3<>"",Y3,IF(V3<>"",V3,IF(S3<>"",S3,IF(P3<>"",P3,IF(M3<>"",M3,"")))))))))))))-1+D12/D7) | E23: =IF(OR(N(IF(CB3<>"",CB3,IF(BY3<>"",BY3,IF(BV3<>"",BV3,IF(BS3<>"",BS3,IF(BP3<>"",BP3,IF(BM3<>"",BM3,IF(BJ3<>"",BJ3,IF(BG3<>"",BG3,IF(BD3<>"",BD3,IF(BA3<>"",BA3,IF(AX3<>"",AX3,IF(AU3<>"",AU3,"")))))))))))))=0,N(E7)=0),"",E6/N(IF(CB3<>"",CB3,IF(BY3<>"",BY3,IF(BV3<>"",BV3,IF(BS3<>"",BS3,IF(BP3<>"",BP3,IF(BM3<>"",BM3,IF(BJ3<>"",BJ3,IF(BG3<>"",BG3,IF(BD3<>"",BD3,IF(BA3<>"",BA3,IF(AX3<>"",AX3,IF(AU3<>"",AU3,"")))))))))))))-1+E12/E7) | F23: =IF(OR(N(IF(CC3<>"",CC3,IF(BZ3<>"",BZ3,IF(BW3<>"",BW3,IF(BT3<>"",BT3,IF(BQ3<>"",BQ3,IF(BN3<>"",BN3,IF(BK3<>"",BK3,IF(BH3<>"",BH3,IF(BE3<>"",BE3,IF(BB3<>"",BB3,IF(AY3<>"",AY3,IF(AV3<>"",AV3,"")))))))))))))=0,N(F7)=0),"",F6/N(IF(CC3<>"",CC3,IF(BZ3<>"",BZ3,IF(BW3<>"",BW3,IF(BT3<>"",BT3,IF(BQ3<>"",BQ3,IF(BN3<>"",BN3,IF(BK3<>"",BK3,IF(BH3<>"",BH3,IF(BE3<>"",BE3,IF(BB3<>"",BB3,IF(AY3<>"",AY3,IF(AV3<>"",AV3,"")))))))))))))-1+F12/F7) | G23: =IF(OR(N(IF(CD3<>"",CD3,IF(CA3<>"",CA3,IF(BX3<>"",BX3,IF(BU3<>"",BU3,IF(BR3<>"",BR3,IF(BO3<>"",BO3,IF(BL3<>"",BL3,IF(BI3<>"",BI3,IF(BF3<>"",BF3,IF(BC3<>"",BC3,IF(AZ3<>"",AZ3,IF(AW3<>"",AW3,"")))))))))))))=0,N(G7)=0),"",G6/N(IF(CD3<>"",CD3,IF(CA3<>"",CA3,IF(BX3<>"",BX3,IF(BU3<>"",BU3,IF(BR3<>"",BR3,IF(BO3<>"",BO3,IF(BL3<>"",BL3,IF(BI3<>"",BI3,IF(BF3<>"",BF3,IF(BC3<>"",BC3,IF(AZ3<>"",AZ3,IF(AW3<>"",AW3,"")))))))))))))-1+G12/G7) | H23: =IF(OR(N(IF(DL3<>"",DL3,IF(DI3<>"",DI3,IF(DF3<>"",DF3,IF(DC3<>"",DC3,IF(CZ3<>"",CZ3,IF(CW3<>"",CW3,IF(CT3<>"",CT3,IF(CQ3<>"",CQ3,IF(CN3<>"",CN3,IF(CK3<>"",CK3,IF(CH3<>"",CH3,IF(CE3<>"",CE3,"")))))))))))))=0,N(H7)=0),"",H6/N(IF(DL3<>"",DL3,IF(DI3<>"",DI3,IF(DF3<>"",DF3,IF(DC3<>"",DC3,IF(CZ3<>"",CZ3,IF(CW3<>"",CW3,IF(CT3<>"",CT3,IF(CQ3<>"",CQ3,IF(CN3<>"",CN3,IF(CK3<>"",CK3,IF(CH3<>"",CH3,IF(CE3<>"",CE3,"")))))))))))))-1+H12/H7) | I23: =IF(OR(N(IF(DM3<>"",DM3,IF(DJ3<>"",DJ3,IF(DG3<>"",DG3,IF(DD3<>"",DD3,IF(DA3<>"",DA3,IF(CX3<>"",CX3,IF(CU3<>"",CU3,IF(CR3<>"",CR3,IF(CO3<>"",CO3,IF(CL3<>"",CL3,IF(CI3<>"",CI3,IF(CF3<>"",CF3,"")))))))))))))=0,N(I7)=0),"",I6/N(IF(DM3<>"",DM3,IF(DJ3<>"",DJ3,IF(DG3<>"",DG3,IF(DD3<>"",DD3,IF(DA3<>"",DA3,IF(CX3<>"",CX3,IF(CU3<>"",CU3,IF(CR3<>"",CR3,IF(CO3<>"",CO3,IF(CL3<>"",CL3,IF(CI3<>"",CI3,IF(CF3<>"",CF3,"")))))))))))))-1+I12/I7) | J23: =IF(OR(N(IF(DN3<>"",DN3,IF(DK3<>"",DK3,IF(DH3<>"",DH3,IF(DE3<>"",DE3,IF(DB3<>"",DB3,IF(CY3<>"",CY3,IF(CV3<>"",CV3,IF(CS3<>"",CS3,IF(CP3<>"",CP3,IF(CM3<>"",CM3,IF(CJ3<>"",CJ3,IF(CG3<>"",CG3,"")))))))))))))=0,N(J7)=0),"",J6/N(IF(DN3<>"",DN3,IF(DK3<>"",DK3,IF(DH3<>"",DH3,IF(DE3<>"",DE3,IF(DB3<>"",DB3,IF(CY3<>"",CY3,IF(CV3<>"",CV3,IF(CS3<>"",CS3,IF(CP3<>"",CP3,IF(CM3<>"",CM3,IF(CJ3<>"",CJ3,IF(CG3<>"",CG3,"")))))))))))))-1+J12/J7) | K23: =IF(OR(N(AR3)=0,N(K6)=0,SUM(AR7,AO7,AL7,AI7,AF7,AC7,Z7,W7,T7,Q7,N7,K7)=0),"",(K6/AR3)^(12/12)-1+SUM(AR12,AO12,AL12,AI12,AF12,AC12,Z12,W12,T12,Q12,N12,K12)/SUM(AR7,AO7,AL7,AI7,AF7,AC7,Z7,W7,T7,Q7,N7,K7)) | L23: =IF(OR(N(AS3)=0,N(L6)=0,SUM(AS7,AP7,AM7,AJ7,AG7,AD7,AA7,X7,U7,R7,O7,L7)=0),"",(L6/AS3)^(12/12)-1+SUM(AS12,AP12,AM12,AJ12,AG12,AD12,AA12,X12,U12,R12,O12,L12)/SUM(AS7,AP7,AM7,AJ7,AG7,AD7,AA7,X7,U7,R7,O7,L7)) | M23: =IF(OR(N(AT3)=0,N(M6)=0,SUM(AT7,AQ7,AN7,AK7,AH7,AE7,AB7,Y7,V7,S7,P7,M7)=0),"",(M6/AT3)^(12/12)-1+SUM(AT12,AQ12,AN12,AK12,AH12,AE12,AB12,Y12,V12,S12,P12,M12)/SUM(AT7,AQ7,AN7,AK7,AH7,AE7,AB7,Y7,V7,S7,P7,M7)) | N23: =IF(OR(N(AU3)=0,N(N6)=0,SUM(AU7,AR7,AO7,AL7,AI7,AF7,AC7,Z7,W7,T7,Q7,N7)=0),"",(N6/AU3)^(12/12)-1+SUM(AU12,AR12,AO12,AL12,AI12,AF12,AC12,Z12,W12,T12,Q12,N12)/SUM(AU7,AR7,AO7,AL7,AI7,AF7,AC7,Z7,W7,T7,Q7,N7)) | O23: =IF(OR(N(AV3)=0,N(O6)=0,SUM(AV7,AS7,AP7,AM7,AJ7,AG7,AD7,AA7,X7,U7,R7,O7)=0),"",(O6/AV3)^(12/12)-1+SUM(AV12,AS12,AP12,AM12,AJ12,AG12,AD12,AA12,X12,U12,R12,O12)/SUM(AV7,AS7,AP7,AM7,AJ7,AG7,AD7,AA7,X7,U7,R7,O7)) | P23: =IF(OR(N(AW3)=0,N(P6)=0,SUM(AW7,AT7,AQ7,AN7,AK7,AH7,AE7,AB7,Y7,V7,S7,P7)=0),"",(P6/AW3)^(12/12)-1+SUM(AW12,AT12,AQ12,AN12,AK12,AH12,AE12,AB12,Y12,V12,S12,P12)/SUM(AW7,AT7,AQ7,AN7,AK7,AH7,AE7,AB7,Y7,V7,S7,P7)) | Q23: =IF(OR(N(AX3)=0,N(Q6)=0,SUM(AX7,AU7,AR7,AO7,AL7,AI7,AF7,AC7,Z7,W7,T7,Q7)=0),"",(Q6/AX3)^(12/12)-1+SUM(AX12,AU12,AR12,AO12,AL12,AI12,AF12,AC12,Z12,W12,T12,Q12)/SUM(AX7,AU7,AR7,AO7,AL7,AI7,AF7,AC7,Z7,W7,T7,Q7)) | R23: =IF(OR(N(AY3)=0,N(R6)=0,SUM(AY7,AV7,AS7,AP7,AM7,AJ7,AG7,AD7,AA7,X7,U7,R7)=0),"",(R6/AY3)^(12/12)-1+SUM(AY12,AV12,AS12,AP12,AM12,AJ12,AG12,AD12,AA12,X12,U12,R12)/SUM(AY7,AV7,AS7,AP7,AM7,AJ7,AG7,AD7,AA7,X7,U7,R7)) | ... CG23: =IF(OR(N(DN3)=0,N(CG6)=0,SUM(DN7,DK7,DH7,DE7,DB7,CY7,CV7,CS7,CP7,CM7,CJ7,CG7)=0),"",(CG6/DN3)^(12/12)-1+SUM(DN12,DK12,DH12,DE12,DB12,CY12,CV12,CS12,CP12,CM12,CJ12,CG12)/SUM(DN7,DK7,DH7,DE7,DB7,CY7,CV7,CS7,CP7,CM7,CJ7,CG7)) | CH23: =IF(OR(N(DL3)=0,N(CH6)=0,SUM(DL7,DI7,DF7,DC7,CZ7,CW7,CT7,CQ7,CN7,CK7,CH7)=0),"",(CH6/DL3)^(12/11)-1+SUM(DL12,DI12,DF12,DC12,CZ12,CW12,CT12,CQ12,CN12,CK12,CH12)/SUM(DL7,DI7,DF7,DC7,CZ7,CW7,CT7,CQ7,CN7,CK7,CH7)) | CI23: =IF(OR(N(DM3)=0,N(CI6)=0,SUM(DM7,DJ7,DG7,DD7,DA7,CX7,CU7,CR7,CO7,CL7,CI7)=0),"",(CI6/DM3)^(12/11)-1+SUM(DM12,DJ12,DG12,DD12,DA12,CX12,CU12,CR12,CO12,CL12,CI12)/SUM(DM7,DJ7,DG7,DD7,DA7,CX7,CU7,CR7,CO7,CL7,CI7)) | CJ23: =IF(OR(N(DN3)=0,N(CJ6)=0,SUM(DN7,DK7,DH7,DE7,DB7,CY7,CV7,CS7,CP7,CM7,CJ7)=0),"",(CJ6/DN3)^(12/11)-1+SUM(DN12,DK12,DH12,DE12,DB12,CY12,CV12,CS12,CP12,CM12,CJ12)/SUM(DN7,DK7,DH7,DE7,DB7,CY7,CV7,CS7,CP7,CM7,CJ7)) | CK23: =IF(OR(N(DL3)=0,N(CK6)=0,SUM(DL7,DI7,DF7,DC7,CZ7,CW7,CT7,CQ7,CN7,CK7)=0),"",(CK6/DL3)^(12/10)-1+SUM(DL12,DI12,DF12,DC12,CZ12,CW12,CT12,CQ12,CN12,CK12)/SUM(DL7,DI7,DF7,DC7,CZ7,CW7,CT7,CQ7,CN7,CK7)) | CL23: =IF(OR(N(DM3)=0,N(CL6)=0,SUM(DM7,DJ7,DG7,DD7,DA7,CX7,CU7,CR7,CO7,CL7)=0),"",(CL6/DM3)^(12/10)-1+SUM(DM12,DJ12,DG12,DD12,DA12,CX12,CU12,CR12,CO12,CL12)/SUM(DM7,DJ7,DG7,DD7,DA7,CX7,CU7,CR7,CO7,CL7)) | CM23: =IF(OR(N(DN3)=0,N(CM6)=0,SUM(DN7,DK7,DH7,DE7,DB7,CY7,CV7,CS7,CP7,CM7)=0),"",(CM6/DN3)^(12/10)-1+SUM(DN12,DK12,DH12,DE12,DB12,CY12,CV12,CS12,CP12,CM12)/SUM(DN7,DK7,DH7,DE7,DB7,CY7,CV7,CS7,CP7,CM7)) | CN23: =IF(OR(N(DL3)=0,N(CN6)=0,SUM(DL7,DI7,DF7,DC7,CZ7,CW7,CT7,CQ7,CN7)=0),"",(CN6/DL3)^(12/9)-1+SUM(DL12,DI12,DF12,DC12,CZ12,CW12,CT12,CQ12,CN12)/SUM(DL7,DI7,DF7,DC7,CZ7,CW7,CT7,CQ7,CN7)) | CO23: =IF(OR(N(DM3)=0,N(CO6)=0,SUM(DM7,DJ7,DG7,DD7,DA7,CX7,CU7,CR7,CO7)=0),"",(CO6/DM3)^(12/9)-1+SUM(DM12,DJ12,DG12,DD12,DA12,CX12,CU12,CR12,CO12)/SUM(DM7,DJ7,DG7,DD7,DA7,CX7,CU7,CR7,CO7)) | CP23: =IF(OR(N(DN3)=0,N(CP6)=0,SUM(DN7,DK7,DH7,DE7,DB7,CY7,CV7,CS7,CP7)=0),"",(CP6/DN3)^(12/9)-1+SUM(DN12,DK12,DH12,DE12,DB12,CY12,CV12,CS12,CP12)/SUM(DN7,DK7,DH7,DE7,DB7,CY7,CV7,CS7,CP7)) | CQ23: =IF(OR(N(DL3)=0,N(CQ6)=0,SUM(DL7,DI7,DF7,DC7,CZ7,CW7,CT7,CQ7)=0),"",(CQ6/DL3)^(12/8)-1+SUM(DL12,DI12,DF12,DC12,CZ12,CW12,CT12,CQ12)/SUM(DL7,DI7,DF7,DC7,CZ7,CW7,CT7,CQ7)) | CR23: =IF(OR(N(DM3)=0,N(CR6)=0,SUM(DM7,DJ7,DG7,DD7,DA7,CX7,CU7,CR7)=0),"",(CR6/DM3)^(12/8)-1+SUM(DM12,DJ12,DG12,DD12,DA12,CX12,CU12,CR12)/SUM(DM7,DJ7,DG7,DD7,DA7,CX7,CU7,CR7)) | CS23: =IF(OR(N(DN3)=0,N(CS6)=0,SUM(DN7,DK7,DH7,DE7,DB7,CY7,CV7,CS7)=0),"",(CS6/DN3)^(12/8)-1+SUM(DN12,DK12,DH12,DE12,DB12,CY12,CV12,CS12)/SUM(DN7,DK7,DH7,DE7,DB7,CY7,CV7,CS7)) | CT23: =IF(OR(N(DL3)=0,N(CT6)=0,SUM(DL7,DI7,DF7,DC7,CZ7,CW7,CT7)=0),"",(CT6/DL3)^(12/7)-1+SUM(DL12,DI12,DF12,DC12,CZ12,CW12,CT12)/SUM(DL7,DI7,DF7,DC7,CZ7,CW7,CT7)) | CU23: =IF(OR(N(DM3)=0,N(CU6)=0,SUM(DM7,DJ7,DG7,DD7,DA7,CX7,CU7)=0),"",(CU6/DM3)^(12/7)-1+SUM(DM12,DJ12,DG12,DD12,DA12,CX12,CU12)/SUM(DM7,DJ7,DG7,DD7,DA7,CX7,CU7)) | CV23: =IF(OR(N(DN3)=0,N(CV6)=0,SUM(DN7,DK7,DH7,DE7,DB7,CY7,CV7)=0),"",(CV6/DN3)^(12/7)-1+SUM(DN12,DK12,DH12,DE12,DB12,CY12,CV12)/SUM(DN7,DK7,DH7,DE7,DB7,CY7,CV7)) | CW23: =IF(OR(N(DL3)=0,N(CW6)=0,SUM(DL7,DI7,DF7,DC7,CZ7,CW7)=0),"",(CW6/DL3)^(12/6)-1+SUM(DL12,DI12,DF12,DC12,CZ12,CW12)/SUM(DL7,DI7,DF7,DC7,CZ7,CW7)) | CX23: =IF(OR(N(DM3)=0,N(CX6)=0,SUM(DM7,DJ7,DG7,DD7,DA7,CX7)=0),"",(CX6/DM3)^(12/6)-1+SUM(DM12,DJ12,DG12,DD12,DA12,CX12)/SUM(DM7,DJ7,DG7,DD7,DA7,CX7)) | CY23: =IF(OR(N(DN3)=0,N(CY6)=0,SUM(DN7,DK7,DH7,DE7,DB7,CY7)=0),"",(CY6/DN3)^(12/6)-1+SUM(DN12,DK12,DH12,DE12,DB12,CY12)/SUM(DN7,DK7,DH7,DE7,DB7,CY7)) | CZ23: =IF(OR(N(DL3)=0,N(CZ6)=0,SUM(DL7,DI7,DF7,DC7,CZ7)=0),"",(CZ6/DL3)^(12/5)-1+SUM(DL12,DI12,DF12,DC12,CZ12)/SUM(DL7,DI7,DF7,DC7,CZ7)) | DA23: =IF(OR(N(DM3)=0,N(DA6)=0,SUM(DM7,DJ7,DG7,DD7,DA7)=0),"",(DA6/DM3)^(12/5)-1+SUM(DM12,DJ12,DG12,DD12,DA12)/SUM(DM7,DJ7,DG7,DD7,DA7)) | DB23: =IF(OR(N(DN3)=0,N(DB6)=0,SUM(DN7,DK7,DH7,DE7,DB7)=0),"",(DB6/DN3)^(12/5)-1+SUM(DN12,DK12,DH12,DE12,DB12)/SUM(DN7,DK7,DH7,DE7,DB7)) | DC23: =IF(OR(N(DL3)=0,N(DC6)=0,SUM(DL7,DI7,DF7,DC7)=0),"",(DC6/DL3)^(12/4)-1+SUM(DL12,DI12,DF12,DC12)/SUM(DL7,DI7,DF7,DC7)) | DD23: =IF(OR(N(DM3)=0,N(DD6)=0,SUM(DM7,DJ7,DG7,DD7)=0),"",(DD6/DM3)^(12/4)-1+SUM(DM12,DJ12,DG12,DD12)/SUM(DM7,DJ7,DG7,DD7)) | DE23: =IF(OR(N(DN3)=0,N(DE6)=0,SUM(DN7,DK7,DH7,DE7)=0),"",(DE6/DN3)^(12/4)-1+SUM(DN12,DK12,DH12,DE12)/SUM(DN7,DK7,DH7,DE7)) | DF23: =IF(OR(N(DL3)=0,N(DF6)=0,SUM(DL7,DI7,DF7)=0),"",(DF6/DL3)^(12/3)-1+SUM(DL12,DI12,DF12)/SUM(DL7,DI7,DF7)) | DG23: =IF(OR(N(DM3)=0,N(DG6)=0,SUM(DM7,DJ7,DG7)=0),"",(DG6/DM3)^(12/3)-1+SUM(DM12,DJ12,DG12)/SUM(DM7,DJ7,DG7)) | DH23: =IF(OR(N(DN3)=0,N(DH6)=0,SUM(DN7,DK7,DH7)=0),"",(DH6/DN3)^(12/3)-1+SUM(DN12,DK12,DH12)/SUM(DN7,DK7,DH7)) | DI23: =IF(OR(N(DL3)=0,N(DI6)=0,SUM(DL7,DI7)=0),"",(DI6/DL3)^(12/2)-1+SUM(DL12,DI12)/SUM(DL7,DI7)) | DJ23: =IF(OR(N(DM3)=0,N(DJ6)=0,SUM(DM7,DJ7)=0),"",(DJ6/DM3)^(12/2)-1+SUM(DM12,DJ12)/SUM(DM7,DJ7)) | DK23: =IF(OR(N(DN3)=0,N(DK6)=0,SUM(DN7,DK7)=0),"",(DK6/DN3)^(12/2)-1+SUM(DN12,DK12)/SUM(DN7,DK7)) | DL23: =IF(OR(N(DL3)=0,N(DL6)=0,SUM(DL7)=0),"",(DL6/DL3)^(12/1)-1+SUM(DL12)/SUM(DL7)) | DM23: =IF(OR(N(DM3)=0,N(DM6)=0,SUM(DM7)=0),"",(DM6/DM3)^(12/1)-1+SUM(DM12)/SUM(DM7)) | DN23: =IF(OR(N(DN3)=0,N(DN6)=0,SUM(DN7)=0),"",(DN6/DN3)^(12/1)-1+SUM(DN12)/SUM(DN7))

Sheet Marketing
B1: ="FY"&YEAR(K$1) | E1: ="FY"&YEAR(AU$1) | H1: ="FY"&YEAR(CE$1) | K1: =EOMONTH(N$1,1) | N1: =EOMONTH(Q$1,1) | Q1: =EOMONTH(T$1,1) | T1: =EOMONTH(W$1,1) | W1: =EOMONTH(Z$1,1) | Z1: =EOMONTH(AC$1,1) | AC1: =EOMONTH(AF$1,1) | AF1: =EOMONTH(AI$1,1) | AI1: =EOMONTH(AL$1,1) | AL1: =EOMONTH(AO$1,1) | AO1: =EOMONTH(AR$1,1) | AR1: =EOMONTH(AU$1,1) | AU1: =EOMONTH(AX$1,1) | AX1: =EOMONTH(BA$1,1) | BA1: =EOMONTH(BD$1,1) | BD1: =EOMONTH(BG$1,1) | BG1: =EOMONTH(BJ$1,1) | BJ1: =EOMONTH(BM$1,1) | BM1: =EOMONTH(BP$1,1) | BP1: =EOMONTH(BS$1,1) | BS1: =EOMONTH(BV$1,1) | BV1: =EOMONTH(BY$1,1) | BY1: =EOMONTH(CB$1,1) | CB1: =EOMONTH(CE$1,1) | CE1: =EOMONTH(CH$1,1) | CH1: =EOMONTH(CK$1,1) | CK1: =EOMONTH(CN$1,1) | CN1: =EOMONTH(CQ$1,1) | CQ1: =EOMONTH(CT$1,1) | CT1: =EOMONTH(CW$1,1) | CW1: =EOMONTH(CZ$1,1) | CZ1: =EOMONTH(DC$1,1) | DC1: =EOMONTH(DF$1,1) | DF1: =EOMONTH(DI$1,1) | DI1: =EOMONTH(DL$1,1) | DL1: =Finance!$B$61
B2: Actual | C2: Rolling | D2: Approved | E2: Actual | F2: Rolling | G2: Approved | H2: Actual | I2: Rolling | J2: Approved | K2: Actual | L2: Rolling | M2: Approved | N2: Actual | O2: Rolling | P2: Approved | Q2: Actual | R2: Rolling | S2: Approved | T2: Actual | U2: Rolling | V2: Approved | W2: Actual | X2: Rolling | Y2: Approved | Z2: Actual | AA2: Rolling | AB2: Approved | AC2: Actual | AD2: Rolling | AE2: Approved | AF2: Actual | AG2: Rolling | AH2: Approved | AI2: Actual | AJ2: Rolling | AK2: Approved | AL2: Actual | AM2: Rolling | AN2: Approved | AO2: Actual | AP2: Rolling | AQ2: Approved | AR2: Actual | AS2: Rolling | AT2: Approved | AU2: Actual | AV2: Rolling | AW2: Approved | AX2: Actual | AY2: Rolling | AZ2: Approved | BA2: Actual | BB2: Rolling | BC2: Approved | BD2: Actual | BE2: Rolling | BF2: Approved | BG2: Actual | BH2: Rolling | BI2: Approved | BJ2: Actual | BK2: Rolling | BL2: Approved | BM2: Actual | BN2: Rolling | BO2: Approved | BP2: Actual | BQ2: Rolling | BR2: Approved | BS2: Actual | BT2: Rolling | BU2: Approved | BV2: Actual | BW2: Rolling | BX2: Approved | BY2: Actual | BZ2: Rolling | CA2: Approved | CB2: Actual | CC2: Rolling | CD2: Approved | CE2: Actual | CF2: Rolling | CG2: Approved | CH2: Actual | CI2: Rolling | CJ2: Approved | CK2: Actual | CL2: Rolling | CM2: Approved | CN2: Actual | CO2: Rolling | CP2: Approved | CQ2: Actual | CR2: Rolling | CS2: Approved | CT2: Actual | CU2: Rolling | CV2: Approved | CW2: Actual | CX2: Rolling | CY2: Approved | CZ2: Actual | DA2: Rolling | DB2: Approved | DC2: Actual | DD2: Rolling | DE2: Approved | DF2: Actual | DG2: Rolling | DH2: Approved | DI2: Actual | DJ2: Rolling | DK2: Approved | DL2: Actual | DM2: Rolling | DN2: Approved
A3: Reach | B3: =IF(COUNT(AR3,AO3,AL3,AI3,AF3,AC3,Z3,W3,T3,Q3,N3,K3)=0,"",SUM(AR3,AO3,AL3,AI3,AF3,AC3,Z3,W3,T3,Q3,N3,K3)) | C3: =IF(COUNT(AS3,AP3,AM3,AJ3,AG3,AD3,AA3,X3,U3,R3,O3,L3)=0,"",SUM(AS3,AP3,AM3,AJ3,AG3,AD3,AA3,X3,U3,R3,O3,L3)) | D3: =IF(COUNT(AT3,AQ3,AN3,AK3,AH3,AE3,AB3,Y3,V3,S3,P3,M3)=0,"",SUM(AT3,AQ3,AN3,AK3,AH3,AE3,AB3,Y3,V3,S3,P3,M3)) | E3: =IF(COUNT(CB3,BY3,BV3,BS3,BP3,BM3,BJ3,BG3,BD3,BA3,AX3,AU3)=0,"",SUM(CB3,BY3,BV3,BS3,BP3,BM3,BJ3,BG3,BD3,BA3,AX3,AU3)) | F3: =IF(COUNT(CC3,BZ3,BW3,BT3,BQ3,BN3,BK3,BH3,BE3,BB3,AY3,AV3)=0,"",SUM(CC3,BZ3,BW3,BT3,BQ3,BN3,BK3,BH3,BE3,BB3,AY3,AV3)) | G3: =IF(COUNT(CD3,CA3,BX3,BU3,BR3,BO3,BL3,BI3,BF3,BC3,AZ3,AW3)=0,"",SUM(CD3,CA3,BX3,BU3,BR3,BO3,BL3,BI3,BF3,BC3,AZ3,AW3)) | H3: =IF(COUNT(DL3,DI3,DF3,DC3,CZ3,CW3,CT3,CQ3,CN3,CK3,CH3,CE3)=0,"",SUM(DL3,DI3,DF3,DC3,CZ3,CW3,CT3,CQ3,CN3,CK3,CH3,CE3)) | I3: =IF(COUNT(DM3,DJ3,DG3,DD3,DA3,CX3,CU3,CR3,CO3,CL3,CI3,CF3)=0,"",SUM(DM3,DJ3,DG3,DD3,DA3,CX3,CU3,CR3,CO3,CL3,CI3,CF3)) | J3: =IF(COUNT(DN3,DK3,DH3,DE3,DB3,CY3,CV3,CS3,CP3,CM3,CJ3,CG3)=0,"",SUM(DN3,DK3,DH3,DE3,DB3,CY3,CV3,CS3,CP3,CM3,CJ3,CG3)) | L3: 9900 | M3: 9900 | O3: 9900 | P3: 9900 | R3: 9900 | S3: 9900 | U3: 9900 | V3: 9900 | X3: 9900 | Y3: 9900 | AA3: 9900 | AB3: 9900 | AD3: 9900 | AE3: 9900 | AG3: 9900 | AH3: 9900 | AJ3: 9900 | AK3: 9900 | AM3: 9900 | AN3: 9900 | AP3: 9900 | AQ3: 9900 | AS3: 9900 | AT3: 9900 | AV3: 7200 | AW3: 7200 | AY3: 7200 | AZ3: 7200 | BB3: 7200 | BC3: 7200 | BE3: 7200 | BF3: 7200 | BH3: 7200 | BI3: 7200 | BK3: 7200 | BL3: 7200 | BN3: 7200 | BO3: 7200 | BQ3: 7200 | BR3: 7200 | BT3: 7200 | BU3: 7200 | BW3: 7200 | BX3: 7200 | BZ3: 7200 | CA3: 7200 | CC3: 7200 | CD3: 7200 | CF3: 5000 | CG3: 5000 | CI3: 5000 | CJ3: 5000 | CL3: 5000 | CM3: 5000 | CO3: 5000 | CP3: 5000 | CR3: 5000 | CS3: 5000 | CU3: 5000 | CV3: 5000 | CX3: 5000 | CY3: 5000 | DA3: 5000 | DB3: 5000 | DD3: 5000 | DE3: 5000 | DG3: 5000 | DH3: 5000 | DI3: 5000 | DJ3: =DI3 | DK3: 5000 | DL3: 5100 | DM3: =DL3 | DN3: 5000
A4: Reach to MQL Rate | B4: =IF(SUM(AR3,AO3,AL3,AI3,AF3,AC3,Z3,W3,T3,Q3,N3,K3)=0,"",SUM(AR5,AO5,AL5,AI5,AF5,AC5,Z5,W5,T5,Q5,N5,K5)/SUM(AR3,AO3,AL3,AI3,AF3,AC3,Z3,W3,T3,Q3,N3,K3)) | C4: =IF(SUM(AS3,AP3,AM3,AJ3,AG3,AD3,AA3,X3,U3,R3,O3,L3)=0,"",SUM(AS5,AP5,AM5,AJ5,AG5,AD5,AA5,X5,U5,R5,O5,L5)/SUM(AS3,AP3,AM3,AJ3,AG3,AD3,AA3,X3,U3,R3,O3,L3)) | D4: =IF(SUM(AT3,AQ3,AN3,AK3,AH3,AE3,AB3,Y3,V3,S3,P3,M3)=0,"",SUM(AT5,AQ5,AN5,AK5,AH5,AE5,AB5,Y5,V5,S5,P5,M5)/SUM(AT3,AQ3,AN3,AK3,AH3,AE3,AB3,Y3,V3,S3,P3,M3)) | E4: =IF(SUM(CB3,BY3,BV3,BS3,BP3,BM3,BJ3,BG3,BD3,BA3,AX3,AU3)=0,"",SUM(CB5,BY5,BV5,BS5,BP5,BM5,BJ5,BG5,BD5,BA5,AX5,AU5)/SUM(CB3,BY3,BV3,BS3,BP3,BM3,BJ3,BG3,BD3,BA3,AX3,AU3)) | F4: =IF(SUM(CC3,BZ3,BW3,BT3,BQ3,BN3,BK3,BH3,BE3,BB3,AY3,AV3)=0,"",SUM(CC5,BZ5,BW5,BT5,BQ5,BN5,BK5,BH5,BE5,BB5,AY5,AV5)/SUM(CC3,BZ3,BW3,BT3,BQ3,BN3,BK3,BH3,BE3,BB3,AY3,AV3)) | G4: =IF(SUM(CD3,CA3,BX3,BU3,BR3,BO3,BL3,BI3,BF3,BC3,AZ3,AW3)=0,"",SUM(CD5,CA5,BX5,BU5,BR5,BO5,BL5,BI5,BF5,BC5,AZ5,AW5)/SUM(CD3,CA3,BX3,BU3,BR3,BO3,BL3,BI3,BF3,BC3,AZ3,AW3)) | H4: =IF(SUM(DL3,DI3,DF3,DC3,CZ3,CW3,CT3,CQ3,CN3,CK3,CH3,CE3)=0,"",SUM(DL5,DI5,DF5,DC5,CZ5,CW5,CT5,CQ5,CN5,CK5,CH5,CE5)/SUM(DL3,DI3,DF3,DC3,CZ3,CW3,CT3,CQ3,CN3,CK3,CH3,CE3)) | I4: =IF(SUM(DM3,DJ3,DG3,DD3,DA3,CX3,CU3,CR3,CO3,CL3,CI3,CF3)=0,"",SUM(DM5,DJ5,DG5,DD5,DA5,CX5,CU5,CR5,CO5,CL5,CI5,CF5)/SUM(DM3,DJ3,DG3,DD3,DA3,CX3,CU3,CR3,CO3,CL3,CI3,CF3)) | J4: =IF(SUM(DN3,DK3,DH3,DE3,DB3,CY3,CV3,CS3,CP3,CM3,CJ3,CG3)=0,"",SUM(DN5,DK5,DH5,DE5,DB5,CY5,CV5,CS5,CP5,CM5,CJ5,CG5)/SUM(DN3,DK3,DH3,DE3,DB3,CY3,CV3,CS3,CP3,CM3,CJ3,CG3)) | K4: =IF(COUNT(K3,K5)=2,IF(K3=0,"",K5/K3),"") | L4: 0.024 | M4: 0.024 | N4: =IF(COUNT(N3,N5)=2,IF(N3=0,"",N5/N3),"") | O4: 0.024 | P4: 0.024 | Q4: =IF(COUNT(Q3,Q5)=2,IF(Q3=0,"",Q5/Q3),"") | R4: 0.024 | S4: 0.024 | T4: =IF(COUNT(T3,T5)=2,IF(T3=0,"",T5/T3),"") | U4: 0.024 | V4: 0.024 | W4: =IF(COUNT(W3,W5)=2,IF(W3=0,"",W5/W3),"") | X4: 0.024 | Y4: 0.024 | Z4: =IF(COUNT(Z3,Z5)=2,IF(Z3=0,"",Z5/Z3),"") | AA4: 0.024 | AB4: 0.024 | AC4: =IF(COUNT(AC3,AC5)=2,IF(AC3=0,"",AC5/AC3),"") | AD4: 0.024 | AE4: 0.024 | AF4: =IF(COUNT(AF3,AF5)=2,IF(AF3=0,"",AF5/AF3),"") | AG4: 0.024 | AH4: 0.024 | AI4: =IF(COUNT(AI3,AI5)=2,IF(AI3=0,"",AI5/AI3),"") | AJ4: 0.024 | AK4: 0.024 | AL4: =IF(COUNT(AL3,AL5)=2,IF(AL3=0,"",AL5/AL3),"") | AM4: 0.024 | AN4: 0.024 | AO4: =IF(COUNT(AO3,AO5)=2,IF(AO3=0,"",AO5/AO3),"") | AP4: 0.024 | AQ4: 0.024 | AR4: =IF(COUNT(AR3,AR5)=2,IF(AR3=0,"",AR5/AR3),"") | AS4: 0.024 | AT4: 0.024 | AU4: =IF(COUNT(AU3,AU5)=2,IF(AU3=0,"",AU5/AU3),"") | AV4: 0.024 | AW4: 0.024 | AX4: =IF(COUNT(AX3,AX5)=2,IF(AX3=0,"",AX5/AX3),"") | AY4: 0.024 | AZ4: 0.024 | BA4: =IF(COUNT(BA3,BA5)=2,IF(BA3=0,"",BA5/BA3),"") | BB4: 0.024 | BC4: 0.024 | BD4: =IF(COUNT(BD3,BD5)=2,IF(BD3=0,"",BD5/BD3),"") | BE4: 0.024 | BF4: 0.024 | BG4: =IF(COUNT(BG3,BG5)=2,IF(BG3=0,"",BG5/BG3),"") | BH4: 0.024 | BI4: 0.024 | BJ4: =IF(COUNT(BJ3,BJ5)=2,IF(BJ3=0,"",BJ5/BJ3),"") | BK4: 0.024 | BL4: 0.024 | BM4: =IF(COUNT(BM3,BM5)=2,IF(BM3=0,"",BM5/BM3),"") | BN4: 0.024 | BO4: 0.024 | BP4: =IF(COUNT(BP3,BP5)=2,IF(BP3=0,"",BP5/BP3),"") | BQ4: 0.024 | BR4: 0.024 | BS4: =IF(COUNT(BS3,BS5)=2,IF(BS3=0,"",BS5/BS3),"") | BT4: 0.024 | BU4: 0.024 | BV4: =IF(COUNT(BV3,BV5)=2,IF(BV3=0,"",BV5/BV3),"") | BW4: 0.024 | BX4: 0.024 | BY4: =IF(COUNT(BY3,BY5)=2,IF(BY3=0,"",BY5/BY3),"") | BZ4: 0.024 | CA4: 0.024 | CB4: =IF(COUNT(CB3,CB5)=2,IF(CB3=0,"",CB5/CB3),"") | CC4: 0.024 | CD4: 0.024 | CE4: =IF(COUNT(CE3,CE5)=2,IF(CE3=0,"",CE5/CE3),"") | CF4: 0.024 | CG4: 0.024 | CH4: =IF(COUNT(CH3,CH5)=2,IF(CH3=0,"",CH5/CH3),"") | CI4: 0.024 | CJ4: 0.024 | CK4: =IF(COUNT(CK3,CK5)=2,IF(CK3=0,"",CK5/CK3),"") | CL4: 0.024 | CM4: 0.024 | CN4: =IF(COUNT(CN3,CN5)=2,IF(CN3=0,"",CN5/CN3),"") | CO4: 0.024 | CP4: 0.024 | CQ4: =IF(COUNT(CQ3,CQ5)=2,IF(CQ3=0,"",CQ5/CQ3),"") | CR4: 0.024 | CS4: 0.024 | CT4: =IF(COUNT(CT3,CT5)=2,IF(CT3=0,"",CT5/CT3),"") | CU4: 0.024 | CV4: 0.024 | CW4: =IF(COUNT(CW3,CW5)=2,IF(CW3=0,"",CW5/CW3),"") | CX4: 0.024 | CY4: 0.024 | CZ4: =IF(COUNT(CZ3,CZ5)=2,IF(CZ3=0,"",CZ5/CZ3),"") | DA4: 0.024 | DB4: 0.024 | DC4: =IF(COUNT(DC3,DC5)=2,IF(DC3=0,"",DC5/DC3),"") | DD4: 0.024 | DE4: 0.024 | DF4: =IF(COUNT(DF3,DF5)=2,IF(DF3=0,"",DF5/DF3),"") | DG4: 0.024 | DH4: 0.024 | DI4: =IF(COUNT(DI3,DI5)=2,IF(DI3=0,"",DI5/DI3),"") | DJ4: =DI4 | DK4: 0.024 | DL4: =IF(COUNT(DL3,DL5)=2,IF(DL3=0,"",DL5/DL3),"") | DM4: =DL4 | DN4: 0.024
A5: Marketing Qualified Leads | B5: =IF(COUNT(AR5,AO5,AL5,AI5,AF5,AC5,Z5,W5,T5,Q5,N5,K5)=0,"",SUM(AR5,AO5,AL5,AI5,AF5,AC5,Z5,W5,T5,Q5,N5,K5)) | C5: =IF(COUNT(AS5,AP5,AM5,AJ5,AG5,AD5,AA5,X5,U5,R5,O5,L5)=0,"",SUM(AS5,AP5,AM5,AJ5,AG5,AD5,AA5,X5,U5,R5,O5,L5)) | D5: =IF(COUNT(AT5,AQ5,AN5,AK5,AH5,AE5,AB5,Y5,V5,S5,P5,M5)=0,"",SUM(AT5,AQ5,AN5,AK5,AH5,AE5,AB5,Y5,V5,S5,P5,M5)) | E5: =IF(COUNT(CB5,BY5,BV5,BS5,BP5,BM5,BJ5,BG5,BD5,BA5,AX5,AU5)=0,"",SUM(CB5,BY5,BV5,BS5,BP5,BM5,BJ5,BG5,BD5,BA5,AX5,AU5)) | F5: =IF(COUNT(CC5,BZ5,BW5,BT5,BQ5,BN5,BK5,BH5,BE5,BB5,AY5,AV5)=0,"",SUM(CC5,BZ5,BW5,BT5,BQ5,BN5,BK5,BH5,BE5,BB5,AY5,AV5)) | G5: =IF(COUNT(CD5,CA5,BX5,BU5,BR5,BO5,BL5,BI5,BF5,BC5,AZ5,AW5)=0,"",SUM(CD5,CA5,BX5,BU5,BR5,BO5,BL5,BI5,BF5,BC5,AZ5,AW5)) | H5: =IF(COUNT(DL5,DI5,DF5,DC5,CZ5,CW5,CT5,CQ5,CN5,CK5,CH5,CE5)=0,"",SUM(DL5,DI5,DF5,DC5,CZ5,CW5,CT5,CQ5,CN5,CK5,CH5,CE5)) | I5: =IF(COUNT(DM5,DJ5,DG5,DD5,DA5,CX5,CU5,CR5,CO5,CL5,CI5,CF5)=0,"",SUM(DM5,DJ5,DG5,DD5,DA5,CX5,CU5,CR5,CO5,CL5,CI5,CF5)) | J5: =IF(COUNT(DN5,DK5,DH5,DE5,DB5,CY5,CV5,CS5,CP5,CM5,CJ5,CG5)=0,"",SUM(DN5,DK5,DH5,DE5,DB5,CY5,CV5,CS5,CP5,CM5,CJ5,CG5)) | L5: =ROUND(L3*L4,0) | M5: =ROUND(M3*M4,0) | O5: =ROUND(O3*O4,0) | P5: =ROUND(P3*P4,0) | R5: =ROUND(R3*R4,0) | S5: =ROUND(S3*S4,0) | U5: =ROUND(U3*U4,0) | V5: =ROUND(V3*V4,0) | X5: =ROUND(X3*X4,0) | Y5: =ROUND(Y3*Y4,0) | AA5: =ROUND(AA3*AA4,0) | AB5: =ROUND(AB3*AB4,0) | AD5: =ROUND(AD3*AD4,0) | AE5: =ROUND(AE3*AE4,0) | AG5: =ROUND(AG3*AG4,0) | AH5: =ROUND(AH3*AH4,0) | AJ5: =ROUND(AJ3*AJ4,0) | AK5: =ROUND(AK3*AK4,0) | AM5: =ROUND(AM3*AM4,0) | AN5: =ROUND(AN3*AN4,0) | AP5: =ROUND(AP3*AP4,0) | AQ5: =ROUND(AQ3*AQ4,0) | AS5: =ROUND(AS3*AS4,0) | AT5: =ROUND(AT3*AT4,0) | AV5: =ROUND(AV3*AV4,0) | AW5: =ROUND(AW3*AW4,0) | AY5: =ROUND(AY3*AY4,0) | AZ5: =ROUND(AZ3*AZ4,0) | BB5: =ROUND(BB3*BB4,0) | BC5: =ROUND(BC3*BC4,0) | BE5: =ROUND(BE3*BE4,0) | BF5: =ROUND(BF3*BF4,0) | BH5: =ROUND(BH3*BH4,0) | BI5: =ROUND(BI3*BI4,0) | BK5: =ROUND(BK3*BK4,0) | BL5: =ROUND(BL3*BL4,0) | BN5: =ROUND(BN3*BN4,0) | BO5: =ROUND(BO3*BO4,0) | BQ5: =ROUND(BQ3*BQ4,0) | BR5: =ROUND(BR3*BR4,0) | BT5: =ROUND(BT3*BT4,0) | BU5: =ROUND(BU3*BU4,0) | BW5: =ROUND(BW3*BW4,0) | BX5: =ROUND(BX3*BX4,0) | BZ5: =ROUND(BZ3*BZ4,0) | CA5: =ROUND(CA3*CA4,0) | CC5: =ROUND(CC3*CC4,0) | CD5: =ROUND(CD3*CD4,0) | CF5: =ROUND(CF3*CF4,0) | CG5: =ROUND(CG3*CG4,0) | CI5: =ROUND(CI3*CI4,0) | CJ5: =ROUND(CJ3*CJ4,0) | CL5: =ROUND(CL3*CL4,0) | CM5: =ROUND(CM3*CM4,0) | CO5: =ROUND(CO3*CO4,0) | CP5: =ROUND(CP3*CP4,0) | CR5: =ROUND(CR3*CR4,0) | CS5: =ROUND(CS3*CS4,0) | CU5: =ROUND(CU3*CU4,0) | CV5: =ROUND(CV3*CV4,0) | CX5: =ROUND(CX3*CX4,0) | CY5: =ROUND(CY3*CY4,0) | DA5: =ROUND(DA3*DA4,0) | DB5: =ROUND(DB3*DB4,0) | DD5: =ROUND(DD3*DD4,0) | DE5: =ROUND(DE3*DE4,0) | DG5: =ROUND(DG3*DG4,0) | DH5: =ROUND(DH3*DH4,0) | DI5: 120 | DJ5: =DI5 | DK5: =ROUND(DK3*DK4,0) | DL5: 122 | DM5: =DL5 | DN5: =ROUND(DN3*DN4,0)
A6: MQL Acceptance Rate | B6: =IF(SUM(AR5,AO5,AL5,AI5,AF5,AC5,Z5,W5,T5,Q5,N5,K5)=0,"",SUM(AR7,AO7,AL7,AI7,AF7,AC7,Z7,W7,T7,Q7,N7,K7)/SUM(AR5,AO5,AL5,AI5,AF5,AC5,Z5,W5,T5,Q5,N5,K5)) | C6: =IF(SUM(AS5,AP5,AM5,AJ5,AG5,AD5,AA5,X5,U5,R5,O5,L5)=0,"",SUM(AS7,AP7,AM7,AJ7,AG7,AD7,AA7,X7,U7,R7,O7,L7)/SUM(AS5,AP5,AM5,AJ5,AG5,AD5,AA5,X5,U5,R5,O5,L5)) | D6: =IF(SUM(AT5,AQ5,AN5,AK5,AH5,AE5,AB5,Y5,V5,S5,P5,M5)=0,"",SUM(AT7,AQ7,AN7,AK7,AH7,AE7,AB7,Y7,V7,S7,P7,M7)/SUM(AT5,AQ5,AN5,AK5,AH5,AE5,AB5,Y5,V5,S5,P5,M5)) | E6: =IF(SUM(CB5,BY5,BV5,BS5,BP5,BM5,BJ5,BG5,BD5,BA5,AX5,AU5)=0,"",SUM(CB7,BY7,BV7,BS7,BP7,BM7,BJ7,BG7,BD7,BA7,AX7,AU7)/SUM(CB5,BY5,BV5,BS5,BP5,BM5,BJ5,BG5,BD5,BA5,AX5,AU5)) | F6: =IF(SUM(CC5,BZ5,BW5,BT5,BQ5,BN5,BK5,BH5,BE5,BB5,AY5,AV5)=0,"",SUM(CC7,BZ7,BW7,BT7,BQ7,BN7,BK7,BH7,BE7,BB7,AY7,AV7)/SUM(CC5,BZ5,BW5,BT5,BQ5,BN5,BK5,BH5,BE5,BB5,AY5,AV5)) | G6: =IF(SUM(CD5,CA5,BX5,BU5,BR5,BO5,BL5,BI5,BF5,BC5,AZ5,AW5)=0,"",SUM(CD7,CA7,BX7,BU7,BR7,BO7,BL7,BI7,BF7,BC7,AZ7,AW7)/SUM(CD5,CA5,BX5,BU5,BR5,BO5,BL5,BI5,BF5,BC5,AZ5,AW5)) | H6: =IF(SUM(DL5,DI5,DF5,DC5,CZ5,CW5,CT5,CQ5,CN5,CK5,CH5,CE5)=0,"",SUM(DL7,DI7,DF7,DC7,CZ7,CW7,CT7,CQ7,CN7,CK7,CH7,CE7)/SUM(DL5,DI5,DF5,DC5,CZ5,CW5,CT5,CQ5,CN5,CK5,CH5,CE5)) | I6: =IF(SUM(DM5,DJ5,DG5,DD5,DA5,CX5,CU5,CR5,CO5,CL5,CI5,CF5)=0,"",SUM(DM7,DJ7,DG7,DD7,DA7,CX7,CU7,CR7,CO7,CL7,CI7,CF7)/SUM(DM5,DJ5,DG5,DD5,DA5,CX5,CU5,CR5,CO5,CL5,CI5,CF5)) | J6: =IF(SUM(DN5,DK5,DH5,DE5,DB5,CY5,CV5,CS5,CP5,CM5,CJ5,CG5)=0,"",SUM(DN7,DK7,DH7,DE7,DB7,CY7,CV7,CS7,CP7,CM7,CJ7,CG7)/SUM(DN5,DK5,DH5,DE5,DB5,CY5,CV5,CS5,CP5,CM5,CJ5,CG5)) | K6: =IF(COUNT(K5,K7)=2,IF(K5=0,"",K7/K5),"") | L6: 0.62 | M6: 0.62 | N6: =IF(COUNT(N5,N7)=2,IF(N5=0,"",N7/N5),"") | O6: 0.62 | P6: 0.62 | Q6: =IF(COUNT(Q5,Q7)=2,IF(Q5=0,"",Q7/Q5),"") | R6: 0.62 | S6: 0.62 | T6: =IF(COUNT(T5,T7)=2,IF(T5=0,"",T7/T5),"") | U6: 0.62 | V6: 0.62 | W6: =IF(COUNT(W5,W7)=2,IF(W5=0,"",W7/W5),"") | X6: 0.62 | Y6: 0.62 | Z6: =IF(COUNT(Z5,Z7)=2,IF(Z5=0,"",Z7/Z5),"") | AA6: 0.62 | AB6: 0.62 | AC6: =IF(COUNT(AC5,AC7)=2,IF(AC5=0,"",AC7/AC5),"") | AD6: 0.62 | AE6: 0.62 | AF6: =IF(COUNT(AF5,AF7)=2,IF(AF5=0,"",AF7/AF5),"") | AG6: 0.62 | AH6: 0.62 | AI6: =IF(COUNT(AI5,AI7)=2,IF(AI5=0,"",AI7/AI5),"") | AJ6: 0.62 | AK6: 0.62 | AL6: =IF(COUNT(AL5,AL7)=2,IF(AL5=0,"",AL7/AL5),"") | AM6: 0.62 | AN6: 0.62 | AO6: =IF(COUNT(AO5,AO7)=2,IF(AO5=0,"",AO7/AO5),"") | AP6: 0.62 | AQ6: 0.62 | AR6: =IF(COUNT(AR5,AR7)=2,IF(AR5=0,"",AR7/AR5),"") | AS6: 0.62 | AT6: 0.62 | AU6: =IF(COUNT(AU5,AU7)=2,IF(AU5=0,"",AU7/AU5),"") | AV6: 0.62 | AW6: 0.62 | AX6: =IF(COUNT(AX5,AX7)=2,IF(AX5=0,"",AX7/AX5),"") | AY6: 0.62 | AZ6: 0.62 | BA6: =IF(COUNT(BA5,BA7)=2,IF(BA5=0,"",BA7/BA5),"") | BB6: 0.62 | BC6: 0.62 | BD6: =IF(COUNT(BD5,BD7)=2,IF(BD5=0,"",BD7/BD5),"") | BE6: 0.62 | BF6: 0.62 | BG6: =IF(COUNT(BG5,BG7)=2,IF(BG5=0,"",BG7/BG5),"") | BH6: 0.62 | BI6: 0.62 | BJ6: =IF(COUNT(BJ5,BJ7)=2,IF(BJ5=0,"",BJ7/BJ5),"") | BK6: 0.62 | BL6: 0.62 | BM6: =IF(COUNT(BM5,BM7)=2,IF(BM5=0,"",BM7/BM5),"") | BN6: 0.62 | BO6: 0.62 | BP6: =IF(COUNT(BP5,BP7)=2,IF(BP5=0,"",BP7/BP5),"") | BQ6: 0.62 | BR6: 0.62 | BS6: =IF(COUNT(BS5,BS7)=2,IF(BS5=0,"",BS7/BS5),"") | BT6: 0.62 | BU6: 0.62 | BV6: =IF(COUNT(BV5,BV7)=2,IF(BV5=0,"",BV7/BV5),"") | BW6: 0.62 | BX6: 0.62 | BY6: =IF(COUNT(BY5,BY7)=2,IF(BY5=0,"",BY7/BY5),"") | BZ6: 0.62 | CA6: 0.62 | CB6: =IF(COUNT(CB5,CB7)=2,IF(CB5=0,"",CB7/CB5),"") | CC6: 0.62 | CD6: 0.62 | CE6: =IF(COUNT(CE5,CE7)=2,IF(CE5=0,"",CE7/CE5),"") | CF6: 0.62 | CG6: 0.62 | CH6: =IF(COUNT(CH5,CH7)=2,IF(CH5=0,"",CH7/CH5),"") | CI6: 0.62 | CJ6: 0.62 | CK6: =IF(COUNT(CK5,CK7)=2,IF(CK5=0,"",CK7/CK5),"") | CL6: 0.62 | CM6: 0.62 | CN6: =IF(COUNT(CN5,CN7)=2,IF(CN5=0,"",CN7/CN5),"") | CO6: 0.62 | CP6: 0.62 | CQ6: =IF(COUNT(CQ5,CQ7)=2,IF(CQ5=0,"",CQ7/CQ5),"") | CR6: 0.62 | CS6: 0.62 | CT6: =IF(COUNT(CT5,CT7)=2,IF(CT5=0,"",CT7/CT5),"") | CU6: 0.62 | CV6: 0.62 | CW6: =IF(COUNT(CW5,CW7)=2,IF(CW5=0,"",CW7/CW5),"") | CX6: 0.62 | CY6: 0.62 | CZ6: =IF(COUNT(CZ5,CZ7)=2,IF(CZ5=0,"",CZ7/CZ5),"") | DA6: 0.62 | DB6: 0.62 | DC6: =IF(COUNT(DC5,DC7)=2,IF(DC5=0,"",DC7/DC5),"") | DD6: 0.62 | DE6: 0.62 | DF6: =IF(COUNT(DF5,DF7)=2,IF(DF5=0,"",DF7/DF5),"") | DG6: 0.62 | DH6: 0.62 | DI6: =IF(COUNT(DI5,DI7)=2,IF(DI5=0,"",DI7/DI5),"") | DJ6: =DI6 | DK6: 0.62 | DL6: =IF(COUNT(DL5,DL7)=2,IF(DL5=0,"",DL7/DL5),"") | DM6: =DL6 | DN6: 0.62
A7: Sales Qualified Leads | B7: =IF(COUNT(AR7,AO7,AL7,AI7,AF7,AC7,Z7,W7,T7,Q7,N7,K7)=0,"",SUM(AR7,AO7,AL7,AI7,AF7,AC7,Z7,W7,T7,Q7,N7,K7)) | C7: =IF(COUNT(AS7,AP7,AM7,AJ7,AG7,AD7,AA7,X7,U7,R7,O7,L7)=0,"",SUM(AS7,AP7,AM7,AJ7,AG7,AD7,AA7,X7,U7,R7,O7,L7)) | D7: =IF(COUNT(AT7,AQ7,AN7,AK7,AH7,AE7,AB7,Y7,V7,S7,P7,M7)=0,"",SUM(AT7,AQ7,AN7,AK7,AH7,AE7,AB7,Y7,V7,S7,P7,M7)) | E7: =IF(COUNT(CB7,BY7,BV7,BS7,BP7,BM7,BJ7,BG7,BD7,BA7,AX7,AU7)=0,"",SUM(CB7,BY7,BV7,BS7,BP7,BM7,BJ7,BG7,BD7,BA7,AX7,AU7)) | F7: =IF(COUNT(CC7,BZ7,BW7,BT7,BQ7,BN7,BK7,BH7,BE7,BB7,AY7,AV7)=0,"",SUM(CC7,BZ7,BW7,BT7,BQ7,BN7,BK7,BH7,BE7,BB7,AY7,AV7)) | G7: =IF(COUNT(CD7,CA7,BX7,BU7,BR7,BO7,BL7,BI7,BF7,BC7,AZ7,AW7)=0,"",SUM(CD7,CA7,BX7,BU7,BR7,BO7,BL7,BI7,BF7,BC7,AZ7,AW7)) | H7: =IF(COUNT(DL7,DI7,DF7,DC7,CZ7,CW7,CT7,CQ7,CN7,CK7,CH7,CE7)=0,"",SUM(DL7,DI7,DF7,DC7,CZ7,CW7,CT7,CQ7,CN7,CK7,CH7,CE7)) | I7: =IF(COUNT(DM7,DJ7,DG7,DD7,DA7,CX7,CU7,CR7,CO7,CL7,CI7,CF7)=0,"",SUM(DM7,DJ7,DG7,DD7,DA7,CX7,CU7,CR7,CO7,CL7,CI7,CF7)) | J7: =IF(COUNT(DN7,DK7,DH7,DE7,DB7,CY7,CV7,CS7,CP7,CM7,CJ7,CG7)=0,"",SUM(DN7,DK7,DH7,DE7,DB7,CY7,CV7,CS7,CP7,CM7,CJ7,CG7)) | L7: =ROUND(L5*L6,0) | M7: =ROUND(M5*M6,0) | O7: =ROUND(O5*O6,0) | P7: =ROUND(P5*P6,0) | R7: =ROUND(R5*R6,0) | S7: =ROUND(S5*S6,0) | U7: =ROUND(U5*U6,0) | V7: =ROUND(V5*V6,0) | X7: =ROUND(X5*X6,0) | Y7: =ROUND(Y5*Y6,0) | AA7: =ROUND(AA5*AA6,0) | AB7: =ROUND(AB5*AB6,0) | AD7: =ROUND(AD5*AD6,0) | AE7: =ROUND(AE5*AE6,0) | AG7: =ROUND(AG5*AG6,0) | AH7: =ROUND(AH5*AH6,0) | AJ7: =ROUND(AJ5*AJ6,0) | AK7: =ROUND(AK5*AK6,0) | AM7: =ROUND(AM5*AM6,0) | AN7: =ROUND(AN5*AN6,0) | AP7: =ROUND(AP5*AP6,0) | AQ7: =ROUND(AQ5*AQ6,0) | AS7: =ROUND(AS5*AS6,0) | AT7: =ROUND(AT5*AT6,0) | AV7: =ROUND(AV5*AV6,0) | AW7: =ROUND(AW5*AW6,0) | AY7: =ROUND(AY5*AY6,0) | AZ7: =ROUND(AZ5*AZ6,0) | BB7: =ROUND(BB5*BB6,0) | BC7: =ROUND(BC5*BC6,0) | BE7: =ROUND(BE5*BE6,0) | BF7: =ROUND(BF5*BF6,0) | BH7: =ROUND(BH5*BH6,0) | BI7: =ROUND(BI5*BI6,0) | BK7: =ROUND(BK5*BK6,0) | BL7: =ROUND(BL5*BL6,0) | BN7: =ROUND(BN5*BN6,0) | BO7: =ROUND(BO5*BO6,0) | BQ7: =ROUND(BQ5*BQ6,0) | BR7: =ROUND(BR5*BR6,0) | BT7: =ROUND(BT5*BT6,0) | BU7: =ROUND(BU5*BU6,0) | BW7: =ROUND(BW5*BW6,0) | BX7: =ROUND(BX5*BX6,0) | BZ7: =ROUND(BZ5*BZ6,0) | CA7: =ROUND(CA5*CA6,0) | CC7: =ROUND(CC5*CC6,0) | CD7: =ROUND(CD5*CD6,0) | CF7: =ROUND(CF5*CF6,0) | CG7: =ROUND(CG5*CG6,0) | CI7: =ROUND(CI5*CI6,0) | CJ7: =ROUND(CJ5*CJ6,0) | CL7: =ROUND(CL5*CL6,0) | CM7: =ROUND(CM5*CM6,0) | CO7: =ROUND(CO5*CO6,0) | CP7: =ROUND(CP5*CP6,0) | CR7: =ROUND(CR5*CR6,0) | CS7: =ROUND(CS5*CS6,0) | CU7: =ROUND(CU5*CU6,0) | CV7: =ROUND(CV5*CV6,0) | CX7: =ROUND(CX5*CX6,0) | CY7: =ROUND(CY5*CY6,0) | DA7: =ROUND(DA5*DA6,0) | DB7: =ROUND(DB5*DB6,0) | DD7: =ROUND(DD5*DD6,0) | DE7: =ROUND(DE5*DE6,0) | DG7: =ROUND(DG5*DG6,0) | DH7: =ROUND(DH5*DH6,0) | DI7: 74 | DJ7: =DI7 | DK7: =ROUND(DK5*DK6,0) | DL7: 76 | DM7: =DL7 | DN7: =ROUND(DN5*DN6,0)
A8: Salaries and Wages | B8: =IF(COUNT(AR8,AO8,AL8,AI8,AF8,AC8,Z8,W8,T8,Q8,N8,K8)=0,"",SUM(AR8,AO8,AL8,AI8,AF8,AC8,Z8,W8,T8,Q8,N8,K8)) | C8: =IF(COUNT(AS8,AP8,AM8,AJ8,AG8,AD8,AA8,X8,U8,R8,O8,L8)=0,"",SUM(AS8,AP8,AM8,AJ8,AG8,AD8,AA8,X8,U8,R8,O8,L8)) | D8: =IF(COUNT(AT8,AQ8,AN8,AK8,AH8,AE8,AB8,Y8,V8,S8,P8,M8)=0,"",SUM(AT8,AQ8,AN8,AK8,AH8,AE8,AB8,Y8,V8,S8,P8,M8)) | E8: =IF(COUNT(CB8,BY8,BV8,BS8,BP8,BM8,BJ8,BG8,BD8,BA8,AX8,AU8)=0,"",SUM(CB8,BY8,BV8,BS8,BP8,BM8,BJ8,BG8,BD8,BA8,AX8,AU8)) | F8: =IF(COUNT(CC8,BZ8,BW8,BT8,BQ8,BN8,BK8,BH8,BE8,BB8,AY8,AV8)=0,"",SUM(CC8,BZ8,BW8,BT8,BQ8,BN8,BK8,BH8,BE8,BB8,AY8,AV8)) | G8: =IF(COUNT(CD8,CA8,BX8,BU8,BR8,BO8,BL8,BI8,BF8,BC8,AZ8,AW8)=0,"",SUM(CD8,CA8,BX8,BU8,BR8,BO8,BL8,BI8,BF8,BC8,AZ8,AW8)) | H8: =IF(COUNT(DL8,DI8,DF8,DC8,CZ8,CW8,CT8,CQ8,CN8,CK8,CH8,CE8)=0,"",SUM(DL8,DI8,DF8,DC8,CZ8,CW8,CT8,CQ8,CN8,CK8,CH8,CE8)) | I8: =IF(COUNT(DM8,DJ8,DG8,DD8,DA8,CX8,CU8,CR8,CO8,CL8,CI8,CF8)=0,"",SUM(DM8,DJ8,DG8,DD8,DA8,CX8,CU8,CR8,CO8,CL8,CI8,CF8)) | J8: =IF(COUNT(DN8,DK8,DH8,DE8,DB8,CY8,CV8,CS8,CP8,CM8,CJ8,CG8)=0,"",SUM(DN8,DK8,DH8,DE8,DB8,CY8,CV8,CS8,CP8,CM8,CJ8,CG8)) | K8: =IF(COUNT(K38)=1,K38,"") | L8: =L38 | M8: =M38 | N8: =IF(COUNT(N38)=1,N38,"") | O8: =O38 | P8: =P38 | Q8: =IF(COUNT(Q38)=1,Q38,"") | R8: =R38 | S8: =S38 | T8: =IF(COUNT(T38)=1,T38,"") | U8: =U38 | V8: =V38 | W8: =IF(COUNT(W38)=1,W38,"") | X8: =X38 | Y8: =Y38 | Z8: =IF(COUNT(Z38)=1,Z38,"") | AA8: =AA38 | AB8: =AB38 | AC8: =IF(COUNT(AC38)=1,AC38,"") | AD8: =AD38 | AE8: =AE38 | AF8: =IF(COUNT(AF38)=1,AF38,"") | AG8: =AG38 | AH8: =AH38 | AI8: =IF(COUNT(AI38)=1,AI38,"") | AJ8: =AJ38 | AK8: =AK38 | AL8: =IF(COUNT(AL38)=1,AL38,"") | AM8: =AM38 | AN8: =AN38 | AO8: =IF(COUNT(AO38)=1,AO38,"") | AP8: =AP38 | AQ8: =AQ38 | AR8: =IF(COUNT(AR38)=1,AR38,"") | AS8: =AS38 | AT8: =AT38 | AU8: =IF(COUNT(AU38)=1,AU38,"") | AV8: =AV38 | AW8: =AW38 | AX8: =IF(COUNT(AX38)=1,AX38,"") | AY8: =AY38 | AZ8: =AZ38 | BA8: =IF(COUNT(BA38)=1,BA38,"") | BB8: =BB38 | BC8: =BC38 | BD8: =IF(COUNT(BD38)=1,BD38,"") | BE8: =BE38 | BF8: =BF38 | BG8: =IF(COUNT(BG38)=1,BG38,"") | BH8: =BH38 | BI8: =BI38 | BJ8: =IF(COUNT(BJ38)=1,BJ38,"") | BK8: =BK38 | BL8: =BL38 | BM8: =IF(COUNT(BM38)=1,BM38,"") | BN8: =BN38 | BO8: =BO38 | BP8: =IF(COUNT(BP38)=1,BP38,"") | BQ8: =BQ38 | BR8: =BR38 | BS8: =IF(COUNT(BS38)=1,BS38,"") | BT8: =BT38 | BU8: =BU38 | BV8: =IF(COUNT(BV38)=1,BV38,"") | BW8: =BW38 | BX8: =BX38 | BY8: =IF(COUNT(BY38)=1,BY38,"") | BZ8: =BZ38 | CA8: =CA38 | CB8: =IF(COUNT(CB38)=1,CB38,"") | CC8: =CC38 | CD8: =CD38 | CE8: =IF(COUNT(CE38)=1,CE38,"") | CF8: =CF38 | CG8: =CG38 | CH8: =IF(COUNT(CH38)=1,CH38,"") | CI8: =CI38 | CJ8: =CJ38 | CK8: =IF(COUNT(CK38)=1,CK38,"") | CL8: =CL38 | CM8: =CM38 | CN8: =IF(COUNT(CN38)=1,CN38,"") | CO8: =CO38 | CP8: =CP38 | CQ8: =IF(COUNT(CQ38)=1,CQ38,"") | CR8: =CR38 | CS8: =CS38 | CT8: =IF(COUNT(CT38)=1,CT38,"") | CU8: =CU38 | CV8: =CV38 | CW8: =IF(COUNT(CW38)=1,CW38,"") | CX8: =CX38 | CY8: =CY38 | CZ8: =IF(COUNT(CZ38)=1,CZ38,"") | DA8: =DA38 | DB8: =DB38 | DC8: =IF(COUNT(DC38)=1,DC38,"") | DD8: =DD38 | DE8: =DE38 | DF8: =IF(COUNT(DF38)=1,DF38,"") | DG8: =DG38 | DH8: =DH38 | DI8: =IF(COUNT(DI38)=1,DI38,"") | DJ8: =DJ38 | DK8: =DK38 | DL8: =IF(COUNT(DL38)=1,DL38,"") | DM8: =DM38 | DN8: =DN38
A9: Bonuses | B9: =IF(COUNT(AR9,AO9,AL9,AI9,AF9,AC9,Z9,W9,T9,Q9,N9,K9)=0,"",SUM(AR9,AO9,AL9,AI9,AF9,AC9,Z9,W9,T9,Q9,N9,K9)) | C9: =IF(COUNT(AS9,AP9,AM9,AJ9,AG9,AD9,AA9,X9,U9,R9,O9,L9)=0,"",SUM(AS9,AP9,AM9,AJ9,AG9,AD9,AA9,X9,U9,R9,O9,L9)) | D9: =IF(COUNT(AT9,AQ9,AN9,AK9,AH9,AE9,AB9,Y9,V9,S9,P9,M9)=0,"",SUM(AT9,AQ9,AN9,AK9,AH9,AE9,AB9,Y9,V9,S9,P9,M9)) | E9: =IF(COUNT(CB9,BY9,BV9,BS9,BP9,BM9,BJ9,BG9,BD9,BA9,AX9,AU9)=0,"",SUM(CB9,BY9,BV9,BS9,BP9,BM9,BJ9,BG9,BD9,BA9,AX9,AU9)) | F9: =IF(COUNT(CC9,BZ9,BW9,BT9,BQ9,BN9,BK9,BH9,BE9,BB9,AY9,AV9)=0,"",SUM(CC9,BZ9,BW9,BT9,BQ9,BN9,BK9,BH9,BE9,BB9,AY9,AV9)) | G9: =IF(COUNT(CD9,CA9,BX9,BU9,BR9,BO9,BL9,BI9,BF9,BC9,AZ9,AW9)=0,"",SUM(CD9,CA9,BX9,BU9,BR9,BO9,BL9,BI9,BF9,BC9,AZ9,AW9)) | H9: =IF(COUNT(DL9,DI9,DF9,DC9,CZ9,CW9,CT9,CQ9,CN9,CK9,CH9,CE9)=0,"",SUM(DL9,DI9,DF9,DC9,CZ9,CW9,CT9,CQ9,CN9,CK9,CH9,CE9)) | I9: =IF(COUNT(DM9,DJ9,DG9,DD9,DA9,CX9,CU9,CR9,CO9,CL9,CI9,CF9)=0,"",SUM(DM9,DJ9,DG9,DD9,DA9,CX9,CU9,CR9,CO9,CL9,CI9,CF9)) | J9: =IF(COUNT(DN9,DK9,DH9,DE9,DB9,CY9,CV9,CS9,CP9,CM9,CJ9,CG9)=0,"",SUM(DN9,DK9,DH9,DE9,DB9,CY9,CV9,CS9,CP9,CM9,CJ9,CG9)) | L9: 2000 | M9: 2000 | O9: 2000 | P9: 2000 | R9: 2000 | S9: 2000 | U9: 2000 | V9: 2000 | X9: 2000 | Y9: 2000 | AA9: 2000 | AB9: 2000 | AD9: 2000 | AE9: 2000 | AG9: 2000 | AH9: 2000 | AJ9: 2000 | AK9: 2000 | AM9: 2000 | AN9: 2000 | AP9: 2000 | AQ9: 2000 | AS9: 2000 | AT9: 2000 | AV9: 2000 | AW9: 2000 | AY9: 2000 | AZ9: 2000 | BB9: 2000 | BC9: 2000 | BE9: 2000 | BF9: 2000 | BH9: 2000 | BI9: 2000 | BK9: 2000 | BL9: 2000 | BN9: 2000 | BO9: 2000 | BQ9: 2000 | BR9: 2000 | BT9: 2000 | BU9: 2000 | BW9: 2000 | BX9: 2000 | BZ9: 2000 | CA9: 2000 | CC9: 2000 | CD9: 2000 | CF9: 2000 | CG9: 2000 | CI9: 2000 | CJ9: 2000 | CL9: 2000 | CM9: 2000 | CO9: 2000 | CP9: 2000 | CR9: 2000 | CS9: 2000 | CU9: 2000 | CV9: 2000 | CX9: 2000 | CY9: 2000 | DA9: 2000 | DB9: 2000 | DD9: 2000 | DE9: 2000 | DG9: 2000 | DH9: 2000 | DI9: 2000 | DJ9: 2000 | DK9: 2000 | DL9: 2000 | DM9: 2000 | DN9: 2000
A10: Payroll Taxes and Benefits | B10: =IF(COUNT(AR10,AO10,AL10,AI10,AF10,AC10,Z10,W10,T10,Q10,N10,K10)=0,"",SUM(AR10,AO10,AL10,AI10,AF10,AC10,Z10,W10,T10,Q10,N10,K10)) | C10: =IF(COUNT(AS10,AP10,AM10,AJ10,AG10,AD10,AA10,X10,U10,R10,O10,L10)=0,"",SUM(AS10,AP10,AM10,AJ10,AG10,AD10,AA10,X10,U10,R10,O10,L10)) | D10: =IF(COUNT(AT10,AQ10,AN10,AK10,AH10,AE10,AB10,Y10,V10,S10,P10,M10)=0,"",SUM(AT10,AQ10,AN10,AK10,AH10,AE10,AB10,Y10,V10,S10,P10,M10)) | E10: =IF(COUNT(CB10,BY10,BV10,BS10,BP10,BM10,BJ10,BG10,BD10,BA10,AX10,AU10)=0,"",SUM(CB10,BY10,BV10,BS10,BP10,BM10,BJ10,BG10,BD10,BA10,AX10,AU10)) | F10: =IF(COUNT(CC10,BZ10,BW10,BT10,BQ10,BN10,BK10,BH10,BE10,BB10,AY10,AV10)=0,"",SUM(CC10,BZ10,BW10,BT10,BQ10,BN10,BK10,BH10,BE10,BB10,AY10,AV10)) | G10: =IF(COUNT(CD10,CA10,BX10,BU10,BR10,BO10,BL10,BI10,BF10,BC10,AZ10,AW10)=0,"",SUM(CD10,CA10,BX10,BU10,BR10,BO10,BL10,BI10,BF10,BC10,AZ10,AW10)) | H10: =IF(COUNT(DL10,DI10,DF10,DC10,CZ10,CW10,CT10,CQ10,CN10,CK10,CH10,CE10)=0,"",SUM(DL10,DI10,DF10,DC10,CZ10,CW10,CT10,CQ10,CN10,CK10,CH10,CE10)) | I10: =IF(COUNT(DM10,DJ10,DG10,DD10,DA10,CX10,CU10,CR10,CO10,CL10,CI10,CF10)=0,"",SUM(DM10,DJ10,DG10,DD10,DA10,CX10,CU10,CR10,CO10,CL10,CI10,CF10)) | J10: =IF(COUNT(DN10,DK10,DH10,DE10,DB10,CY10,CV10,CS10,CP10,CM10,CJ10,CG10)=0,"",SUM(DN10,DK10,DH10,DE10,DB10,CY10,CV10,CS10,CP10,CM10,CJ10,CG10)) | K10: =IF(COUNT(K8)=1,K8*0.22,"") | L10: =L8*0.22 | M10: =M8*0.22 | N10: =IF(COUNT(N8)=1,N8*0.22,"") | O10: =O8*0.22 | P10: =P8*0.22 | Q10: =IF(COUNT(Q8)=1,Q8*0.22,"") | R10: =R8*0.22 | S10: =S8*0.22 | T10: =IF(COUNT(T8)=1,T8*0.22,"") | U10: =U8*0.22 | V10: =V8*0.22 | W10: =IF(COUNT(W8)=1,W8*0.22,"") | X10: =X8*0.22 | Y10: =Y8*0.22 | Z10: =IF(COUNT(Z8)=1,Z8*0.22,"") | AA10: =AA8*0.22 | AB10: =AB8*0.22 | AC10: =IF(COUNT(AC8)=1,AC8*0.22,"") | AD10: =AD8*0.22 | AE10: =AE8*0.22 | AF10: =IF(COUNT(AF8)=1,AF8*0.22,"") | AG10: =AG8*0.22 | AH10: =AH8*0.22 | AI10: =IF(COUNT(AI8)=1,AI8*0.22,"") | AJ10: =AJ8*0.22 | AK10: =AK8*0.22 | AL10: =IF(COUNT(AL8)=1,AL8*0.22,"") | AM10: =AM8*0.22 | AN10: =AN8*0.22 | AO10: =IF(COUNT(AO8)=1,AO8*0.22,"") | AP10: =AP8*0.22 | AQ10: =AQ8*0.22 | AR10: =IF(COUNT(AR8)=1,AR8*0.22,"") | AS10: =AS8*0.22 | AT10: =AT8*0.22 | AU10: =IF(COUNT(AU8)=1,AU8*0.22,"") | AV10: =AV8*0.22 | AW10: =AW8*0.22 | AX10: =IF(COUNT(AX8)=1,AX8*0.22,"") | AY10: =AY8*0.22 | AZ10: =AZ8*0.22 | BA10: =IF(COUNT(BA8)=1,BA8*0.22,"") | BB10: =BB8*0.22 | BC10: =BC8*0.22 | BD10: =IF(COUNT(BD8)=1,BD8*0.22,"") | BE10: =BE8*0.22 | BF10: =BF8*0.22 | BG10: =IF(COUNT(BG8)=1,BG8*0.22,"") | BH10: =BH8*0.22 | BI10: =BI8*0.22 | BJ10: =IF(COUNT(BJ8)=1,BJ8*0.22,"") | BK10: =BK8*0.22 | BL10: =BL8*0.22 | BM10: =IF(COUNT(BM8)=1,BM8*0.22,"") | BN10: =BN8*0.22 | BO10: =BO8*0.22 | BP10: =IF(COUNT(BP8)=1,BP8*0.22,"") | BQ10: =BQ8*0.22 | BR10: =BR8*0.22 | BS10: =IF(COUNT(BS8)=1,BS8*0.22,"") | BT10: =BT8*0.22 | BU10: =BU8*0.22 | BV10: =IF(COUNT(BV8)=1,BV8*0.22,"") | BW10: =BW8*0.22 | BX10: =BX8*0.22 | BY10: =IF(COUNT(BY8)=1,BY8*0.22,"") | BZ10: =BZ8*0.22 | CA10: =CA8*0.22 | CB10: =IF(COUNT(CB8)=1,CB8*0.22,"") | CC10: =CC8*0.22 | CD10: =CD8*0.22 | CE10: =IF(COUNT(CE8)=1,CE8*0.22,"") | CF10: =CF8*0.22 | CG10: =CG8*0.22 | CH10: =IF(COUNT(CH8)=1,CH8*0.22,"") | CI10: =CI8*0.22 | CJ10: =CJ8*0.22 | CK10: =IF(COUNT(CK8)=1,CK8*0.22,"") | CL10: =CL8*0.22 | CM10: =CM8*0.22 | CN10: =IF(COUNT(CN8)=1,CN8*0.22,"") | CO10: =CO8*0.22 | CP10: =CP8*0.22 | CQ10: =IF(COUNT(CQ8)=1,CQ8*0.22,"") | CR10: =CR8*0.22 | CS10: =CS8*0.22 | CT10: =IF(COUNT(CT8)=1,CT8*0.22,"") | CU10: =CU8*0.22 | CV10: =CV8*0.22 | CW10: =IF(COUNT(CW8)=1,CW8*0.22,"") | CX10: =CX8*0.22 | CY10: =CY8*0.22 | CZ10: =IF(COUNT(CZ8)=1,CZ8*0.22,"") | DA10: =DA8*0.22 | DB10: =DB8*0.22 | DC10: =IF(COUNT(DC8)=1,DC8*0.22,"") | DD10: =DD8*0.22 | DE10: =DE8*0.22 | DF10: =IF(COUNT(DF8)=1,DF8*0.22,"") | DG10: =DG8*0.22 | DH10: =DH8*0.22 | DI10: =IF(COUNT(DI8)=1,DI8*0.22,"") | DJ10: =DJ8*0.22 | DK10: =DK8*0.22 | DL10: =IF(COUNT(DL8)=1,DL8*0.22,"") | DM10: =DM8*0.22 | DN10: =DN8*0.22
A11: Contractors and Freelancers | B11: =IF(COUNT(AR11,AO11,AL11,AI11,AF11,AC11,Z11,W11,T11,Q11,N11,K11)=0,"",SUM(AR11,AO11,AL11,AI11,AF11,AC11,Z11,W11,T11,Q11,N11,K11)) | C11: =IF(COUNT(AS11,AP11,AM11,AJ11,AG11,AD11,AA11,X11,U11,R11,O11,L11)=0,"",SUM(AS11,AP11,AM11,AJ11,AG11,AD11,AA11,X11,U11,R11,O11,L11)) | D11: =IF(COUNT(AT11,AQ11,AN11,AK11,AH11,AE11,AB11,Y11,V11,S11,P11,M11)=0,"",SUM(AT11,AQ11,AN11,AK11,AH11,AE11,AB11,Y11,V11,S11,P11,M11)) | E11: =IF(COUNT(CB11,BY11,BV11,BS11,BP11,BM11,BJ11,BG11,BD11,BA11,AX11,AU11)=0,"",SUM(CB11,BY11,BV11,BS11,BP11,BM11,BJ11,BG11,BD11,BA11,AX11,AU11)) | F11: =IF(COUNT(CC11,BZ11,BW11,BT11,BQ11,BN11,BK11,BH11,BE11,BB11,AY11,AV11)=0,"",SUM(CC11,BZ11,BW11,BT11,BQ11,BN11,BK11,BH11,BE11,BB11,AY11,AV11)) | G11: =IF(COUNT(CD11,CA11,BX11,BU11,BR11,BO11,BL11,BI11,BF11,BC11,AZ11,AW11)=0,"",SUM(CD11,CA11,BX11,BU11,BR11,BO11,BL11,BI11,BF11,BC11,AZ11,AW11)) | H11: =IF(COUNT(DL11,DI11,DF11,DC11,CZ11,CW11,CT11,CQ11,CN11,CK11,CH11,CE11)=0,"",SUM(DL11,DI11,DF11,DC11,CZ11,CW11,CT11,CQ11,CN11,CK11,CH11,CE11)) | I11: =IF(COUNT(DM11,DJ11,DG11,DD11,DA11,CX11,CU11,CR11,CO11,CL11,CI11,CF11)=0,"",SUM(DM11,DJ11,DG11,DD11,DA11,CX11,CU11,CR11,CO11,CL11,CI11,CF11)) | J11: =IF(COUNT(DN11,DK11,DH11,DE11,DB11,CY11,CV11,CS11,CP11,CM11,CJ11,CG11)=0,"",SUM(DN11,DK11,DH11,DE11,DB11,CY11,CV11,CS11,CP11,CM11,CJ11,CG11)) | L11: 3000 | M11: 3000 | O11: 3000 | P11: 3000 | R11: 3000 | S11: 3000 | U11: 3000 | V11: 3000 | X11: 3000 | Y11: 3000 | AA11: 3000 | AB11: 3000 | AD11: 3000 | AE11: 3000 | AG11: 3000 | AH11: 3000 | AJ11: 3000 | AK11: 3000 | AM11: 3000 | AN11: 3000 | AP11: 3000 | AQ11: 3000 | AS11: 3000 | AT11: 3000 | AV11: 3000 | AW11: 3000 | AY11: 3000 | AZ11: 3000 | BB11: 3000 | BC11: 3000 | BE11: 3000 | BF11: 3000 | BH11: 3000 | BI11: 3000 | BK11: 3000 | BL11: 3000 | BN11: 3000 | BO11: 3000 | BQ11: 3000 | BR11: 3000 | BT11: 3000 | BU11: 3000 | BW11: 3000 | BX11: 3000 | BZ11: 3000 | CA11: 3000 | CC11: 3000 | CD11: 3000 | CF11: 3000 | CG11: 3000 | CI11: 3000 | CJ11: 3000 | CL11: 3000 | CM11: 3000 | CO11: 3000 | CP11: 3000 | CR11: 3000 | CS11: 3000 | CU11: 3000 | CV11: 3000 | CX11: 3000 | CY11: 3000 | DA11: 3000 | DB11: 3000 | DD11: 3000 | DE11: 3000 | DG11: 3000 | DH11: 3000 | DI11: 3000 | DJ11: 3000 | DK11: 3000 | DL11: 3000 | DM11: 3000 | DN11: 3000
A12: Recruiting | B12: =IF(COUNT(AR12,AO12,AL12,AI12,AF12,AC12,Z12,W12,T12,Q12,N12,K12)=0,"",SUM(AR12,AO12,AL12,AI12,AF12,AC12,Z12,W12,T12,Q12,N12,K12)) | C12: =IF(COUNT(AS12,AP12,AM12,AJ12,AG12,AD12,AA12,X12,U12,R12,O12,L12)=0,"",SUM(AS12,AP12,AM12,AJ12,AG12,AD12,AA12,X12,U12,R12,O12,L12)) | D12: =IF(COUNT(AT12,AQ12,AN12,AK12,AH12,AE12,AB12,Y12,V12,S12,P12,M12)=0,"",SUM(AT12,AQ12,AN12,AK12,AH12,AE12,AB12,Y12,V12,S12,P12,M12)) | E12: =IF(COUNT(CB12,BY12,BV12,BS12,BP12,BM12,BJ12,BG12,BD12,BA12,AX12,AU12)=0,"",SUM(CB12,BY12,BV12,BS12,BP12,BM12,BJ12,BG12,BD12,BA12,AX12,AU12)) | F12: =IF(COUNT(CC12,BZ12,BW12,BT12,BQ12,BN12,BK12,BH12,BE12,BB12,AY12,AV12)=0,"",SUM(CC12,BZ12,BW12,BT12,BQ12,BN12,BK12,BH12,BE12,BB12,AY12,AV12)) | G12: =IF(COUNT(CD12,CA12,BX12,BU12,BR12,BO12,BL12,BI12,BF12,BC12,AZ12,AW12)=0,"",SUM(CD12,CA12,BX12,BU12,BR12,BO12,BL12,BI12,BF12,BC12,AZ12,AW12)) | H12: =IF(COUNT(DL12,DI12,DF12,DC12,CZ12,CW12,CT12,CQ12,CN12,CK12,CH12,CE12)=0,"",SUM(DL12,DI12,DF12,DC12,CZ12,CW12,CT12,CQ12,CN12,CK12,CH12,CE12)) | I12: =IF(COUNT(DM12,DJ12,DG12,DD12,DA12,CX12,CU12,CR12,CO12,CL12,CI12,CF12)=0,"",SUM(DM12,DJ12,DG12,DD12,DA12,CX12,CU12,CR12,CO12,CL12,CI12,CF12)) | J12: =IF(COUNT(DN12,DK12,DH12,DE12,DB12,CY12,CV12,CS12,CP12,CM12,CJ12,CG12)=0,"",SUM(DN12,DK12,DH12,DE12,DB12,CY12,CV12,CS12,CP12,CM12,CJ12,CG12)) | L12: 500 | M12: 500 | O12: 500 | P12: 500 | R12: 500 | S12: 500 | U12: 500 | V12: 500 | X12: 500 | Y12: 500 | AA12: 500 | AB12: 500 | AD12: 500 | AE12: 500 | AG12: 500 | AH12: 500 | AJ12: 500 | AK12: 500 | AM12: 500 | AN12: 500 | AP12: 500 | AQ12: 500 | AS12: 500 | AT12: 500 | AV12: 500 | AW12: 500 | AY12: 500 | AZ12: 500 | BB12: 500 | BC12: 500 | BE12: 500 | BF12: 500 | BH12: 500 | BI12: 500 | BK12: 500 | BL12: 500 | BN12: 500 | BO12: 500 | BQ12: 500 | BR12: 500 | BT12: 500 | BU12: 500 | BW12: 500 | BX12: 500 | BZ12: 500 | CA12: 500 | CC12: 500 | CD12: 500 | CF12: 500 | CG12: 500 | CI12: 500 | CJ12: 500 | CL12: 500 | CM12: 500 | CO12: 500 | CP12: 500 | CR12: 500 | CS12: 500 | CU12: 500 | CV12: 500 | CX12: 500 | CY12: 500 | DA12: 500 | DB12: 500 | DD12: 500 | DE12: 500 | DG12: 500 | DH12: 500 | DI12: 500 | DJ12: 500 | DK12: 500 | DL12: 500 | DM12: 500 | DN12: 500
A13: Training and Development | B13: =IF(COUNT(AR13,AO13,AL13,AI13,AF13,AC13,Z13,W13,T13,Q13,N13,K13)=0,"",SUM(AR13,AO13,AL13,AI13,AF13,AC13,Z13,W13,T13,Q13,N13,K13)) | C13: =IF(COUNT(AS13,AP13,AM13,AJ13,AG13,AD13,AA13,X13,U13,R13,O13,L13)=0,"",SUM(AS13,AP13,AM13,AJ13,AG13,AD13,AA13,X13,U13,R13,O13,L13)) | D13: =IF(COUNT(AT13,AQ13,AN13,AK13,AH13,AE13,AB13,Y13,V13,S13,P13,M13)=0,"",SUM(AT13,AQ13,AN13,AK13,AH13,AE13,AB13,Y13,V13,S13,P13,M13)) | E13: =IF(COUNT(CB13,BY13,BV13,BS13,BP13,BM13,BJ13,BG13,BD13,BA13,AX13,AU13)=0,"",SUM(CB13,BY13,BV13,BS13,BP13,BM13,BJ13,BG13,BD13,BA13,AX13,AU13)) | F13: =IF(COUNT(CC13,BZ13,BW13,BT13,BQ13,BN13,BK13,BH13,BE13,BB13,AY13,AV13)=0,"",SUM(CC13,BZ13,BW13,BT13,BQ13,BN13,BK13,BH13,BE13,BB13,AY13,AV13)) | G13: =IF(COUNT(CD13,CA13,BX13,BU13,BR13,BO13,BL13,BI13,BF13,BC13,AZ13,AW13)=0,"",SUM(CD13,CA13,BX13,BU13,BR13,BO13,BL13,BI13,BF13,BC13,AZ13,AW13)) | H13: =IF(COUNT(DL13,DI13,DF13,DC13,CZ13,CW13,CT13,CQ13,CN13,CK13,CH13,CE13)=0,"",SUM(DL13,DI13,DF13,DC13,CZ13,CW13,CT13,CQ13,CN13,CK13,CH13,CE13)) | I13: =IF(COUNT(DM13,DJ13,DG13,DD13,DA13,CX13,CU13,CR13,CO13,CL13,CI13,CF13)=0,"",SUM(DM13,DJ13,DG13,DD13,DA13,CX13,CU13,CR13,CO13,CL13,CI13,CF13)) | J13: =IF(COUNT(DN13,DK13,DH13,DE13,DB13,CY13,CV13,CS13,CP13,CM13,CJ13,CG13)=0,"",SUM(DN13,DK13,DH13,DE13,DB13,CY13,CV13,CS13,CP13,CM13,CJ13,CG13)) | L13: 500 | M13: 500 | O13: 500 | P13: 500 | R13: 500 | S13: 500 | U13: 500 | V13: 500 | X13: 500 | Y13: 500 | AA13: 500 | AB13: 500 | AD13: 500 | AE13: 500 | AG13: 500 | AH13: 500 | AJ13: 500 | AK13: 500 | AM13: 500 | AN13: 500 | AP13: 500 | AQ13: 500 | AS13: 500 | AT13: 500 | AV13: 500 | AW13: 500 | AY13: 500 | AZ13: 500 | BB13: 500 | BC13: 500 | BE13: 500 | BF13: 500 | BH13: 500 | BI13: 500 | BK13: 500 | BL13: 500 | BN13: 500 | BO13: 500 | BQ13: 500 | BR13: 500 | BT13: 500 | BU13: 500 | BW13: 500 | BX13: 500 | BZ13: 500 | CA13: 500 | CC13: 500 | CD13: 500 | CF13: 500 | CG13: 500 | CI13: 500 | CJ13: 500 | CL13: 500 | CM13: 500 | CO13: 500 | CP13: 500 | CR13: 500 | CS13: 500 | CU13: 500 | CV13: 500 | CX13: 500 | CY13: 500 | DA13: 500 | DB13: 500 | DD13: 500 | DE13: 500 | DG13: 500 | DH13: 500 | DI13: 500 | DJ13: 500 | DK13: 500 | DL13: 500 | DM13: 500 | DN13: 500
